Workbook
Name _13省当月点对点用户到达数_户81: '[1]#REF'!$A$206
Name _13省当月点对点用户净增数_户82: '[1]#REF'!$A$222
Name _13省点对点用户累计净增数_户83: '[1]#REF'!$A$238
Name AAA: '[1]#REF'!#REF!
Name ABC: '[1]#REF'!$A$302
Name bcd: '[1]#REF'!#REF!
Name efg: '[1]#REF'!#REF!
Name GPRS业务登记用户到达数: '[1]#REF'!$A$643
Name GPRS业务登记用户到达数免费用户: '[1]#REF'!$A$647
Name GPRS业务累计使用量: '[1]#REF'!$A$663
Name GPRS业务使用量: '[1]#REF'!$A$651
Name GPRS业务使用用户到达数: '[1]#REF'!$A$619
Name GPRS业务使用用户到达数免费用户: '[1]#REF'!$A$631
Name HLR总容量: '[1]#REF'!#REF!
Name Internet上网累计使用量: '[1]#REF'!$A$146
Name Internet上网使用量: '[1]#REF'!$A$134
Name Internet上网用户到达数: '[1]#REF'!$A$110
Name Internet上网用户到达数免费用户: '[1]#REF'!$A$122
Name IP充值卡用户数: '[1]#REF'!$A$448
Name IP直通车用户数: '[1]#REF'!$A$443
Name 本年度累计新增市场中移动占有率: '[1]#REF'!$A$77
Name 本年累计IP分钟数情况表: '[1]#REF'!$A$384
Name 本年累计WAP使用量: '[1]#REF'!$A$98
Name 本年累计电信小灵通用户净增数: '[1]#REF'!$A$182
Name 本年累计净增电路总数: '[1]#REF'!#REF!
Name 本年累计联通CDMA用户净增数: '[1]#REF'!$A$106
Name 本年累计联通签约用户净增数: '[1]#REF'!$A$102
Name 本年累计联通预付卡用户净增数: '[1]#REF'!$A$110
Name 本年累计新增用户市场占有率不含预付卡用户: '[1]#REF'!$A$166
Name 本年累计总使用分钟数不含漫游来访的: '[1]#REF'!$A$202
Name 本年累计总通话分钟数分析表: '[1]#REF'!$A$439
Name 本年其他省内签约品牌累计总使用分钟数不含漫游来访的: '[1]#REF'!$A$295
Name 本年其他预付品牌累计总使用分钟数不含漫游来访的: '[1]#REF'!$A$322
Name 本年其它全球通优惠累计总使用分钟数不含漫游来访的: '[1]#REF'!$A$226
Name 本年签约累计总使用分钟数不含漫游来访的: '[1]#REF'!$A$210
Name 本年全球通累计总使用分钟数不含漫游来访的: '[1]#REF'!$A$218
Name 本年全球通预付费累计总使用分钟数不含漫游来访的: '[1]#REF'!$A$313
Name 本年神州行累计总使用分钟数不含漫游来访的: '[1]#REF'!$A$304
Name 本月1860台客服座席数: '[1]#REF'!$A$21
Name 本月1860台客户服务话务员: '[1]#REF'!$A$37
Name 本月1860台人工热线数: '[1]#REF'!$A$52
Name 本月1860台人工热线中投诉电话数: '[1]#REF'!$A$70
Name 本月1860台人工热线中咨询电话数: '[1]#REF'!$A$88
Name 本月DDD分钟数: '[1]#REF'!$A$282
Name 本月IDD分钟数: '[1]#REF'!$A$291
Name 本月IP呼叫DDD: '[1]#REF'!$A$2
Name 本月IP呼叫IDD: '[1]#REF'!$A$86
Name 本月点对点使用量比较表87: '[1]#REF'!$A$733
Name 本月点对点用户数比较表86: '[1]#REF'!$A$723
Name 本月电信小灵通用户到达数: '[1]#REF'!$A$186
Name 本月电信小灵通用户净增数: '[1]#REF'!$A$178
Name 本月非IP呼叫DDD: '[1]#REF'!$A$320
Name 本月非IP呼叫IDD: '[1]#REF'!$A$330
Name 本月高价值用户数比较表65: '[1]#REF'!$A$55
Name 本月净增电路总数: '[1]#REF'!#REF!
Name 本月净增话音信道数量GSM: '[1]#REF'!#REF!
Name 本月净增话音信道数量总数: '[1]#REF'!#REF!
Name 本月净增基站控制器数量GSM: '[1]#REF'!#REF!
Name 本月净增基站数量GSM: '[1]#REF'!#REF!
Name 本月净增基站数量总数: '[1]#REF'!#REF!

Sheet Sheet1
B2: 后续要考虑的事项：
B3: 1、修改后的总表1、2，能不能加一列，展示每个指标的折现图，历年or历月变化情况
B4: 2、分市场表里增加存量保有情况。
B10: 1、第一页和第四页合并，第一部分就是财务状态，第二部分就是业务运营，就是业务部、基站；第三部分份额啥的。两增长和4提升和上市相关的，可以放里面。
B11: 2、开通轻量化（RedCap）功能5G基站是5G基站开通这个功能，只有这一个功能，还是说基于现有基站，只需要进行软件升级or改造，就能开通这功能。
B12: 3、主要产品业务情况表。能不能吧“8+5”的都放进来，补充下政企市场产品。
B13: 4、个人市场分省主要产品表。能不能挑一挑重点指标，合成一张表。
B14: 5、主要产品效益情况表，问下丛鑫CHBN是不是就是通信服务收入全量；（基础）能不能去掉；除了主要产品，能不能只展示重点产品的情况，比如政企市场指标太多了。
B15: 6、主表（分省也可以看下）标题的括号，都放在标题最后
B20: 回答
B21: 1、已改
B22: 2、是基于现有5G基站进行升级、开通RedCap功能的基站。
... B28: 8、两增长、四提升方面的指标。两增长即收入和利润增长，现有月报已有展示；四提升，董事长报告书只是提了概念，没有列出具体对应的指标。科创能力提升方面，问了预算处，国资委在2024年预算报表中增加了一张《核心竞争力和核心功能情况表》里面有科技指标（包含研发经费投入、研发经费投入强度、科技收入、专利数、论文数、国家级创新平台数量等）、效率指标、人才指标等，目前口径没定，技术部正在牵头研究口径。研发经费投入强度已经在月报中展示，建议不再增加其他指标。

Sheet 目录1
A1: 目 录
B2: 一、高质量发展指标情况表 *………………………………………………………………………………………………………………… | I2: 1
B3: 一、上市公司主要情况表………………………………………………………………………………………………………………… | I3: （1~16）
B4: 主要经营情况表（1/16）……………………………………………………………………………… | I4: 1
B5: CHBN收入情况表（2/16）………………………………………………………………………………………… | I5: 2
B6: 连接+算力+能力情况表（3/16）………………………………………………………………………………………………… | I6: 3
B7: 5G业务情况表（4/16）………………………………………………………………………………………………… | I7: 4
B8: 移动云业务情况表（5/16）……………………………………………………………………………………………… | I8: 5
B9: 主要产品运营情况表（6/16）……………………………………………………………………………………………… | I9: 6
B10: 个人市场整体情况表（7/16）…………………………………………………………………………… | I10: 7
B11: 家庭市场整体情况表（8/16）………………………………………………………………………………………………………………………… | I11: 8
B12: 政企市场整体情况表（9/16）………………………………………………………………………………………………………………………… | I12: 9
B13: 网络能力与投资情况表（10/16） ………………………………………………………………………………………………………………… | I13: 10
B14: 营运收入情况表（11/16）………………………………………………………………………………………………… | I14: 11
B15: 营运支出情况表（12/16）…………………………………………………………………………………… | I15: 12
... B19: 电信行业主要指标情况表（续）（16/16）………………………………………………………………………… | I19: 16
B20: 二、上市公司各省主要情况表…………………………………………………………………………… | I20: (17~52)
B21: 收入和利润情况表（1/36)……………………………………………………………………… | I21: 17
B22: 数字化转型收入和支出情况表（2/36)…………………………………………………………………………………………………………………………… | I22: 18
B23: “CHBN”收入情况表（3/36)………………………………………………………………………………………………………………… | I23: 19
B24: 分市场收入驱动因素情况表（4/36)……………………………………………………………… | I24: 20
B25: 收入与行业发展、宏观经济对比情况表（5/36)………………………………………………………………………………………………………………… | I25: 21
B26: 总连接情况表（6/36)………………………………………………………………… | I26: 22
B27: 移动电话客户情况表（7/36)……………………………………………………………… | I27: 23
B28: 有线宽带业务情况表（8/36)………………………………………………………………………………………………………………… | I28: 24
B29: 千兆有线宽带业务情况表（9/36)………………………………………………………………………………………………………………… | I29: 25
B30: 个人市场-5G套餐客户情况表（10/36)…………………………………………………………………………………………………………………………… | I30: 26
B31: 个人市场-5G网络客户情况表（11/36)…………………………………………………………………………………………………………………………… | I31: 27
B32: 个人市场-5G机套网客户情况表（12/36)…………………………………………………………………………………………………………………………… | I32: 28
B34: *为支撑高质量发展，统计月报围绕考核管控、经营目标等重点梳理指标，新增《高质量发展指标情况表》

Sheet 目录2
B1: 个人市场-个人上网业务情况表（13/36)…………………………………………………………………………………………………………………………… | I1: 29
B2: 个人市场-手机上网业务情况表（14/36)…………………………………………………………………………………………………………………………… | I2: 30
B3: 个人市场-携号转网情况表（15/36)…………………………………………………………………………………………………………………………… | I3: 31
B4: 个人市场-重点产品情况表（16/36)……………………………………………………………… | I4: 32
B5: 个人市场-重点产品情况表（续）（17/36)……………………………………………………………… | I5: 33
B6: 家庭市场-家庭宽带业务情况表（18/36)……………………………………………………………… | I6: 34
B7: 家庭市场-家庭宽带业务情况表（续）（19/36)…………………………………………………… | I7: 35
B8: 家庭市场-移动高清业务情况表（20/36)……………………………………………………………… | I8: 36
B9: 家庭市场-重点产品情况表（21/36)……………………………………………………………… | I9: 37
B10: 政企市场-客户和DICT收入情况表（22/36)………………………………………………………………………… | I10: 38
B11: 政企市场-行业份额情况表（23/36)……………………………………………………………… | I11: 39
B12: 政企市场-专线业务情况表（24/36)…………………………………………………………………………… | I12: 40
... B24: 重点地市业务数据表（续）（36/36)………………………………………………………………………………………………………………… | I24: 52
B25: 三、专业公司主要情况表…………………………………………………………………………………. | I25: （53~62）
B26: 香港公司主要情况表……………………………………………………………………………………… | I26: 53
B27: 辛姆巴科公司主要情况表……………………………………………………………………………………… | I27: 54
B28: 国际公司主要情况表……………………………………………………………………………………… | I28: 55
B29: 财务公司、终端公司主要情况表……………………………………………………………………………………… | I29: 56
B30: 中移铁通公司主要情况表……………………………………………………………………………………… | I30: 57
B31: 集成公司、在线营销服务中心、物联网公司主要情况表……………………………………………………………………………………… | I31: 58
B32: 金科公司、信息技术中心主要情况表……………………………………………………………………………………… | I32: 59
B33: 专业公司、事业部及直属单位主要财务指标表……………………………………………………………………………………… | I33: 60
B34: 四、集团公司人员和薪酬情况表……………………………………………………………………………………… | I34: 61
B35: 五、集团公司主要情况表……………………………………………………………………… | I35: 62

Sheet 主要经营情况表
A1: 上市公司主要经营情况表（1/16）
A2: 45323
A3: 指标 | B3: 单位 | C3: 本月实际 | D3: 比上月± | E3: 比上年同期± | F3: 本年累计 | G3: 比上年同期±
A4: 一、经营业绩
A5: （一）营运收入 | B5: 亿元 | C5: 906.01272 | D5: -0.071866415 | E5: 0.027292438 | F5: 1882.179 | G5: 0.032259278
A6: 1.通信服务收入 | B6: 亿元 | C6: 776.99523 | D6: -0.032483166 | E6: 0.020870014 | F6: 1580.0771 | G6: 0.020617651
A7: 其中：数字化转型收入 | B7: 亿元 | C7: 245.3963 | D7: -0.076775135 | E7: 0.1336611 | F7: 511.19969 | G7: 0.11892124
A8: 其中：算力网络收入 | B8: 亿元 | C8: 138.15411 | D8: -0.1537844 | E8: 0.1140614 | F8: 301.41523 | G8: 0.11015701
A9: 2.销售产品收入及其他 | B9: 亿元 | C9: 129.01749 | D9: -0.2545979 | E9: 0.067746916 | F9: 302.10191 | G9: 0.09774985
A10: （二）营运支出 | B10: 亿元 | C10: 736.23642 | D10: -0.059298287 | E10: 0.075596822 | F10: 1518.8824 | G10: 0.06320185
A11: （三）营运利润 | B11: 亿元 | C11: 169.7763 | D11: -0.12269516 | E11: -0.14016111 | F11: 363.29661 | G11: -0.079716739
A12: （四）归属于母公司所有者的净利润 | B12: 亿元 | C12: 151.97367 | D12: -0.032629667 | E12: -0.10828462 | F12: 309.07345 | G12: -0.081225066
A13: 净利润率 | B13: % | C13: 0.167739 | D13: 0.680353 | E13: -2.550316 | F13: 0.16421045 | G13: -2.0282785
A14: （五）EBITDA | B14: 亿元 | C14: 346.17503 | D14: -0.065299361 | E14: -0.068260325 | F14: 716.53429 | G14: -0.029586494
A15: EBITDA margin | B15: % | C15: 0.38208629 | D15: 0.26844759 | E15: -3.9184121 | F15: 0.38069402 | G15: -2.4262147
A16: （六）资产总额 | B16: 亿元 | C16: - | D16: - | E16: - | F16: 19652.564 | G16: 0.019178387
A17: 其中：货币资金 | B17: 亿元 | C17: - | D17: - | E17: - | F17: 2485.6838 | G17: -0.08163684
A18: （七）负债总额 | B18: 亿元 | C18: - | D18: - | E18: - | F18: 6222.4031 | G18: -0.015659751
A19: 资产负债率 | B19: % | C19: - | D19: - | E19: - | F19: 0.31662041 | G19: -1.1205948
A20: （八）经营净现金流 | B20: 亿元 | C20: 254.97438 | D20: 11.990689 | E20: -0.099541257 | F20: 274.60186 | G20: -0.43434707
A21: （九）自由现金流 | B21: 亿元 | C21: 215.0144 | D21: - | E21: 0.068775527 | F21: 140.40726 | G21: -0.57086886
A22: 二、业务运营
A23: （一）移动计费总时长 | B23: 亿分钟 | C23: 1989.0403 | D23: -0.14217867 | E23: -0.11485198 | F23: 4307.7519 | G23: -0.06763202
A24: （二）短彩信计费量 | B24: 亿条 | C24: 727.47341 | D24: -0.1185024 | E24: -0.054926271 | F24: 1552.7433 | G24: 0.0039086597
A25: 其中：集团短信计费量 | B25: 亿条 | C25: 617.94295 | D25: -0.11592465 | E25: 0.023788554 | F25: 1316.9138 | G25: 0.087168248
A26: （三）移动数据流量 | B26: 亿MB | C26: 121963.58 | D26: -0.12466615 | E26: 0.018990687 | F26: 261297.37 | G26: 0.069909991
A27: 其中：手机上网流量 | B27: 亿MB | C27: 119128.07 | D27: -0.12532187 | E27: 0.0071415762 | F27: 255324.53 | G27: 0.057741259
A28: （四）基站数 | B28: 万个 | C28: - | D28: - | E28: - | F28: 667.1712 | G28: 0.098158941
A29: （五）资本开支 | B29: 亿元 | C29: 39.959988 | D29: -0.57595212 | E29: -0.51257777 | F29: 134.1946 | G29: -0.15211787
A30: 资本开支占通信服务收入比重 | B30: % | C30: 0.051428872 | D30: -6.5912356 | E30: -5.6285118 | F30: 0.084929147 | G30: -1.7302264
A31: 三、竞争态势
A32: （一）行业通信服务收入增幅 | B32: % | C32: - | D32: - | E32: - | F32: 0.0426 | G32: -3.15
A33: 公司通信服务收入增幅与行业收入增幅差 | B33: % | C33: - | D33: - | E33: - | F33: -1.4103526 | G33: -
A34: （二）通信服务收入份额 | B34: % | C34: - | D34: - | E34: - | F34: 0.52275603 | G34: -0.87892477
A35: （三）政企市场收入份额 | B35: % | C35: - | D35: - | E35: - | F35: 0.40367639 | G35: -0.37351247
A36: （四）移动电话客户份额 | B36: % | C36: - | D36: - | E36: - | F36: 0.5702233 | G36: -0.52234362
A37: 移动电话客户净增份额 | B37: % | C37: 0.21855808 | D37: -4.7789189 | E37: 4.8684117 | F37: 0.21855808 | G37: 4.8684117
A38: （五）有线宽带客户份额 | B38: % | C38: - | D38: - | E38: - | F38: 0.4690676 | G38: 0.66448778
A39: 有线宽带客户净增份额 | B39: % | C39: 0.54382703 | D39: 55.248469 | E39: -6.7832051 | F39: 0.54382703 | G39: -6.7832051
A40: （六）千兆有线宽带客户份额 | B40: % | C40: - | D40: - | E40: - | F40: 0.50643044 | G40: 6.7337223
A41: 千兆有线宽带客户净增份额 | B41: % | C41: 0.497007 | D41: -7.8816801 | E41: -11.66171 | F41: 0.497007 | G41: -11.66171
A42: 注：1.数字化转型收入包括个人市场新业务（移动云盘等）收入，家庭市场智慧家庭增值业务收入，政企市场DICT收入、物联网收入、专线收入，以及新兴市场收入
A43: 2.算力网络收入包括个人市场移动云盘（个人）收入，家庭市场移动云盘（家庭）收入、家庭安防收入，政企市场DICT收入、物联网功能费，
A44: 新兴市场内容媒体和国际算力网络业务收入
A45: 3.基站数=GSM基站+TD-LTE基站+LTE FDD基站+5G基站+NB-IoT基站
A46: 4.市场份额根据工业和信息化部公布数据计算得出，政企市场收入份额取自政企事业部，均为上月值
A47: 1

Sheet 主要财务情况表
A1: 上市公司主要财务情况表（1/17） | L1: 删除部分指标，其余的放在表一上市公司主要经营情况表
A2: 2024年
A3: 指标 | B3: 单位 | C3: 本月实际 | D3: 比上月± | E3: 比上年同期± | F3: 本年累计 | G3: 比上年同期± | H3: 占收入比重
A4: 一、营运收入 | B4: 亿元
A5: （一）通信服务收入 | B5: 亿元
A6: 其中：个人市场收入（C） | B6: 亿元
A7: 家庭市场收入（H） | B7: 亿元
A8: 政企市场收入（B） | B8: 亿元
A9: 新兴市场收入（N） | B9: 亿元
A10: 其中：数字化转型收入 | B10: 亿元
A11: 其中：算力网络收入 | B11: 亿元
A12: （二）销售产品收入及其他 | B12: 亿元
A13: 二、营运支出 | B13: 亿元
A14: 其中：成本费用总额 | B14: 亿元
A15: 三、营运利润 | B15: 亿元
... A29: 资产负债率 | B29: %
A30: 九、现金流量
A31: 1.经营净现金流 | B31: 亿元
A32: 2.自由现金流 | B32: 亿元
A33: 注：1.数字化转型收入包括个人市场新业务（移动云盘等）收入，家庭市场智慧家庭增值业务收入，政企市场DICT收入、物联网收入、专线收入，以及新兴市场收入
A34: 2.算力网络收入包括个人市场移动云盘（个人）收入，家庭市场移动云盘（家庭）收入、家庭安防收入，政企市场DICT收入、物联网功能费，
A35: 新兴市场内容媒体和国际算力网络业务收入
A36: 3.成本费用总额=营运支出-销售产品成本+融资成本
A37: 1

Sheet CHBN收入报表
A1: CHBN收入情况表（2/16）
A2: =主要经营情况表!A2 -> 45323
A3: 指标 | B3: 单位 | C3: 本月实际 | D3: 比上月± | E3: 比上年同期± | F3: 本年累计 | G3: 比上年同期± | H3: 占通信服务收入比
A4: 通信服务收入 | B4: 亿元 | C4: 776.99523 | D4: -0.0325 | E4: 0.020870014 | F4: 1580.0771 | G4: 0.020617651 | H4: 1
A5: 一、个人市场收入（C） | B5: 亿元 | C5: 430.86084 | D5: -0.0076985941 | E5: -0.021391716 | F5: 865.06444 | G5: -0.025469581 | H5: 0.54748242
A6: 1.个人语音 | B6: 亿元 | C6: 55.536706 | D6: -0.078573048 | E6: -0.075521914 | F6: 115.80921 | G6: -0.050442431 | H6: 0.07329339
A7: 2.个人短彩信 | B7: 亿元 | C7: 2.7829826 | D7: 0.29299423 | E7: 0.27920135 | F7: 4.9353375 | G7: 0.12033366 | H7: 0.0031234789
A8: 3.个人无线上网 | B8: 亿元 | C8: 339.01571 | D8: 0.0038748478 | E8: -0.035282031 | F8: 676.72286 | G8: -0.043243615 | H8: 0.42828471
A9: 4.个人新业务 | B9: 亿元 | C9: 28.059439 | D9: 0.14110727 | E9: 0.59879778 | F9: 52.649097 | G9: 0.45282884 | H9: 0.033320588
A10: 5.其他 | B10: 亿元 | C10: 5.4659993 | D10: -0.42353537 | E10: -0.39704593 | F10: 14.947933 | G10: -0.1582484 | H10: 0.0094602553
A11: 二、家庭市场收入（H） | B11: 亿元 | C11: 115.81369 | D11: -0.0094863415 | E11: 0.075159274 | F11: 232.73656 | G11: 0.080947402 | H11: 0.14729443
A12: 1.家庭语音 | B12: 亿元 | C12: 0.89124119 | D12: 0.001446539 | E12: -0.15696816 | F12: 1.781195 | G12: -0.16731925 | H12: 0.0011272836
A13: 2.家庭宽带 | B13: 亿元 | C13: 83.690915 | D13: -0.017574447 | E13: 0.085957618 | F13: 168.87896 | G13: 0.09504403 | H13: 0.1068802
A14: 3.智慧家庭增值业务 | B14: 亿元 | C14: 31.139832 | D14: 0.012895116 | E14: 0.058271434 | F14: 61.883225 | G14: 0.055684035 | H14: 0.039164687
A15: 4.其他 | B15: 亿元 | C15: 0.091705591 | D15: -0.096229047 | E15: -0.45695791 | F15: 0.19317554 | G15: -0.41210873 | H15: 0.00012225703
... A32: （四）资本运作并表收入 | B32: 亿元 | C32: 0 | D32: 0 | E32: 0 | F32: 0 | G32: 0 | H32: 0
A33: 注：1.个人市场、家庭市场、政企市场、新兴市场为互斥关系，合计等于财务报表《香港口径损益表》中的“通信服务收入”
A34: 2.网间结算收入按照各市场的语音、短彩信收入权重进行分摊
A35: 3.物联网流量收入属于政企市场无线上网收入，不属于个人市场收入
A36: 4.个人市场收入包含政企客户代成员用户付费收入
A37: 5.本年截至目前，家庭类内容媒体、资本运作两项暂无收入，后续将逐步随着业务实际发展状况展示相关数据
A38: =主要经营情况表!A47+1 -> 2

Sheet 连接+算力+能力情况表
A1: 连接+算力+能力情况表（3/16）
A2: =主要经营情况表!A2 -> 45323
A3: 指标 | B3: 单位 | C3: 本月实际 | D3: 比上月± | E3: 比上年同期± | F3: 本年累计 | G3: 比上年同期±
A4: 一、连接
A5: （一）总连接数 | B5: 万 | C5: - | D5: - | E5: - | F5: 337911.95 | G5: 0.12649179
A6: 1.网络连接数 | B6: 万户 | C6: - | D6: - | E6: - | F6: 260734.88 | G6: 0.11584023
A7: 其中：移动电话客户数 | B7: 万户 | C7: - | D7: - | E7: - | F7: 99106.556 | G7: 0.012688813
A8: —5G网络客户数 | B8: 万户 | C8: - | D8: - | E8: - | F8: 47473.219 | G8: 0.37692118
A9: 有线宽带客户数 | B9: 万户 | C9: - | D9: - | E9: - | F9: 30237.259 | G9: 0.089077154
A10: —家庭宽带客户数 | B10: 万户 | C10: - | D10: - | E10: - | F10: 26711.157 | G10: 0.076203392
A11: 物联网卡客户数 | B11: 万户 | C11: - | D11: - | E11: - | F11: 131391.07 | G11: 0.21615627
A12: 2.设备连接数 | B12: 万 | C12: - | D12: - | E12: - | F12: 77177.069 | G12: 0.16403112
A13: 其中：家庭设备数 | B13: 万 | C13: - | D13: - | E13: - | F13: 51079.746 | G13: 0.20394143
A14: 行业设备数 | B14: 万 | C14: - | D14: - | E14: - | F14: 26097.323 | G14: 0.093106817
A15: （二）净增总连接数 | B15: 万 | C15: 1029.2042 | D15: -0.28445118 | E15: -0.72520325 | F15: 2467.5466 | G15: -0.58631736
A16: 1.净增网络连接数 | B16: 万户 | C16: 42.233 | D16: -0.77229705 | E16: -0.98464431 | F16: 227.7071 | G16: -0.91676291
A17: 其中：净增移动电话客户数 | B17: 万户 | C17: -51.0601 | D17: -1.8855484 | E17: -1.1626996 | F17: 6.5992 | G17: -0.98187754
A18: —净增5G网络客户数 | B18: 万户 | C18: 828.7119 | D18: 4.0737722 | E18: 0.023480431 | F18: 992.0444 | G18: -0.43682949
A19: 净增有线宽带客户数 | B19: 万户 | C19: 151.3206 | D19: -0.42107645 | E19: -0.4860898 | F19: 412.7033 | G19: -0.24590693
A20: 净增物联网卡客户数 | B20: 万户 | C20: -58.0275 | D20: - | E20: -1.0270899 | F20: -191.5954 | G20: -1.1050289
A21: 2.净增设备连接数 | B21: 万 | C21: 986.9712 | D21: -0.21223069 | E21: -0.0080821055 | F21: 2239.8395 | G21: -0.30637631
A22: 其中：净增家庭设备数 | B22: 万 | C22: 918.8342 | D22: -0.033112354 | E22: 0.17189974 | F22: 1869.1351 | G22: -0.37654122
A23: 净增行业设备数 | B23: 万 | C23: 68.137 | D23: -0.77480389 | E23: -0.67701108 | F23: 370.7044 | G23: 0.60355711
A24: 二、算力
A25: 1. 服务器算力规模（用FP32精度计算） | B25: EFLOPS | C25: - | D25: - | E25: - | F25: 11 | G25: 0.375
A26: 其中：智算规模（用FP32精度计算） | B26: EFLOPS | C26: - | D26: - | E26: - | F26: 3 | G26: -
A27: 2.智算规模（用FP16精度计算） | B27: EFLOPS | C27: - | D27: - | E27: - | F27: 10 | G27: -
A28: 3. 数据中心机架数（含自用、合作） | B28: 万个 | C28: - | D28: - | E28: - | F28: 134 | G28: 0.072
A29: 数据中心平均PUE值 | B29: - | C29: - | D29: - | E29: - | F29: 1.32 | G29: -0.029411765
A30: 4.自有可装机架数 | B30: 万个 | C30: - | D30: - | E30: - | F30: 122.5 | G30: -
A31: 三、能力
A32: 1. 汇聚中台能力数量 | B32: 项 | C32: - | D32: - | E32: - | F32: 1036 | G32: 0.16143498
A33: 2. 智慧中台能力调用量 | B33: 亿次 | C33: 524.82 | D33: -0.05507643 | E33: 0.79948568 | F33: 524.82 | G33: 0.79948568
A34: 注：1.总连接数=网络连接数+设备连接数。其中，网络连接数=移动电话客户数+有线宽带客户数+物联网卡客户数，设备连接数=家庭设备数
A35: +行业设备数
A36: 2.家庭设备数=移动高清设备数+智能组网、语音遥控器、智能安防、智能音箱、智能电视等智家设备数
A37: 3.行业设备数=OneNET平台连接设备数+千里眼连接设备数+和商务TV设备数+云视讯硬终端设备数
A38: 4.算力规模、数据中心机架数、自有可装机架数按季度统计，为截至2023年12月数据；数据中心平均PUE值按季度统计，为2023年全年的平均值
A39: 5.自有可装机架数是指由我公司投资建设，产权、资产完全归我公司所有的数据中心和通信枢纽机房的全部可装机架
A40: 6.汇聚中台能力数量、智慧中台能力调用量为上月值
A41: =CHBN收入报表!A38+1 -> 3

Sheet 主要业务指标
A1: 主要运营情况表（4/17） | I1: 删除部分指标，其余的放在表一上市公司主要经营情况表
A2: =主要经营情况表!A2 -> 45323
A3: 指标 | B3: 单位 | C3: 本月实际 | D3: 比上月± | E3: 比上年同期± | F3: 本年累计 | G3: 比上年同期±
A4: 一、业务量
A5: 1. 移动计费总时长 | B5: 亿分钟
A6: 2. 短彩信计费量 | B6: 亿条
A7: 3. 移动数据流量 | B7: 亿MB
A8: 其中：物联网流量 | B8: 亿MB | I8: 挪到政企表
A9: 二、基站与投资
A10: 1. 基站数 | B10: 万个
A11: —5G基站数 | B11: 万个 | I11: 删除，5G表中有
A12: 2. 净增基站数 | B12: 万个 | I12: 删除，能力表中有
A13: —净增5G基站数 | B13: 万个 | I13: 删除，5G表中有
A14: 3. 资本开支 | B14: 亿元
A15: —5G资本开支 | B15: 亿元 | I15: 删除，5G表中有
A16: 4. 资本开支占通信服务收入比重 | B16: %
A17: 三、资费
A18: 1. 每分钟语音业务收入 | B18: 元/分钟 | I18: 挪到个人市场表
A19: 2. 手机上网流量资费 | B19: 元/GB | I19: 删除，个人市场表中有
A20: 四、市场份额
A21: 1. 行业通信服务收入增幅 | B21: %
A22: 2. 通信服务收入增幅与行业收入增幅差 | B22: %
A23: 3. 通信服务收入份额 | B23: %
A24: 4. 移动电话客户份额 | B24: %
A25: —5G网络客户份额 | B25: % | I25: 删除，挪到5G表中
A26: 5. 移动电话客户净增份额 | B26: %
A27: —5G网络客户净增份额 | B27: % | I27: 删除，挪到5G表中
A28: 6.有线宽带客户份额 | B28: %
A29: —千兆有线宽带客户份额 | B29: %
A30: 7.有线宽带客户净增份额 | B30: %
A31: —千兆有线宽带客户净增份额 | B31: %
A32: 注：1.基站数=GSM基站+TD-LTE基站+LTE FDD+5G基站+NB-IoT基站 | I32: 删除3G基站
A33: 自3月起，5G室内基站改按行业通用口径统计（一次性调整到位，往期数据不追溯） | I33: 删除
A34: 2.市场份额根据工业和信息化部公布数据计算得出，为上月值
A35: 4

Sheet 5G业务指标表
A1: 5G业务情况表（4/16）
A2: =主要经营情况表!A2 -> 45323
A3: 指标 | B3: 单位 | C3: 本月实际 | D3: 比上月± | E3: 比上年同期± | F3: 本年累计 | G3: 比上年同期±
A4: 一、客户发展
A5: （一）2C市场
A6: 1.5G套餐客户数 | B6: 万户 | C6: - | D6: - | E6: - | F6: 80078.506 | G6: 0.25292479
A7: 5G终端客户数 | B7: 万户 | C7: - | D7: - | E7: - | F7: 57651.448 | G7: 0.28992532
A8: 5G网络客户数 | B8: 万户 | C8: - | D8: - | E8: - | F8: 47473.219 | G8: 0.37692118
A9: —700M 5G网络客户数 | B9: 万户 | C9: - | D9: - | E9: - | F9: 31898.341 | G9: 0.62411693
A10: 5G机套网客户数 | B10: 万户 | C10: - | D10: - | E10: - | F10: 39588.919 | G10: 0.50178712
A11: 2.净增5G套餐客户数 | B11: 万户 | C11: 1127.3208 | D11: - | E11: -0.32328429 | F11: 628.2272 | G11: -0.74998266
A12: 净增5G终端客户数 | B12: 万户 | C12: 1102.0972 | D12: 0.57840486 | E12: -0.019705212 | F12: 1800.332 | G12: -0.26704169
A13: 净增5G网络客户数 | B13: 万户 | C13: 828.7119 | D13: 4.0737722 | E13: 0.023480431 | F13: 992.0444 | G13: -0.43682949
A14: 净增5G机套网客户数 | B14: 万户 | C14: 1172.2347 | D14: - | E14: 0.29178572 | F14: 1152.641 | G14: -0.38283077
A15: （二）2B市场
A16: 1.5G物联卡客户数 | B16: 万户 | C16: - | D16: - | E16: - | F16: 1187.8419 | G16: 2.7451529
A17: 净增5G物联卡客户数 | B17: 万户 | C17: 69.0291 | D17: 2.1041893 | E17: 0.78802682 | F17: 91.2665 | G17: 0.3288348
A18: 二、发展质量
A19: （一）2C市场
A20: 1.5G套餐客户渗透率 | B20: % | C20: - | D20: - | E20: - | F20: 0.80800412 | G20: 15.492683
A21: 5G套餐客户出账ARPU | B21: 元/户·月 | C21: 67.193834 | D21: 0.042982979 | E21: -0.12925551 | F21: 65.757351 | G21: -0.11420325
A22: 5G套餐客户DOU | B22: GB/户·月 | C22: 13.662185 | D22: -0.06820897 | E22: -0.15185835 | F22: 14.171997 | G22: -0.098956884
A23: 2.5G网络客户渗透率 | B23: % | C23: - | D23: - | E23: - | F23: 0.4790119 | G23: 12.671142
A24: 5G网络客户出账ARPU | B24: 元/户·月 | C24: 79.150445 | D24: 0.044406511 | E24: -0.083337789 | F24: 77.403732 | G24: -0.06665479
A25: 5G网络客户DOU | B25: GB/户·月 | C25: 18.647272 | D25: -0.079598286 | E25: -0.17515116 | F25: 19.467623 | G25: -0.10807211
A26: 5G网络流量占比 | B26: % | C26: 0.56988297 | D26: -0.84824823 | E26: 11.737505 | F26: 0.5744082 | G26: 14.560161
A27: 5G流量中700M流量占比 | B27: % | C27: 0.24888835 | D27: 5.459086 | E27: 9.5089705 | F27: 0.21956458 | G27: 5.037341
A28: 3.5G机套网匹配率 | B28: % | C28: - | D28: - | E28: - | F28: 0.68969711 | G28: 9.7685409
A29: 5G机套网客户出账ARPU | B29: 元/户·月 | C29: 85.582722 | D29: 0.03956516 | E29: -0.1095506 | F29: 83.882244 | G29: -0.091655203
A30: 5G机套网客户DOU | B30: GB/户·月 | C30: 20.003784 | D30: -0.077051726 | E30: -0.15940417 | F30: 20.843632 | G30: -0.097657897
A31: （二）2B市场
A32: 1.5G专网收入 | B32: 亿元 | C32: 4.9668429 | D32: -0.35520769 | E32: 0.41148558 | F32: 12.669855 | G32: 0.58498971
A33: 三、网络能力及投资
A34: 1.5G基站数 | B34: 万个 | C34: 1.5105 | D34: -0.66254859 | E34: -0.50368009 | F34: 200.5492 | G34: 0.51223897
A35: 其中：5G 700MHz基站数 | B35: 万个 | C35: 0.5874 | D35: -0.57245797 | E35: -0.27651189 | F35: 63.9137 | G35: 0.29476149
A36: 其中：开通轻量化（RedCap）功能5G基站数 | B36: 万个 | C36: -5.0336 | D36: - | E36: - | F36: 14.1953 | G36: -
A37: 2.5G载频数 | B37: 万个 | C37: 3.5599 | D37: -0.43595716 | E37: -0.54064621 | F37: 462.307 | G37: 0.26193297
A38: —5G 700MHz载频数 | B38: 万个 | C38: 1.5017 | D38: -0.45651623 | E38: -0.20884042 | F38: 185.407 | G38: 0.28302594
A39: 3.5G资本开支 | B39: 亿元 | C39: 19.662287 | D39: -0.68919274 | E39: -0.61069446 | F39: 82.924279 | G39: -0.11627192
A40: 四、网络情况
A41: 1.5G无线网络利用率 | B41: % | C41: 0.181 | D41: -4 | E41: - | F41: - | G41: -
A42: 2.5G SA时长驻留比 | B42: % | C42: 0.938 | D42: -0.8 | E42: 6.5 | F42: - | G42: -
A43: 五、市场份额
A44: 5G网络客户份额 | B44: % | C44: - | D44: - | E44: - | F44: 0.56833512 | G44: -1.4800699
A45: 5G网络客户净增份额 | B45: % | C45: 0.13713423 | D45: -50.361713 | E45: -54.215544 | F45: 0.13713423 | G45: -54.215544
A46: 注：1.5G物联卡客户数为开通5G服务的物联卡客户数
A47: 2.网络情况指标取自网络事业部
A48: 5G SA时长驻留比=SA用户的SA话单时长/(SA用户在4G网络的话单时长（不含EPS FB）+SA话单时长)*100%
A49: 3.市场份额根据工业和信息化部公布数据计算得出，为上月值
A50: ='连接+算力+能力情况表'!A41+1 -> 4

Sheet 移动云业务情况表
A1: 移动云业务情况表（5/16）
A2: =主要经营情况表!A2 -> 45323
A3: 指标 | B3: 单位 | C3: 本月实际 | D3: 比上月± | E3: 比上年同期± | F3: 本年累计 | G3: 比上年同期±
A4: 一、收入
A5: 移动云业务收入 | B5: 亿元 | C5: 75.474154 | D5: -0.17010632 | E5: 0.086041811 | F5: 166.41852 | G5: 0.12718889
A6: 1.行业云收入 | B6: 亿元 | C6: 63.404992 | D6: -0.19070301 | E6: 0.050326351 | F6: 141.75076 | G6: 0.092528939
A7: 其中：公有云收入 | B7: 亿元 | C7: 40.028179 | D7: -0.057058962 | E7: 0.0032611894 | F7: 82.478531 | G7: -0.00034576663
A8: 其中：云标准化产品收入 | B8: 亿元 | C8: 15.467431 | D8: -0.094402732 | E8: -0.21733815 | F8: 32.547244 | G8: -0.15166493
A9: 云网收入 | B9: 亿元 | C9: 14.765212 | D9: 0.034099881 | E9: 0.051929349 | F9: 29.043534 | G9: 0.0093178408
A10: 云数收入 | B10: 亿元 | C10: 2.4076756 | D10: -0.25251465 | E10: -0.03112682 | F10: 5.6287095 | G10: 0.24839054
A11: 云智收入 | B11: 亿元 | C11: 0.20164676 | D11: -0.44662806 | E11: 0.48334674 | F11: 0.5660432 | G11: 1.2477611
A12: 云边收入 | B12: 亿元 | C12: 5.0444998 | D12: 0.1391988 | E12: 0.93919894 | F12: 9.4726117 | G12: 0.73913995
A13: 云通信收入 | B13: 亿元 | C13: 2.1417136 | D13: -0.30433911 | E13: 1.4425028 | F13: 5.2203882 | G13: 0.012035584
A14: 私有云收入 | B14: 亿元 | C14: 23.376813 | D14: -0.34875209 | E14: 0.14206605 | F14: 59.272226 | G14: 0.25474455
A15: 其中：云定制化项目收入 | B15: 亿元 | C15: 20.879335 | D15: -0.35493698 | E15: 0.12580765 | F15: 53.247235 | G15: 0.22862169
A16: 云数-ICT大数据收入 | B16: 亿元 | C16: 2.4974775 | D16: -0.29200055 | E16: 0.29888534 | F16: 6.0249908 | G16: 0.54507512
... A24: 云VR\云AR | B24: 亿元 | C24: 0.023246626 | D24: 0.1275119 | E24: -0.49874198 | F24: 0.043864258 | G24: -0.44342528
A25: 二、业务发展
A26: 1.公有云资源池主机数量 | B26: 台 | C26: 7027 | D26: -0.18555865 | E26: -0.1847082 | F26: 234065 | G26: 0.30492109
A27: 2.公有云资源池资源总量 | B27: vCPU | C27: 29186.2 | D27: -0.95085406 | E27: - | F27: 8475447.4 | G27: 0.45797092
A28: 其中：公有云资源池已售资源数量 | B28: vCPU | C28: -23042.17 | D28: - | E28: -1.0960863 | F28: 3841752.4 | G28: 0.37065391
A29: 3.公有云资源池存储容量 | B29: TB | C29: 558119.19 | D29: 0.87018963 | E29: 20.30722 | F29: 5684851.2 | G29: 1.2926768
A30: 其中：公有云资源池已售存储容量 | B30: TB | C30: 267928.85 | D30: 1.5232638 | E30: 2.0065307 | F30: 1874084 | G30: 1.154585
A31: 5.公有云已售带宽 | B31: G | C31: 1166.95 | D31: -0.7849827 | E31: 2.8228068 | F31: 36105.89 | G31: 0.86459997
A32: 三、市场份额
A33: 行业云收入份额 | B33: % | C33: - | D33: - | E33: - | F33: 0.45885283 | G33: 0.46657944
A34: 注：1.收入指标取自管理会计收入报表
A35: 2.移动云业务收入=行业云收入+移动云盘收入+其他云收入
A36: 3.行业云收入=公有云+私有云收入，其中公有云收入=云标准化产品收入[IaaS+PaaS（含9one标准产品、云视讯）+SaaS收入]+云网+云数+云智+云边+云通信收入;
A37: 私有云收入=云定制化项目收入（含ICT9one收入）+云边_局域边缘云收入+云数_ICT大数据收入
A38: 4.云网收入=云专线业务收入+云互联业务收入+IDC入云带宽收入
A39: 5.云数收入=公有云云数收入（乾坤大数据业务收入+其他大数据业务收入）+私有云云数收入（ICT大数据收入）
A40: 6.云边收入=公有云云边收入（CDN+专属云业务收入+广域边缘云业务收入）+私有云云边收入（局域边缘云业务收入）
A41: 7.云通信收入=云MAS收入+云IoT收入+能力开放收入
A42: 8.云定制化项目收入=移动方投资定制化项目收入+ICT服务中云计算收入+ICT服务中9one收入
A43: 9.市场份额取自政企事业部，为上月值
A44: ='5G业务指标表'!A50+1 -> 5

Sheet 主要产品业务情况表
A1: 主要产品运营情况表（6/16）
A2: =主要经营情况表!A2 -> 45323
A3: 产品名称 | B3: 指标 | C3: 单位 | D3: 数值 | E3: 比上月± | F3: 比上年同期±
A4: 一、C+N (个人市场与新兴市场）
A5: 权益 | B5: 融合客户到达数 | C5: 万户 | D5: 31666.01 | E5: -0.043791243 | F5: 0.066896829
A6: 咪咕视频 | B6: 全场景月活用户数 | C6: 万户 | D6: 36422.702 | E6: -0.046813897 | F6: 0.062459597
B7: 会员到达数 | C7: 万户 | D7: 24717.566 | E7: -0.011224986 | F7: 0.10922717
B8: 手机APP月活用户数 | C8: 万户 | D8: 9332.8652 | E8: 0.024802118 | F8: -
A9: 视频彩铃 | B9: 订购用户数 | C9: 万户 | D9: 40589.219 | E9: 0.004713509 | F9: 0.13165364
B10: 会员用户数 | C10: 万户 | D10: 16378.542 | E10: -0.0026504336 | F10: -
B11: 行为月活用户数 | C11: 万户 | D11: 8421.0632 | E11: 0.20730455 | F11: -
A12: 移动云盘 | B12: 会员用户数 | C12: 万户 | D12: 23484.974 | E12: -0.0030371084 | F12: -
B13: 全场景月活用户数 | C13: 万户 | D13: 17872.888 | E13: -0.064057313 | F13: 0.062539071
B14: 核心行为月活用户数 | C14: 万户 | D14: 10263.883 | E14: -0.080525712 | F14: -
A15: 咪咕音乐 | B15: 全场景月活用户数 | C15: 万户 | D15: 18517.158 | E15: -0.021068853 | F15: -0.10465375
A16: 云游戏 | B16: 全场景月活用户数 | C16: 万户 | D16: 11978.001 | E16: 0.021521742 | F16: 0.07889863
B17: 核心用户月活规模 | C17: 万户 | D17: 5218.8556 | E17: -0.033416686 | F17: -
B18: 会员用户数 | C18: 万户 | D18: 4768.371 | E18: -0.018574017 | F18: -0.027550583
A19: 移动认证 | B19: 月活用户数 | C19: 万户 | D19: 77637.473 | E19: -0.0016088612 | F19: 0.031449651
B20: 核心功能月活用户数 | C20: 万户 | D20: 36601.92 | E20: 0.0054305979 | F20: 0.12757261
A21: 和多号（含中间号） | B21: 月服务人次 | C21: 万人次 | D21: 44128.679 | E21: -0.1430403 | F21: 0.42830209
A22: 和包 | B22: 客户端月活用户数 | C22: 万户 | D22: 32758.137 | E22: -0.01130016 | F22: 0.48610686
B23: 客户端交易月活用户数 | C23: 万户 | D23: 8215.0394 | E23: -0.018532033 | F23: 0.21722328
A24: 139邮箱 | B24: 月活用户数 | C24: 万户 | D24: 21937.092 | E24: -0.0060277502 | F24: 0.11103921
A25: 和留言 | B25: 使用用户数 | C25: 万户 | D25: 16935.463 | E25: -0.0038628361 | F25: 0.013036832
A26: 5G新通话 | B26: 全场景月活用户数 | C26: 万户 | D26: 12184.09 | E26: -0.014492132 | F26: -
A27: 和彩印 | B27: 订购用户数 | C27: 万户 | D27: 10713.88 | E27: 0.010117314 | F27: 0.075686443
A28: 咪咕阅读 | B28: 全场景月活用户数 | C28: 万户 | D28: 10143.766 | E28: -0.0030033348 | F28: 0.035922428
A29: 5G消息 | B29: UP2.4终端在网用户到达数 | C29: 万户 | D29: 10767.889 | E29: 0.035816395 | F29: 4.7263329
A30: 云VR | B30: 全场景月活用户数 | C30: 万户 | D30: 758.3086 | E30: -0.16674631 | F30: -0.29789062
A31: 超级SIM | B31: 全场景月活用户数 | C31: 万户 | D31: 1707.0264 | E31: 0.0048281038 | F31: 1.9812941
A32: 二、H（家庭市场）
A33: 大屏点播 | B33: 到达用户数 | C33: 万户 | D33: 13056.834 | E33: 0.011993535 | F33: 0.14254148
B34: 其中：本年累计净增用户数 | C34: 万户 | D34: 323.2283 | E34: - | F34: -0.27837908
A35: 智能组网 | B35: 到达用户数 | C35: 万户 | D35: 14109.73 | E35: 0.018120466 | F35: 0.34111578
B36: 其中：本年累计净增用户数 | C36: 万户 | D36: 599.8418 | E36: - | F36: -0.056181158
A37: 家庭安防 | B37: 到达用户数 | C37: 万户 | D37: 5725.3337 | E37: 0.0074253744 | F37: 0.37520105
B38: 其中：本年累计净增用户数 | C38: 万户 | D38: 98.993 | E38: - | F38: -0.37580355
A39: 健康养老 | B39: 订购用户数 | C39: 万户 | D39: 4234.1579 | E39: 0.12393293 | F39: 1.9374956
B40: 其中：本年累计净增用户数 | C40: 万户 | D40: 200.3947 | E40: - | F40: 1.6233141
A41: 注：1.月活用户数指从月初到月末，在该产品内有过注册、登录、访问、使用、订购、评论等主动行为的用户数（剔重后）
A42: 2.到达（订购）用户数指截止到月末，开通了该产品功能且在网的用户数（BOSS侧存在订购关系）
A43: =移动云业务情况表!A44+1 -> 6

Sheet 主要产品效益情况表
A1: 主要产品效益情况表（7/17）
D2: =主要经营情况表!A2 -> 45323 | I2: 单位：亿元
A3: 产品名称 | B3: 本年累计
B4: 收入 | C4: 占通信服务收入比 | D4: 毛利 | E4: 占通信服务毛利比 | F4: 毛利率 | G4: 利润 | H4: 占通信服务利润比 | I4: 利润率
A5: 通信服务
A6: 一、C(个人市场）
A7: 其中:个人无线上网
A8: 个人语音
A9: 个人短彩信
A10: 权益产品
A11: 移动云盘
A12: 和留言
A13: 二、H（家庭市场）
A14: 其中:家庭宽带
A15: 移动高清
A16: 大屏点播
... A50: 主要通过综合权重分摊至各产品。利润率=利润/收入*100%
A51: 7

Sheet 个人市场
A1: 个人市场整体情况表（7/16）
A2: =主要经营情况表!A2 -> 45323
B3: 单位 | C3: 本月实际 | D3: 比上月± | E3: 比上年同期± | F3: 本年累计 | G3: 比上年同期±
A4: 一、收入规模
A5: 个人市场收入 | B5: 亿元 | C5: 430.86084 | D5: -0.0076985941 | E5: -0.021391716 | F5: 865.06444 | G5: -0.025469581
A6: 其中：个人市场增量收入 | B6: 亿元 | C6: -9.4183271 | D6: -0.28596752 | E6: - | F6: -22.608661 | G6: -4.5008241
A7: 二、客户发展
A8: 1.移动电话客户数 | B8: 万户 | C8: - | D8: - | E8: - | F8: 99106.556 | G8: 0.012688813
A9: 2.净增移动电话客户数 | B9: 万户 | C9: -51.0601 | D9: -1.8855484 | E9: -1.1626996 | F9: 6.5992 | G9: -0.98187754
A10: 移动电话客户离网率 | B10: % | C10: 0.012752216 | D10: -0.014648789 | E10: -0.041346734 | F10: 0.012827933 | G10: 0.0026943185
A11: 3.个人上网客户数 | B11: 万户 | C11: - | D11: - | E11: - | F11: 87367.508 | G11: 0.013768713
A12: 其中：手机上网客户数 | B12: 万户 | C12: - | D12: - | E12: - | F12: 87295.742 | G12: 0.013713727
A13: 4.有效融合客户数 | B13: 万户 | C13: - | D13: - | E13: - | F13: 49917.766 | G13: -
A14: 其中：“四大基座”融合客户数 | B14: 万户 | C14: - | D14: - | E14: - | F14: 28043.147 | G14: -
A15: “六大场景”融合客户数 | B15: 万户 | C15: - | D15: - | E15: - | F15: 46300.906 | G15: -
A16: 三、携号转网
A17: 1.携入至中国移动客户数 | B17: 万户 | C17: 70.4427 | D17: -0.20812106 | E17: -0.4185934 | F17: 159.3991 | G17: -0.26960987
A18: 其中：电信转移动 | B18: 万户 | C18: 40.4563 | D18: -0.21151342 | E18: -0.38905115 | F18: 91.7651 | G18: -0.23361692
A19: 联通转移动 | B19: 万户 | C19: 29.9864 | D19: -0.2034977 | E19: -0.45420029 | F19: 67.634 | G19: -0.31336319
A20: 2.从中国移动携出客户数 | B20: 万户 | C20: 81.9209 | D20: -0.26352644 | E20: -0.34721938 | F20: 193.1549 | G20: -0.20456772
A21: 其中：移动转电信 | B21: 万户 | C21: 49.9058 | D21: -0.26936614 | E21: -0.35919784 | F21: 118.2106 | G21: -0.22526663
A22: 移动转联通 | B22: 万户 | C22: 32.0151 | D22: -0.25423488 | E22: -0.32762716 | F22: 74.9443 | G22: -0.169572
A23: 3.净携入客户数
A24: 移动净携入客户数 | B24: 万户 | C24: -11.4782 | D24: - | E24: - | F24: -33.7558 | G24: -
A25: 电信净携入客户数 | B25: 万户 | C25: 12.0677 | D25: -0.435046 | E25: -0.39518158 | F25: 33.4282 | G25: -0.32705242
A26: 联通净携入客户数 | B26: 万户 | C26: -0.5895 | D26: -1.642787 | E26: - | F26: 0.3276 | G26: -
A27: 四、业务量
A28: 1.个人移动电话计费时长 | B28: 亿分钟 | C28: 1988.0075 | D28: -0.14210737 | E28: -0.11478397 | F28: 4305.3225 | G28: -0.067645192
A29: 2.个人上网流量 | B29: 亿MB | C29: 119266.06 | D29: -0.12526526 | E29: 0.0069696399 | F29: 255611.46 | G29: 0.057416682
A30: 其中：手机上网流量 | B30: 亿MB | C30: 119128.07 | D30: -0.12532187 | E30: 0.0071415762 | F30: 255324.53 | G30: 0.057741259
A31: 五、户均流量（DOU）
A32: 个人上网客户 | B32: GB/户·月 | C32: 14.020671 | D32: -0.064019942 | E32: -0.038330711 | F32: 14.516626 | G32: 0.02620869
A33: 其中：手机上网客户 | B33: GB/户·月 | C33: 14.015962 | D33: -0.064079449 | E33: -0.038114337 | F33: 14.512243 | G33: 0.026578421
A34: 六、户均收入及资费
A35: 1.个人客户出账ARPU | B35: 元/户·月 | C35: 62.507815 | D35: 0.050080785 | E35: -0.019601287 | F35: 60.967651 | G35: -0.0037295455
A36: 2.移动业务ARPU | B36: 元/户·月 | C36: 54.766599 | D36: 0.066711253 | E36: -0.04488964 | F36: 53.001829 | G36: -0.03174204
A37: 3.个人上网流量资费 | B37: 元/GB | C37: 2.9463465 | D37: 0.14782506 | E37: -0.040583035 | F37: 2.7439438 | G37: -0.093508927
A38: 其中：手机上网流量资费 | B38: 元/GB | C38: 2.9437904 | D38: 0.14778348 | E38: -0.041569624 | F38: 2.7416067 | G38: -0.094537107
A39: 4.每分钟语音业务收入 | B39: 元/分钟 | C39: 0.029430694 | D39: 0.074858272 | E39: 0.041170815 | F39: 0.028327415 | G39: 0.016191222
A40: 七、市场份额
A41: 1.移动电话客户份额 | B41: % | C41: - | D41: - | E41: - | F41: 0.5702233 | G41: -0.52234362
A42: 移动电话客户净增份额 | B42: % | C42: 0.21855808 | D42: -4.7789189 | E42: 4.8684117 | F42: 0.21855808 | G42: 4.8684117
A43: 2.个人上网流量份额 | B43: % | C43: 0.51420546 | D43: -2.8394187 | E43: -5.0367677 | F43: 0.51420546 | G43: -5.0367677
A44: 注：1.个人市场收入是指在境内面向个人客户提供的各类通信及信息服务收入,取自管理会计报表
A45: 2.增量收入=本年收入-去年同期收入，下同
A46: 3.融合客户数指办理了“四大基座”或“六大场景”业务的移动电话客户数，已剔重
A47: 4.“四大基座”融合客户数指办理了“四大基座”业务（固移活跃、电视活跃、硬件合约、信用购机）的移动电话客户数
A48: 5.“六大场景”融合客户数指办理了“六大场景”业务（副卡、共享卡、多人保底、家庭V网活跃成员、代付、集团统付）
A49: 的移动电话客户数
A50: 6.携号转网客户数取自工信部携号转网平台
A51: 7.个人上网包含手机上网、数据卡两部分
A52: 8.个人客户出账ARPU=个人客户出账收入（折后税前）/个人出账客户数
A53: 9.移动业务ARPU=移动业务收入/移动电话客户数
A54: 10.市场份额根据工业和信息化部公布数据计算得出，为上月值
A55: =主要产品业务情况表!A43+1 -> 7

Sheet 家庭市场
A1: 家庭市场整体情况表（8/16）
A2: =主要经营情况表!A2 -> 45323
B3: 单位 | C3: 本月实际 | D3: 比上月± | E3: 比上年同期± | F3: 本年累计 | G3: 比上年同期±
A4: 一、收入规模
A5: 家庭市场收入 | B5: 亿元 | C5: 115.81369 | D5: -0.0094863415 | E5: 0.075159274 | F5: 232.73656 | G5: 0.080947402
A6: 其中：家庭市场增量收入 | B6: 亿元 | C6: 8.0959848 | D6: -0.13250802 | E6: -0.34814089 | F6: 17.428618 | G6: -0.25603854
A7: 二、客户发展
A8: 1.家庭宽带客户数 | B8: 万户 | C8: - | D8: - | E8: - | F8: 26711.157 | G8: 0.076203392
A9: 其中：速率在(0,100M)家庭宽带客户数 | B9: 万户 | C9: - | D9: - | E9: - | F9: 756.1427 | G9: 0.03343417
A10: 速率在[100M,300M)家庭宽带客户数 | B10: 万户 | C10: - | D10: - | E10: - | F10: 8312.6877 | G10: -0.13890601
A11: 速率在[300M,500M)家庭宽带客户数 | B11: 万户 | C11: - | D11: - | E11: - | F11: 7176.1182 | G11: -0.065113864
A12: 速率在[500M,1000M)家庭宽带客户数 | B12: 万户 | C12: - | D12: - | E12: - | F12: 2104.2483 | G12: -0.076715373
A13: 千兆家庭宽带客户数 | B13: 万户 | C13: - | D13: - | E13: - | F13: 8361.9596 | G13: 0.86672926
A14: 千兆家庭宽带客户渗透率 | B14: % | C14: - | D14: - | E14: - | F14: 0.3130512 | G14: 13.257149
A15: 其中：0流量家庭宽带客户数 | B15: 万户 | C15: 4675.2941 | D15: 0.027086511 | E15: - | F15: - | G15: -
A16: 其中：0流量千兆家庭宽带客户数 | B16: 万户 | C16: 903.4231 | D16: 0.036901216 | E16: - | F16: - | G16: -
A17: 2.家庭宽带客户活跃率 | B17: % | C17: 0.82445529 | D17: -0.38114779 | E17: -1.7054364 | F17: - | G17: -
A18: 其中：千兆家庭宽带客户活跃率 | B18: % | C18: 0.89035726 | D18: -0.11659876 | E18: -1.3978904 | F18: - | G18: -
A19: 3.净增家庭宽带客户数 | B19: 万户 | C19: 125.9664 | D19: -0.38004451 | E19: -0.46359865 | F19: 329.1526 | G19: -0.26793142
A20: 其中：速率在(0,100M)家庭宽带客户数 | B20: 万户 | C20: 2.2724 | D20: -0.92678039 | E20: -0.49543709 | F20: 33.3078 | G20: -
A21: 速率在[100M,300M)家庭宽带客户数 | B21: 万户 | C21: -84.0823 | D21: - | E21: - | F21: -175.699 | G21: -
A22: 速率在[300M,500M)家庭宽带客户数 | B22: 万户 | C22: -8.0556 | D22: -1.2275002 | E22: - | F22: 27.3536 | G22: -0.39251346
A23: 速率在[500M,1000M)家庭宽带客户数 | B23: 万户 | C23: 7.9813 | D23: - | E23: - | F23: -5.1729 | G23: -
A24: 千兆家庭宽带客户数 | B24: 万户 | C24: 207.8506 | D24: -0.13937954 | E24: -0.45809737 | F24: 449.3631 | G24: -0.30437135
A25: 4.移动高清客户数 | B25: 万户 | C25: - | D25: - | E25: - | F25: 20968.545 | G25: 0.069170717
A26: 净增移动高清客户数 | B26: 万户 | C26: 72.5731 | D26: -0.51850719 | E26: -0.5205671 | F26: 223.2983 | G26: -0.37815073
A27: 移动高清客户渗透率 | B27: % | C27: - | D27: - | E27: - | F27: 0.78501075 | G27: -0.51635583
A28: 移动高清客户活跃率 | B28: % | C28: 0.57757348 | D28: 1.9199528 | E28: 0.30113536 | F28: - | G28: -
A29: 三、户均收入
A30: 1.家庭客户综合ARPU | B30: 元/户·月 | C30: 43.460275 | D30: -0.015603649 | E30: -0.0033463725 | F30: 43.814265 | G30: 0.00085963436
A31: 2.家庭宽带ARPU | B31: 元/户·月 | C31: 28.14668 | D31: -0.009549189 | E31: 0.0071869188 | F31: 28.288796 | G31: 0.0074738962
A32: 四、网络能力
A33: 家庭宽带端口数 | B33: 万个 | C33: - | D33: - | E33: - | F33: 47076.791 | G33: 0.066265605
A34: 家庭宽带端口实装率 | B34: % | C34: - | D34: - | E34: - | F34: 0.56739544 | G34: 0.52393955
A35: 五、市场份额
A36: 1.家庭宽带客户份额 | B36: % | C36: - | D36: - | E36: - | F36: 0.48455184 | G36: 0.32536135
A37: 家庭宽带客户净增份额 | B37: % | C37: 0.50806972 | D37: 58.58561 | E37: -9.4474063 | F37: 0.50806972 | G37: -9.4474063
A38: 2.移动高清客户份额 | B38: % | C38: - | D38: - | E38: - | F38: 0.51743887 | G38: 1.0165663
A39: 移动高清客户净增份额 | B39: % | C39: 0.53577847 | D39: -14.79817 | E39: -11.448825 | F39: 0.53577847 | G39: -11.448825
A40: 注：1.家庭宽带收入包含裸宽带、融合宽带、装移机收入、智能组网
A41: 2.千兆家庭宽带客户渗透率=千兆家庭宽带客户数/家庭宽带客户数*100%
A42: 3.家庭宽带客户活跃率=家庭宽带活跃客户数/家庭宽带客户数*100%，千兆家庭宽带客户活跃率=千兆家庭宽带活跃客户数/千兆家庭宽带客户数*100%
A43: 4.移动高清客户渗透率=移动高清客户数/家庭宽带客户数*100%，移动高清客户活跃率=移动高清活跃客户数/移动高清客户数*100%
A44: 5.家庭客户综合ARPU=家庭市场收入/家庭宽带客户数，家庭宽带ARPU=家庭宽带收入（裸宽带收入+融合宽带收入）/家庭宽带客户数
A45: 6.市场份额根据工业和信息化部公布数据计算得出，为上月值
A46: =个人市场!A55+1 -> 8

Sheet 政企市场
A1: 政企市场整体情况表（9/16）
A2: =主要经营情况表!A2 -> 45323
A3: 指标 | B3: 单位 | C3: 本月实际 | D3: 比上月± | E3: 比上年同期± | F3: 本年累计 | G3: 比上年同期±
A4: 一、收入规模
A5: 政企市场收入 | B5: 亿元 | C5: 188.18417 | D5: -0.10391323 | E5: 0.076305685 | F5: 398.19082 | G5: 0.072843764
A6: 其中：政企市场增量收入 | B6: 亿元 | C6: 13.341491 | D6: -0.025798906 | E6: -0.43232353 | F6: 27.036292 | G6: -0.56737174
A7: 其中：专线业务收入 | B7: 亿元 | C7: 33.222869 | D7: -0.0032442885 | E7: 0.033708264 | F7: 66.553873 | G7: 0.026549739
A8: DICT业务收入 | B8: 亿元 | C8: 106.18986 | D8: -0.17882504 | E8: 0.078476027 | F8: 235.5044 | G8: 0.068604181
A9: 其中：行业云收入 | B9: 亿元 | C9: 63.404992 | D9: -0.19070301 | E9: 0.050326351 | F9: 141.75076 | G9: 0.092528939
A10: IDC业务收入 | B10: 亿元 | C10: 29.304354 | D10: 0.067907152 | E10: 0.089022649 | F10: 56.745273 | G10: 0.041271252
A11: ICT业务收入 | B11: 亿元 | C11: 22.690997 | D11: -0.32193021 | E11: 0.21399756 | F11: 56.155099 | G11: 0.098746852
A12: 应用及信息化业务收入 | B12: 亿元 | C12: 9.9171228 | D12: -0.069674505 | E12: 0.2414642 | F12: 20.576965 | G12: 0.25421524
A13: 物联网业务收入 | B13: 亿元 | C13: 20.876251 | D13: -0.21902232 | E13: 0.17832461 | F13: 47.60717 | G13: 0.21353504
A14: 其中：物联网流量收入 | B14: 亿元 | C14: 6.5401682 | D14: -0.039688324 | E14: 0.20801528 | F14: 13.350632 | G14: 0.25220315
A15: 物联网服务费收入 | B15: 亿元 | C15: 14.138978 | D15: -0.28414368 | E15: 0.1629365 | F15: 33.890118 | G15: 0.19786832
A16: 政企外部欠费原值 | B16: 亿元 | C16: - | D16: - | E16: - | F16: 705.41443 | G16: 0.41909694
A17: 二、业务发展
A18: 1.政企客户数 | B18: 万家 | C18: -33.109 | D18: - | E18: -3.9856709 | F18: 2779.3216 | G18: 0.21174131
A19: 2.政企成员数 | B19: 万户 | C19: -5.5889 | D19: - | E19: -1.0258948 | F19: 14526.877 | G19: 0.016708938
A20: 3.专线订购条数 | B20: 万条 | C20: 29.5518 | D20: -0.55692726 | E20: -0.54440648 | F20: 3958.1642 | G20: 0.18756934
A21: （1）互联网专线订购条数 | B21: 万条 | C21: 1.8427 | D21: -0.4980797 | E21: 0.34288005 | F21: 176.3126 | G21: 0.093507769
A22: （2）企业宽带订购条数 | B22: 万条 | C22: 23.5115 | D22: -0.56879571 | E22: -0.59630811 | F22: 3349.7899 | G22: 0.20363038
A23: （3）数据专线订购条数 | B23: 万条 | C23: 4.1975 | D23: -0.50622294 | E23: -0.20062845 | F23: 432.0612 | G23: 0.11158701
A24: 4.IDC外部客户已计费机架数 | B24: 万架 | C24: -0.2319 | D24: - | E24: - | F24: 16.6955 | G24: -
A25: IDC外部客户已计费机架总功率数 | B25: 万千瓦 | C25: -0.41453 | D25: - | E25: - | F25: 91.975058 | G25: -
A26: 5.IDC外部客户开通带宽量 | B26: 万Gbps | C26: 0.486185 | D26: - | E26: - | F26: 30.780166 | G26: -
A27: 其中：IDC外部客户计费带宽量 | B27: 万Gbps | C27: -0.772653 | D27: - | E27: - | F27: 15.735822 | G27: -
A28: 6.物联网卡客户数 | B28: 万户 | C28: -58.0275 | D28: - | E28: -1.0270899 | F28: 131391.07 | G28: 0.21615627
A29: 其中：NB-IoT客户数 | B29: 万户 | C29: -444.8255 | D29: - | E29: -2.1234755 | F29: 14887.254 | G29: 0.053143671
A30: 其中：车联网卡客户数 | B30: 万户 | C30: 108.9383 | D30: - | E30: - | F30: 22901.223 | G30: -
A31: 其中：前装车联网卡客户数 | B31: 万户 | C31: 5211.0377 | D31: 0.02935176 | E31: - | F31: 5211.0377 | G31: -
A32: 物联网流量 | B32: 亿MB | C32: 2648.766 | D32: -0.093270572 | E32: 1.3214601 | F32: 5569.9969 | G32: 1.4408183
A33: 三、户均收入
A34: 1.互联网专线ARPU | B34: 元/户·月 | C34: 658.55045 | D34: -0.027576271 | E34: -0.15068183 | F34: 668.39947 | G34: -0.15676149
A35: 2.企业宽带ARPU | B35: 元/户·月 | C35: 21.524756 | D35: 0.054036929 | E35: -0.081159574 | F35: 20.992598 | G35: -0.099208312
A36: 3.数据专线ARPU | B36: 元/户·月 | C36: 401.36301 | D36: -0.047078225 | E36: -0.066743812 | F36: 411.54956 | G36: -0.040310451
A37: 四、市场份额
A38: 1.政企市场收入份额 | B38: % | C38: - | D38: - | E38: - | F38: 0.40367639 | G38: -0.37351247
A39: 政企市场增量收入份额 | B39: % | C39: - | D39: - | E39: - | F39: 0.35678729 | G39: -34.821271
A40: 2.专线业务收入份额 | B40: % | C40: - | D40: - | E40: - | F40: 0.29690013 | G40: 1.7822262
A41: 3.DICT收入份额 | B41: % | C41: - | D41: - | E41: - | F41: 0.41362015 | G41: -1.1773593
A42: 4.物联网客户份额 | B42: % | C42: - | D42: - | E42: - | F42: 0.55873665 | G42: -1.0527457
A43: 其中：物联网客户净增份额 | B43: % | C43: -0.065622755 | D43: -46.177676 | E43: 13.674102 | F43: -0.065622755 | G43: 13.674102
A44: 5.NB-IoT客户份额 | B44: % | C44: - | D44: - | E44: - | F44: 0.35809572 | G44: -3.5502059
A45: 其中：NB-IoT客户净增份额 | B45: % | C45: -0.81741004 | D45: - | E45: -103.65874 | F45: -0.81741004 | G45: -103.65874
A46: 注：1.行业云收入=公有云+私有云收入，其中公有云收入=云标准化产品[IaaS+PaaS（含9one标准产品、云视讯）+SaaS]+云网收入（含IDC入云带宽）+云数+
A47: 云智+云边+云通信;私有云收入=云定制化项目收入（含ICT9one）+云边_局域边缘云+云数_ICT大数据收入
A48: 2.政企外部欠费原值为省公司政企业务应收账款原值（不含集团内部关联单位）
A49: 3.政企客户数即有效集团客户数，指截至统计周期末，订购了集团单位产品（包含集团V网，不含校园V网、乡情网、家庭V网）或集团代付业务，且近三
A50: 个月累计通信和信息化收入大于0，处于在网状态的A、B、C、D类集团客户数
A51: 4.政企成员数为A、B、C类集团客户所包含的成员数,为集团在网、成员在网、剔除非18-60岁年龄、剔除物联网和IMS固话用户
A52: 5.前装车联网卡客户数为上月值
A53: 6.收入份额取自政企事业部，物联网客户份额根据工业和信息化部公布数据计算得出，均为上月值
A54: =家庭市场!A46+1 -> 9

Sheet 业务-能力投资
A1: 网络能力与投资情况表（10/16）
A2: =主要经营情况表!A2 -> 45323
A3: 指标名称 | B3: 单位 | C3: 本月净增 | D3: 本年累计净增 | E3: 到达数 | F3: 比上年同期±
A4: 一、通信能力
A5: 1.基站数 | B5: 万个 | C5: 1.8156 | D5: 5.5786 | E5: 667.1712 | F5: 0.098158941
A6: 其中：GSM基站数 | B6: 万个 | C6: -0.5181 | D6: -1.3285 | E6: 90.0401 | F6: -0.11914948
A7: 4G基站数 | B7: 万个 | C7: 0.7937 | D7: 0.7668 | E7: 337.7592 | F7: 0.010211003
A8: 其中：TD-LTE基站数 | B8: 万个 | C8: 0.6906 | D8: 0.3805 | E8: 218.7406 | F8: -0.0019938169
A9: LTE FDD基站数 | B9: 万个 | C9: 0.1031 | D9: 0.3863 | E9: 119.0186 | F9: 0.033438224
A10: 5G基站数 | B10: 万个 | C10: 1.5105 | D10: 5.9867 | E10: 200.5492 | F10: 0.51223897
A11: 其中：5G 700MHz基站数 | B11: 万个 | C11: 0.5874 | D11: 1.9613 | E11: 63.9137 | F11: 0.29476149
A12: 其中：开通轻量化（RedCap）功能5G基站数 | B12: 万个 | C12: -5.0336 | D12: - | E12: 14.1953 | F12: -
A13: NB-IoT基站数 | B13: 万个 | C13: 0.0295 | D13: 0.154 | E13: 38.8227 | F13: 0.012230925
A14: 2.载频数 | B14: 万个 | C14: 1.5585 | D14: 10.6135 | E14: 1885.6945 | F14: -0.0072653521
A15: 其中：GSM载频数 | B15: 万个 | C15: -1.5297 | D15: -5.6142 | E15: 299.7 | F15: -0.19532607
A16: 4G载频数 | B16: 万个 | C16: -0.523 | D16: 5.8994 | E16: 1015.2292 | F16: -0.035834911
A17: 其中：TD-LTE载频数 | B17: 万个 | C17: -0.684 | D17: 5.3817 | E17: 685.5425 | F17: -0.061029825
A18: LTE FDD载频数 | B18: 万个 | C18: 0.161 | D18: 0.5177 | E18: 329.6867 | F18: 0.021139398
A19: 5G载频数 | B19: 万个 | C19: 3.5599 | D19: 9.8713 | E19: 462.307 | F19: 0.26193297
A20: 其中：5G 700MHz载频 | B20: 万个 | C20: 1.5017 | D20: 4.2648 | E20: 185.407 | F20: 0.28302594
A21: NB-IoT载频数 | B21: 万个 | C21: 0.0513 | D21: 0.4604 | E21: 108.4583 | F21: 0.006738926
A22: 3.有线宽带端口数 | B22: 万个 | C22: 206.9113 | D22: 621.6178 | E22: 53673.118 | F22: 0.071641574
A23: 其中：家庭宽带端口数 | B23: 万个 | C23: 158.8879 | D23: 606.9811 | E23: 47076.791 | F23: 0.066265605
A24: 4.10G PON端口数 | B24: 万个 | C24: 10.6403 | D24: 31.5048 | E24: 775.5719 | F24: 0.62497384
... A28: 其中：租用铁塔公司的铁塔数 | B28: 万个 | C28: 0.15 | D28: 0.0542 | E28: 146.2709 | F28: 0.0089262558
A29: 二、资本开支
A30: 资本开支合计 | B30: 亿元 | C30: 39.959988 | D30: - | E30: 134.1946 | F30: -0.15211787
A31: 其中：连接 | B31: 亿元 | C31: 17.381591 | D31: - | E31: 82.873655 | F31: -
A32: 算力 | B32: 亿元 | C32: 11.334483 | D32: - | E32: 27.514411 | F32: -
A33: 能力 | B33: 亿元 | C33: 5.9397704 | D33: - | E33: 7.9706984 | F33: -
A34: 基础 | B34: 亿元 | C34: 5.5301776 | D34: - | E34: 16.486849 | F34: -
A35: 其中：移动通信网 | B35: 亿元 | C35: 13.525477 | D35: - | E35: 71.736476 | F35: -0.094847103
A36: 传输网 | B36: 亿元 | C36: 9.8387145 | D36: - | E36: 31.428097 | F36: -0.24476593
A37: 业务支撑网 | B37: 亿元 | C37: 11.950279 | D37: - | E37: 18.953977 | F37: -0.35531466
A38: 局房土建 | B38: 亿元 | C38: 2.6096729 | D38: - | E38: 8.0176729 | F38: 0.35736518
A39: 其他 | B39: 亿元 | C39: 2.0358449 | D39: - | E39: 4.0583779 | F39: 0.93619973
A40: 注：资本开支中连接主要包括5G、核心网、千兆家宽、集客专线、综合业务接入区、NB-IoT等；算力主要包括移动云、IT云、网络云、
A41: 数据承载网、省际传送网、数据中心等；能力主要包括智慧中台、自智网络、业务系统、支撑系统等；基础主要包括国际通信
A42: 设施、省内传送网、传输管道、汇聚机房、办公用房等。
A43: =政企市场!A54+1 -> 10

Sheet 财务-收入
A1: 营运收入情况表（11/16）
B2: =主要经营情况表!A2 -> 45323 | G2: 单位：亿元
A3: 指标 | B3: 单月 | C3: 比上月± | D3: 比上年同期± | E3: 本年累计 | F3: 上年同期 | G3: 比上年同期±
A4: 营运收入 | B4: 906.01272 | C4: -0.071866415 | D4: 0.027292438 | E4: 1882.179 | F4: 1823.3588 | G4: 0.032259278
A5: 一、通信服务收入 | B5: 776.99523 | C5: -0.032483166 | D5: 0.020870014 | E5: 1580.0771 | F5: 1548.1577 | G5: 0.020617651
A6: （一）语音业务收入 | B6: 59.046238 | C6: -0.078115975 | D6: -0.081759664 | E6: 123.09577 | F6: 130.36127 | G6: -0.055733619
A7: 1.移动语音通话收入 | B7: 55.231356 | C7: -0.06611554 | D7: -0.088748457 | E7: 114.37289 | F7: 122.64699 | G7: -0.067462789
A8: 2.语音增值业务收入 | B8: 1.5788566 | C8: 0.019215588 | D8: 0.038716491 | E8: 3.1279466 | F8: 2.9562264 | G8: 0.058087632
A9: 3.月租费收入 | B9: 1.7286223 | C9: -0.38219813 | D9: 0.24457597 | E9: 4.5266428 | F9: 3.1905438 | G9: 0.41876845
A10: 4.固定语音通话收入 | B10: 0.50740283 | C10: -0.095358926 | D10: -0.35306207 | E10: 1.0682914 | F10: 1.5675078 | G10: -0.3184778
A11: （二）数据业务收入 | B11: 693.35844 | C11: -0.036767898 | D11: 0.022695976 | E11: 1413.1833 | F11: 1381.4214 | G11: 0.022992224
A12: 1. 短彩信业务收入 | B12: 25.798936 | C12: -0.15034062 | D12: -0.056517341 | E12: 56.162793 | F12: 56.26067 | G12: -0.0017397185
A13: （1）短信业务收入 | B13: 25.503371 | C13: -0.15123819 | D13: -0.060497744 | E13: 55.551108 | F13: 55.833022 | G13: -0.0050492262
A14: 其中：点对点短消息收入 | B14: 2.6175535 | C14: 0.34444396 | D14: 0.35100217 | E14: 4.5644948 | F14: 3.9546045 | G14: 0.15422283
A15: 集团短信收入 | B15: 22.399943 | C15: -0.18860347 | D15: -0.092390809 | E15: 50.006598 | F15: 50.824363 | G15: -0.016090035
... A50: 其中：商品销售收入 | B50: 109.54985 | C50: -0.32198095 | D50: 0.011097856 | E50: 271.12325 | F50: 247.09566 | G50: 0.097240015
A51: ='业务-能力投资'!A43+1 -> 11

Sheet 财务-支出
A1: 营运支出情况表（12/16）
C2: =主要经营情况表!A2 -> 45323 | F2: 单位：亿元
A3: 指标 | B3: 单月 | C3: 比上月± | D3: 比上年同期± | E3: 本年累计 | F3: 上年同期 | G3: 比上年同期±
A4: 营运支出 | B4: 736.23642 | C4: -0.059298287 | D4: 0.075596822 | E4: 1518.8824 | F4: 1428.5927 | G4: 0.06320185
A5: 一、网络运营及支撑成本 | B5: 213.25316 | C5: -0.045629336 | D5: 0.022403368 | E5: 436.70215 | F5: 438.65921 | G5: -0.0044614652
A6: 1.维护支撑费用 | B6: 137.33796 | C6: -0.07211245 | D6: 0.054801257 | E6: 285.34939 | F6: 283.99022 | G6: 0.0047859924
A7: 2.能源使用费 | B7: 34.4874 | C7: -0.035831689 | D7: 0.022440319 | E7: 70.256465 | F7: 68.47035 | G7: 0.026085974
A8: 3.铁塔使用费 | B8: 21.160236 | C8: 0.062528604 | D8: -0.0052282572 | E8: 41.075216 | F8: 44.760773 | G8: -0.082338996
A9: 4.电路及网元使用费 | B9: 11.977713 | C9: 0.016396129 | D9: 0.29600362 | E9: 23.762207 | F9: 16.163665 | G9: 0.47010022
A10: 5.其他资产使用费 | B10: 2.9202502 | C10: 0.27825407 | D10: -0.53785572 | E10: 5.2048118 | F10: 11.570315 | G10: -0.55015816
A11: 6.其他 | B11: 5.3695987 | C11: -0.055389764 | D11: -0.31288413 | E11: 11.054058 | F11: 13.703894 | G11: -0.1933637
A12: 二、折旧及摊销 | B12: 176.39873 | C12: -0.0024893655 | D12: 0.013291268 | E12: 353.23768 | F12: 343.6143 | G12: 0.028006335
A13: 1.物业、厂房及设备折旧费 | B13: 146.96326 | C13: -0.0017533276 | D13: 0.015429623 | E13: 294.18464 | F13: 285.66472 | G13: 0.029824902
A14: 2.使用权资产折旧费 | B14: 24.940888 | C14: -0.0034736999 | D14: 0.021986143 | E14: 49.968716 | F14: 47.975002 | G14: 0.041557337
A15: 3.无形资产摊销 | B15: 4.4945866 | C15: -0.020731102 | D15: -0.092088118 | E15: 9.0843236 | F15: 9.9745821 | G15: -0.089252716
... A19: 2.业务宣传费 | B19: 1.0222251 | C19: -0.081029622 | D19: 0.29555611 | E19: 2.1345843 | F19: 1.6336244 | G19: 0.30665548
A20: 3.展览费 | B20: 0.10644755 | C20: - | D20: 1.6461758 | E20: 0.10604335 | F20: 0.039620803 | G20: 1.6764564
A21: 4.社会渠道相关费用 | B21: 21.878573 | C21: 0.035305733 | D21: -0.17218514 | E21: 43.011048 | F21: 54.093287 | G21: -0.20487272
A22: 其中：社会渠道服务费 | B22: 20.408959 | C22: 0.034914372 | D22: -0.17318193 | E22: 40.129392 | F22: 50.734686 | G22: -0.20903437
A23: 社会渠道手续费 | B23: 1.4696135 | C23: 0.040771443 | D23: -0.15808983 | E23: 2.881656 | F23: 3.3586014 | G23: -0.14200714
A24: 5.营销支撑费 | B24: 20.274268 | C24: 0.22059339 | D24: 2.1589812 | E24: 36.884442 | F24: 12.341901 | G24: 1.9885542
A25: 6.客户服务费 | B25: 3.1045372 | C25: -0.21870595 | D25: -0.16924726 | E25: 7.0781207 | F25: 7.2138363 | G25: -0.018813243
A26: 7.欠费催缴费 | B26: 0.013961902 | C26: 0.45245915 | D26: 0.27961068 | E26: 0.023574497 | F26: 0.021934055 | G26: 0.074789761
A27: 五、销售产品成本 | B27: 128.06869 | C27: -0.22091227 | D27: 0.063086109 | E27: 292.45157 | F27: 272.23711 | G27: 0.074253136
A28: 六、其他营运支出 | B28: 52.912002 | C28: -0.10300812 | D28: 0.31682639 | E28: 111.90028 | F28: 85.398131 | G28: 0.31033636
A29: 其中：坏账准备 | B29: 16.651384 | C29: -0.39537809 | D29: 0.22595435 | E29: 44.191543 | F29: 28.486931 | G29: 0.55129181
A30: 坏账率 | B30: 0.021430484 | C30: -1.2862607 | D30: 0.35850084 | E30: 0.027967967 | F30: 0.018400536 | G30: 0.95674309
A31: 1.网间互联支出 | B31: 15.335309 | C31: -0.11234919 | D31: -0.24339381 | E31: 32.611595 | F31: 33.744646 | G31: -0.033577197
A32: 2.呆账减值亏损 | B32: 16.66102 | C32: -0.39488996 | D32: 0.23214429 | E32: 44.194888 | F32: 28.425569 | G32: 0.55475822
... A36: 6.其他 | B36: 18.070382 | C36: 0.83073122 | D36: 4.3863264 | E36: 27.940963 | F36: 17.207442 | G36: 0.62377206
A37: 注：1.能源使用费是指动力水电取暖费等
A38: 2.坏账率=坏账准备/通信服务收入*100%
A39: ='财务-收入'!A51+1 -> 12

Sheet 市值管理
A1: 资本市场市值管理情况表（13/16）
A2: =主要经营情况表!A2 -> 45323
A3: 指标 | B3: 单位 | C3: 本月 | D3: 比上月± | F3: 比上年同期± | G3: 本月 | H3: 比上月± | J3: 比上年同期±
A4: 一、股价表现1 | C4: 港股（港元） | G4: A股（人民币）
A5: 1.中国移动股价-当期期末 | B5: 元/股 | C5: 65.8 | D5: -0.0097817908 | F5: 0.11904762 | G5: 102 | H5: -0.0041979889 | J5: 0.32069437
A6: -当期平均 | B6: 元/股 | C6: 66.816667 | D6: 0.01978332 | F6: 0.16461138 | G6: 103.134 | H6: 0.050020825 | J6: 0.38808499
A7: 2.中国电信股价-当期期末 | B7: 元/股 | C7: 4.17 | D7: 0.037313433 | F7: 0.066496164 | G7: 5.85 | H7: 0.017391304 | J7: 0.037638795
A8: -当期平均 | B8: 元/股 | C8: 4.1371429 | D8: 0.078146682 | F8: 0.05579759 | G8: 5.9046667 | H8: 0.095855126 | J8: 0.14489102
A9: 3.中国联通股价-当期期末 | B9: 元/股 | C9: 5.44 | D9: 0.014925373 | F9: -0.048951049 | G9: 4.8 | H9: 0.061946903 | J9: -0.065857076
A10: -当期平均 | B10: 元/股 | C10: 5.4347619 | D10: 0.09091936 | F10: -0.046951003 | G10: 4.6606667 | H10: 0.1094424 | J10: -0.065641024
A11: 4.三家股价平均变化-当期期末 | B11: % | C11: - | D11: 0.014152338 | F11: 0.045530911 | G11: - | H11: 0.025046739 | J11: 0.097492031
A12: -当期平均 | B12: % | C12: - | D12: 0.03736078 | F12: 0.057819324 | G12: - | H12: 0.085106117 | J12: 0.15577833
A13: 5.市场情况 | C13: 恒生指数 | G13: 上证指数
A14: 大盘指数-当期期末 | B14: 点 | C14: 16511.44 | D14: 0.066281263 | F14: -0.16549631 | G14: 3015.1712 | H14: 0.081269171 | J14: -0.080629855
A15: -当期平均 | B15: 点 | C15: 16140.913 | D15: 0.010589252 | F15: -0.22962262 | G15: 2895.4105 | H15: 0.0079122859 | J15: -0.11448873
A17: 指标 | B17: 单位 | C17: 本月 | F17: 比上月± | H17: 比上年同期±
A18: 二、市值规模与排名2
A19: 1.中国移动-市值 | B19: 亿元人民币 | C19: 13145.782 | F19: -0.0094913634 | H19: 0.12688585
A20: 全球运营商中市值排名 | B20: 位 | C20: 2 | F20: 持平 | H20: 持平
A21: 2.中国电信-市值 | B21: 亿元人民币 | C21: 5013.7302 | F21: 0.018229662 | H21: -0.027754568
A22: 全球运营商中市值排名 | B22: 位 | C22: 9 | F22: 持平 | H22: 下降2位
A23: 3.中国联通-市值 | B23: 亿元人民币 | C23: 1510.6181 | F23: 0.014925373 | H23: -0.048951049
A24: 全球运营商中市值排名 | B24: 位 | C24: 26 | F24: 持平 | H24: 上升2位
A26: 指标 | B26: 单位 | C26: 境外主要投行平均预测（港股) | G26: 境内主要投行平均预测（A股）
C27: 绝对值 | E27: 增幅 | G27: 绝对值 | I27: 增幅
A28: 三、资本市场对上市公司2023年业绩预期3
A29: 1.营运收入 | B29: 亿元人民币 | C29: 10105.26 | E29: 0.0782 | G29: 10231.448 | I29: 0.091635023
A30: 2.通信服务收入 | B30: 亿元人民币 | C30: 8717.27 | E30: 0.0735 | G30: - | I30: -
A31: 3.EBITDA | B31: 亿元人民币 | C31: 3504.75 | E31: 0.0647 | G31: - | I31: -
A32: 4.净利润 | B32: 亿元人民币 | C32: 1348.93 | E32: 0.0752 | G32: 1357.4558 | I32: 0.081991594
A33: 5.资本开支 | B33: 亿元人民币 | C33: 1831.06 | E33: -0.0027 | G33: 1832 | I33: -0.010799136
A34: 6.派息率 | B34: % | C34: 0.7055 | E34: 3.55pp | G34: - | I34: -
A35: 7.投资目标价 | B35: 元/股 | C35: 82.0港元 | G35: 111.5元人民币
A36: 注：1、当期期末为当期开市最后一天收盘价；当期平均为当期开市每天收盘价的平均值。
A37: 2、中国移动、中国电信市值按两地股数*股价折算为同一种货币后合计，中国联通按港股市值，排名按月末汇率折算美元后与国际运营商比较确定。
A38: 截至2月末，全球运营商按市值排名前五顺序为T-Mobile, 中国移动, Verizon, AT&T, 德国电信。
A39: 截至2月末，中国联通港股公司+A股公司市值合计为3,037亿人民币。
A40: 3、资本市场对上市公司2023年业绩预期为境内外主要投行对上市公司主要业绩指标全年表现及股票投资目标价的最新预测。
A41: ='财务-支出'!A39+1 -> 13

Sheet 信息服务业重点指标对标表
A1: 信息服务业重点指标对标表（14/16）
A2: =主要经营情况表!A2 -> 45323
A3: 国内信息服务业收入情况表 | E3: 国内信息服务业
A4: 指标 | D4: 单位 | E4: 本月 | F4: 比上月± | G4: 比上年同期± | H4: 本年累计 | I4: 比上年同期 ±
A5: 信息服务业收入 | D5: 亿元 | E5: 15878 | F5: 0.040157222 | G5: 0.087373912 | H5: 157541 | I5: 0.11824646
A6: 其中：通信业收入 | D6: 亿元 | E6: 1252 | F6: -0.092753623 | G6: -0.017865889 | H6: 16800 | I6: 0.062
A7: 软件及信息服务业收入 | D7: 亿元 | E7: 12811 | F7: 0.045283943 | G7: 0.092647915 | H7: 123258 | I7: 0.134
A8: 互联网和相关服务业收入 | D8: 亿元 | E8: 1815 | F8: 0.11418048 | G8: 0.1324997 | H8: 17483 | I8: 0.068
A9: 其中：通信业收入占信息服务业收入比 | D9: % | E9: 0.078851241 | F9: -1.1551642 | G9: -0.84492421 | H9: 0.10663891 | I9: -0.56478916
A10: 我公司收入占信息服务业收入比 | D10: % | E10: 0.038384658 | F10: -0.73890209 | G10: -0.76622028 | H10: 0.05506126 | I10: -0.28218048
A11: 注：1.该表取自工信部网站发布数据，因未公开1月数据，仍展示23年12月值。
A12: 2.从2022年开始规模以上互联网和相关服务企业口径由上年互联网和相关服务收入500万元以上调整为2000万元及以上
A13: 3.通信业收入为三家基础运营企业主营业务收入
A20: 国内外信息服务企业情况表
I21: 单位：人民币亿元
A22: 企业名称 | B22: 2023年1-3季度 营运收入 | D22: 2023年1-3季度 净利润 | F22: 2022年 营运收入 | H22: 2022年 净利润
B23: 本年累计 | C23: 同比增幅 | D23: 本年累计 | E23: 同比增幅 | F23: 本年累计 | G23: 同比增幅 | H23: 本年累计 | I23: 同比增幅
A24: 一、国际运营商
A25: 中国移动 | B25: 7755.6 | C25: 0.072 | D25: 1056.11 | E25: 0.071 | F25: 9372.59 | G25: 0.10492209 | H25: 1255.94 | I25: 0.079858305
A26: Verizon | B26: 6933.74 | C26: -0.027 | D26: 1028.94 | E26: -0.025 | F26: 9203.6261 | G26: 0.02411442 | H26: 1462.787 | I26: -0.038464939
A27: Comcast | B27: 6335.72 | C27: -0.006 | D27: 838.48 | E27: 4.825 | F27: 8167.2723 | G27: 0.043321734 | H27: 331.25924 | I27: -0.64396732
A28: AT&T | B28: 6341.83 | C28: 0.011 | D28: 914.8 | E28: -0.19 | F28: 8121.1315 | G28: -0.099203211 | H28: -474.52466 | I28: -1.3284604
A29: Deutsche Telekom | B29: 6292.72 | C29: -0.024 | D29: 1433.72 | E29: 1.694 | F29: 8091.3701 | G29: 0.061236794 | H29: 565.83651 | I29: 0.91594828
A30: NTT | B30: 5057.35 | C30: 0.043 | D30: 436.28 | E30: 0.011 | F30: 6733.7491 | G30: 0.08059952 | H30: 662.67981 | I30: 0.029269248
A31: 中国电信 | B31: 3842.56 | C31: 0.064 | D31: 271.43 | E31: 0.102 | F31: 4814.48 | G31: 0.095312738 | H31: 276.76 | I31: 0.058396115
A32: 中国联通 | B32: 2816.91 | C32: 0.067 | D32: 173.77 | E32: 0.105 | F32: 3549.44 | G32: 0.082628243 | H32: 168.37 | I32: 0.16061212
A33: Vodafone | B33: 2519.27 | C33: -0.037 | D33: - | E33: - | F33: 3232.3614 | G33: 0.0027643703 | H33: 872.34012 | I33: 3.448251
A34: Orange | B34: 2478.9 | C34: 0.013 | D34: - | E34: - | F34: 3074.2776 | G34: 0.02231022 | H34: 185.07613 | I34: 2.3637532
A35: KDDI | B35: 2174 | C35: 0.022550888 | D35: 261.94636 | E35: 0.087992231 | F35: 2907.4026 | G35: 0.04131927 | H35: 378.50824 | I35: 0.0079913725
A36: Telefonica | B36: 2323.063 | C36: 0.023711367 | D36: 96.155185 | E36: -0.15042822 | F36: 2828.3339 | G36: 0.018229498 | H36: 142.21937 | I36: -0.75285732
A37: BT | B37: 1363.3915 | C37: 0.015 | D37: - | E37: - | F37: 1462.5753 | G37: -0.0059601057 | H37: 134.72298 | I37: 0.49529042
A38: SK Telecom | B38: 706.73 | C38: 0.013 | D38: 51.78 | E38: 0.324 | F38: 902.16063 | G38: 0.03322 | H38: 49.413299 | I38: -0.6081706
A39: LG U+ | B39: 570.0706 | C39: 0.024901405 | D39: 28.3686 | E39: 0.043514763 | F39: 724.96137 | G39: 0.0039607044 | H39: 34.542759 | I39: -0.085087508
A40: 二、软件和互联网企业
A41: Amazon | B41: 28397.71 | C41: 0.11 | D41: 1389.01 | E41: - | F41: 34570.887 | G41: 0.093995173 | H41: -183.08379 | I41: -1.0815849
A42: Google | B42: 15508.67 | C42: 0.069 | D42: 3725.44 | E42: 0.146 | F42: 19023.764 | G42: 0.097808156 | H42: 4033.7623 | I42: -0.21089474
A43: 阿里巴巴集团 | B43: 6671.46 | C43: 0.082 | D43: 816.92 | E43: - | F43: 8686.87 | G43: 0.018316371 | H43: 655.73 | I43: 0.39282907
A44: 腾讯 | B44: 4538.19 | C44: 0.108 | D44: 901.98 | E44: 0.103 | F44: 5545.52 | G44: -0.0099371918 | H44: 1887.09 | I44: -0.17163865
A45: 注：1.根据2022年《财富》世界500强排名对运营商部分进行更新，补充了排名更高的 Vodafone（沃达丰）
A46: 和 Orange（法国电信），用以替换 BT（英国电信）和 Telefonica（西班牙电信）
A47: 注: 1.取自各企业披露数据，本年累计为按汇率折算成人民币的金额，同比增幅为各企业本位币的增幅
A48: 2.我公司为港股披露数据,净利润未剔除非控制性权益
A49: 3.Vodafone、Orange净利润每半年披露一次，Q3不披露净利润
A50: 4.Amazon和阿里巴巴2022年Q1-Q3净利润为负值，因此无法计算增幅
A51: 5.自2023Q1起，BT实施了季报披露方式的调整，每半年披露一次净利润
A52: =市值管理!A41+1 -> 14

Sheet 电信行业主要指标情况表
A1: 电信行业主要指标情况表（15/16）
A2: =主要经营情况表!A2 -> 45323
A3: 指标 | C3: 单位 | D3: 行业 | E3: 移动 | F3: 电信 | G3: 联通
A4: 一、经济效益
A5: （一）通信服务收入 | B5: 本年累计 | C5: 亿元 | D5: 1461.3438 | E5: 728.17964 | F5: 427.94273 | G5: 305.22141
B6: 同比变化 | C6: % | D6: 0.0426 | E6: 0.0285 | F6: 0.0556 | G6: 0.0589
A7: 其中：移动数据流量收入 | B7: 本年累计 | C7: 亿元 | D7: 517.82553 | E7: 309.11451 | F7: 124.39999 | G7: 84.311022
B8: 同比变化 | C8: % | D8: -0.0336 | E8: -0.043 | F8: -0.0123 | G8: -0.0295
B9: 市场份额 | C9: % | D9: - | E9: 0.59694723 | F9: 0.24023534 | G9: 0.16281743
B10: 市场份额同比变化 | C10: PP | D10: - | E10: -0.58634315 | F10: 0.51807357 | G10: 0.068784283
B11: 市场份额比年末变化 | C11: PP | D11: - | E11: -1.2254181 | F11: 1.0555255 | G11: 0.16989268
A12: 有线宽带收入 | B12: 本年累计 | C12: 亿元 | D12: 217.31769 | E12: 93.58478 | F12: 84.635519 | G12: 39.097391
B13: 同比变化 | C13: % | D13: 0.0559 | E13: 0.0836 | F13: 0.043 | G13: 0.021
B14: 市场份额 | C14: % | D14: - | E14: 0.43063581 | F14: 0.38945527 | G14: 0.17990892
B15: 市场份额同比变化 | C15: PP | D15: - | E15: 1.1008317 | F15: -0.48168485 | G15: -0.61496781
B16: 市场份额比年末变化 | C16: PP | D16: - | E16: -2.177645 | F16: 1.7342649 | G16: 0.44338005
A17: IPTV（互联网电视）收入 | B17: 本年累计 | C17: 亿元 | D17: 35.740584 | E17: 23.505706 | F17: 7.917528 | G17: 4.31735
B18: 同比变化 | C18: % | D18: 0.0365 | E18: 0.0598 | F18: -0.0383 | G18: 0.0603
B19: 市场份额 | C19: % | D19: - | E19: 0.65767549 | F19: 0.22152766 | G19: 0.12079685
B20: 市场份额同比变化 | C20: PP | D20: - | E20: 1.445918 | F20: -1.7230185 | G20: 0.27114638
B21: 市场份额比年末变化 | C21: PP | D21: - | E21: -0.38559741 | F21: -0.56421068 | G21: 0.94980808
A22: 政企信息化收入 | B22: 本年累计 | C22: 亿元 | D22: 332.7373 | E22: 107.5415 | F22: 139.8233 | G22: 85.372497
B23: 同比变化 | C23: % | D23: 0.1460224 | E23: 0.077407114 | F23: 0.20042573 | G23: 0.15293254
B24: 市场份额 | C24: % | D24: - | E24: 0.32320243 | F24: 0.4202213 | G24: 0.25657627
B25: 市场份额同比变化 | C25: PP | D25: - | E25: -2.0583331 | F25: 1.904444 | G25: 0.1537798
B26: 市场份额比年末变化 | C26: PP | D26: - | E26: -1.414969 | F26: 2.0768884 | G26: -0.66191942
A27: 物联网业务收入 | B27: 本年累计 | C27: 亿元 | D27: 27.548146 | E27: 12.88741 | F27: 3.989876 | G27: 10.67086
B28: 同比变化 | C28: % | D28: 0.1679 | E28: 0.2282 | F28: -0.019 | G28: 0.1819
B29: 市场份额 | C29: % | D29: - | E29: 0.46781406 | F29: 0.14483283 | G29: 0.38735311
B30: 市场份额同比变化 | C30: PP | D30: - | E30: 2.2967911 | F30: -2.7593533 | G30: 0.45883269
B31: 市场份额比年末变化 | C31: PP | D31: - | E31: -0.54962575 | F31: 0.35277178 | G31: 0.19685397
A32: （二）利润总额 | B32: 本年累计 | C32: 亿元 | D32: 156.23536 | E32: 93.273023 | F32: 47.110254 | G32: 15.852079
B33: 同比变化 | C33: % | D33: 0.0384 | E33: 0.0177 | F33: 0.0587 | G33: 0.1073
B34: 市场份额 | C34: % | D34: - | E34: 0.5970033 | F34: 0.30153389 | G34: 0.10146281
B35: 市场份额同比变化 | C35: PP | D35: - | E35: -1.2143037 | F35: 0.57817492 | G35: 0.6313364
B36: 市场份额比年末变化 | C36: PP | D36: - | E36: -16.418503 | F36: 14.95781 | G36: 1.4606933
A37: 注：1.本表数据为三家运营商报工信部的集团公司数据，源于工信部反馈，为上月值
A38: 2.IPTV（互联网电视）收入=移动高清业务收入+大屏点播业务收入
A39: 3.政企信息化收入=数据中心业务收入+云计算业务收入+大数据业务收入+集成业务收入
A40: =信息服务业重点指标对标表!A52+1 -> 15
A46: g

Sheet 电信行业主要指标情况表（续）
A1: 电信行业主要指标情况表（续）（16/16）
A2: =主要经营情况表!A2 -> 45323
A3: 指标 | C3: 单位 | D3: 行业 | E3: 移动 | F3: 电信 | G3: 联通
A4: 二、用户情况
A5: （一）移动电话客户数 | B5: 本期到达 | C5: 万户 | D5: 172938.93 | E5: 98613.81 | F5: 40904.97 | G5: 33420.16
B6: 同比变化 | C6: % | D6: 0.0257 | E6: 0.0164 | F6: 0.0427 | G6: 0.0331
B7: 市场份额 | C7: % | D7: - | E7: 0.57022332 | F7: 0.23652841 | G7: 0.19324833
B8: 市场份额比年末变化 | C8: PP | D8: - | E8: -0.056881829 | F8: 0.035805902 | G8: 0.021081709
B9: 年累计净增 | C9: 万户 | D9: 279.29 | E9: 61.04 | F9: 127.88 | G9: 90.37
A10: 其中：5G网络客户数 | B10: 本期到达 | C10: 万户 | D10: 81662.27 | E10: 46411.54 | F10: 20113.84 | G10: 15136.9
B11: 同比变化 | C11: % | D11: 0.4214 | E11: 0.3853 | F11: 0.4977 | G11: 0.4389
B12: 市场份额 | C12: % | D12: - | E12: 0.56833517 | F12: 0.24630518 | G12: 0.18535978
B13: 市场份额比年末变化 | C13: PP | D13: - | E13: -0.62341738 | F13: 0.36864095 | G13: 0.25478867
B14: 年累计净增 | C14: 万户 | D14: 1163.84 | E14: 159.6 | F14: 583.41 | G14: 420.83
A15: （二）有线宽带客户数 | B15: 本期到达 | C15: 万户 | D15: 64110.96 | E15: 30072.37 | F15: 22616.29 | G15: 11422.3
B16: 同比变化 | C16: % | D16: 0.0797 | E16: 0.0952 | F16: 0.0514 | G16: 0.0973
B17: 市场份额 | C17: % | D17: - | E17: 0.46906754 | F17: 0.35276792 | G17: 0.17816454
B18: 市场份额比年末变化 | C18: PP | D18: - | E18: 0.056431118 | F18: -0.048689574 | G18: -0.0077258285
B19: 年累计净增 | C19: 万户 | D19: 480.33 | E19: 261.21 | F19: 138.46 | G19: 80.66
A20: 其中：千兆有线宽带客户数 | B20: 本期到达 | C20: 万户 | D20: 16840.05 | E20: 8528.31 | F20: 5748.53 | G20: 2563.2
B21: 同比变化 | C21: % | D21: 0.7505 | E21: 1.0189 | F21: 0.5454 | G21: 0.529
B22: 市场份额 | C22: % | D22: - | E22: 0.50643021 | F22: 0.34136063 | G22: 0.15220857
B23: 市场份额比年末变化 | C23: PP | D23: - | E23: -0.029586084 | F23: 0.0029547577 | G23: 0.026571944
B24: 年累计净增 | C24: 万户 | D24: 512.52 | E24: 254.73 | F24: 175.44 | G24: 82.35
A25: （三）IPTV（互联网电视） 客户数 | B25: 本期到达 | C25: 万户 | D25: 40383.46 | E25: 20895.97 | F25: 14711.06 | G25: 4776.43
B26: 同比变化 | C26: % | D26: 0.0527 | E26: 0.0738 | F26: 0.0115 | G26: 0.096
B27: 市场份额 | C27: % | D27: - | E27: 0.51743882 | F27: 0.36428429 | G27: 0.11827689
B28: 市场份额比年末变化 | C28: PP | D28: - | E28: 0.012852457 | F28: -0.091268087 | G28: 0.078390694
B29: 年累计净增 | C29: 万户 | D29: 281.32 | E29: 150.73 | F29: 65.88 | G29: 64.71
A30: （四）物联网卡客户数 | B30: 本期到达 | C30: 万户 | D30: 235261.27 | E30: 131449.09 | F30: 53243.83 | G30: 50568.34
B31: 同比变化 | C31: % | D31: 0.2647 | E31: 0.2413 | F31: 0.3119 | G31: 0.2789
B32: 市场份额 | C32: % | D32: - | E32: 0.55873663 | F32: 0.22631787 | G32: 0.21494545
B33: 市场份额比年末变化 | C33: PP | D33: - | E33: -0.54488677 | F33: 0.22770409 | G33: 0.31717843
B34: 年累计净增 | C34: 万户 | D34: 2035.38 | E34: -133.57 | F34: 991.71 | G34: 1177.24
A35: 三、业务量情况
A36: 个人上网流量 | B36: 本年累计 | C36: 万GB | D36: 2577196.3 | E36: 1325208.4 | F36: 734456.29 | G36: 517531.6
B37: 同比变化 | C37: % | D37: 0.213 | E37: 0.1048 | F37: 0.4052 | G37: 0.2859
B38: 市场份额 | C38: % | D38: - | E38: 0.51420546 | F38: 0.28498267 | G38: 0.20081187
B39: 市场份额同比变化 | C39: PP | D39: - | E39: -5.0359369 | F39: 3.8979269 | G39: 1.1384388
B40: 市场份额比年末变化 | C40: PP | D40: - | E40: -3.4711705 | F40: 2.7097283 | G40: 0.76144214
A41: 四、投资情况
A42: 资本开支 | B42: 本年累计 | C42: 亿元 | D42: 228.92408 | E42: 102.39613 | F42: 40.278792 | G42: 59.858352
B43: 同比变化 | C43: % | D43: 0.555 | E43: 0.2273 | F43: 1.2636 | G43: 0.7312
B44: 行业占比 | C44: % | D44: - | E44: 0.44729298 | F44: 0.17594826 | G44: 0.26147687
A45: 注：1.用户情况、业务量情况为三家运营商报工信部的内地31省数据，源于工信部反馈，为上月值
A46: 2.资本开支为电信企业报工信部的集团公司数据，行业资本开支包含中国铁塔，源于工信部反馈，为上月值
A47: =电信行业主要指标情况表!A40+1 -> 16

Sheet 分省财务-收入和利润
A1: 收入和利润情况表（1/36)
D2: =主要经营情况表!A2 -> 45323 | K2: 单位：亿元
A3: 单位 | B3: 营运收入 | D3: 通信服务收入 | F3: 通信服务收入 （含双计双考） | H3: 归属于母公司所有者的净利润 | J3: 净利润率
B4: 本年累计 | C4: 比上年 同期± | D4: 本年累计 | E4: 比上年 同期± | F4: 本年累计 | G4: 比上年 同期± | H4: 本年累计 | I4: 比上年 同期± | J4: 本年累计 | K4: 比上年同期±
A5: 广东 | B5: 216.26299 | C5: 0.032611126 | D5: 213.50609 | E5: 0.030334761 | F5: 1135.8015 | G5: 0.079607648 | H5: 44.739991 | I5: -0.12184242 | J5: 0.20687771 | K5: -3.6386402
A6: 江苏 | B6: 147.85293 | C6: 0.032869139 | D6: 139.79828 | E6: 0.035473575 | F6: 1135.8015 | G6: 0.079607648 | H6: 32.639201 | I6: -0.099772306 | J6: 0.22075452 | K6: -3.2526435
A7: 浙江 | B7: 144.72396 | C7: 0.033738817 | D7: 136.92939 | E7: 0.036330815 | F7: 1135.8015 | G7: 0.079607648 | H7: 36.552899 | I7: -0.040186466 | J7: 0.25256979 | K7: -1.9453042
A8: 山东 | B8: 101.84733 | C8: 0.059219465 | D8: 97.739168 | E8: 0.052959252 | F8: 1135.8015 | G8: 0.079607648 | H8: 18.554785 | I8: 0.00060772708 | J8: 0.18218235 | K8: -1.0671539
A9: 河南 | B9: 88.945351 | C9: 0.00024455092 | D9: 87.235711 | E9: 0.0050350576 | F9: 1135.8015 | G9: 0.079607648 | H9: 20.171349 | I9: -0.06517295 | J9: 0.22678362 | K9: -1.5869907
A10: 四川 | B10: 75.027554 | C10: 0.039262922 | D10: 73.091028 | E10: 0.021647795 | F10: 1135.8015 | G10: 0.079607648 | H10: 12.098455 | I10: 0.055043092 | J10: 0.1612535 | K10: 0.24118517
A11: 云南 | B11: 66.343865 | C11: 0.043282525 | D11: 65.849375 | E11: 0.04500877 | F11: 1135.8015 | G11: 0.079607648 | H11: 20.039229 | I11: 0.039962755 | J11: 0.30205098 | K11: -0.096420739
A12: 福建 | B12: 55.614444 | C12: 0.0033290053 | D12: 52.345707 | E12: 0.0017992064 | F12: 1135.8015 | G12: 0.079607648 | H12: 8.4313153 | I12: -0.22504275 | J12: 0.15160298 | K12: -4.4675804
A13: 江西 | B13: 52.834996 | C13: 0.019820026 | D13: 49.890918 | E13: 0.012016467 | F13: 1135.8015 | G13: 0.079607648 | H13: 11.666551 | I13: -0.01715158 | J13: 0.22081106 | K13: -0.83062042
A14: 安徽 | B14: 50.215591 | C14: 0.037201731 | D14: 49.018664 | E14: 0.043590669 | F14: 1135.8015 | G14: 0.079607648 | H14: 9.6145029 | I14: -0.033626636 | J14: 0.1914645 | K14: -1.4033
A15: 北京 | B15: 49.328843 | C15: 0.0004293605 | D15: 48.843253 | E15: 0.0025717106 | F15: 1135.8015 | G15: 0.079607648 | H15: 11.84 | I15: -0.035069418 | J15: 0.24002185 | K15: -0.88301506
A16: 湖南 | B16: 49.799189 | C16: 0.052235795 | D16: 48.035893 | E16: 0.028911738 | F16: 1135.8015 | G16: 0.079607648 | H16: 7.1309011 | I16: -0.035580955 | J16: 0.14319312 | K16: -1.3038683
... A31: 海南 | B31: 12.924482 | C31: 0.013424333 | D31: 12.82326 | E31: 0.014118238 | F31: 1135.8015 | G31: 0.079607648 | H31: 4.0109033 | I31: 0.44467861 | J31: 0.31033377 | K31: 9.2638436
A32: 天津 | B32: 10.317107 | C32: 0.0028781519 | D32: 10.212225 | E32: 0.0058679407 | F32: 1135.8015 | G32: 0.079607648 | H32: -0.73653852 | I32: - | J32: -0.071390021 | K32: 1.4120603
A33: 宁夏 | B33: 7.4598963 | C33: 0.063718547 | D33: 6.8655421 | E33: 0.061308385 | F33: 1135.8015 | G33: 0.079607648 | H33: 0.35111545 | I33: -0.63391909 | J33: 0.047067069 | K33: -8.969536
A34: 青海 | B34: 6.5429594 | C34: 0.07820972 | D34: 6.3855271 | E34: 0.060111694 | F34: 1135.8015 | G34: 0.079607648 | H34: 1.8768217 | I34: -0.092085933 | J34: 0.286846 | K34: -5.3803139
A35: 西藏 | B35: 5.3833187 | C35: 0.038988565 | D35: 5.231848 | E35: 0.048306332 | F35: 1135.8015 | G35: 0.079607648 | H35: -0.29585555 | I35: - | J35: -0.054957837 | K35: 0.54591877
A36: 香港 | B36: 11.921694 | C36: -0.02612853 | D36: 9.2441065 | E36: -0.014451017 | F36: 1135.8015 | G36: 0.079607648 | H36: 1.1688029 | I36: 0.026849545 | J36: 0.098040005 | K36: 0.50581615
A37: 上市合计 | B37: 1882.179 | C37: 0.032259278 | D37: 1580.0771 | E37: 0.020617651 | F37: 1135.8015 | G37: 0.079607648 | H37: 309.07345 | I37: -0.081225066 | J37: 0.16421045 | K37: -2.0282785
A38: 注：1.广东公司净利润已剔除浦发影响；各省、自治区、直辖市按照累计通信服务收入规模排序
A39: 2.部分省公司净利润去年同期数为负，因此无法计算净利润的同比变化情况
A40: ='电信行业主要指标情况表（续）'!A47+1 -> 17

Sheet 分省财务-数字化转型收入和支出
A1: 数字化转型收入和支出情况表（2/36)
C2: =主要经营情况表!A2 -> 45323 | K2: 单位：亿元
A3: 单位 | B3: 数字化转型收入 | E3: 营运支出 | G3: 销售费用 | J3: 政企外部欠费原值
B4: 本年累计 | C4: 比上年同期± | D4: 占通信服务收入比 | E4: 本年累计 | F4: 比上年同期± | G4: 本年累计 | H4: 比上年同期± | I4: 占通信服务收入比 | J4: 本年累计 | K4: 比上年同期±
A5: 广东 | B5: 69.345146 | C5: 0.10823571 | D5: 0.32479236 | E5: 158.46418 | F5: 0.099690038 | G5: 12.459278 | H5: 0.39533365 | I5: 0.05835561 | J5: 109.30021 | K5: 0.52899735
A6: 江苏 | B6: 55.655711 | C6: 0.14331439 | D6: 0.39811443 | E6: 106.45876 | F6: 0.10273676 | G6: 9.3079058 | H6: 0.28175163 | I6: 0.066580977 | J6: 72.284211 | K6: 0.50281984
A7: 浙江 | B7: 43.749021 | C7: 0.11875484 | D7: 0.31950058 | E7: 98.165349 | F7: 0.073916928 | G7: 7.4533811 | H7: 0.23252347 | I7: 0.054432295 | J7: 39.245576 | K7: 0.3350229
A8: 山东 | B8: 34.219989 | C8: 0.10170319 | D8: 0.35011541 | E8: 78.132457 | F8: 0.081027909 | G8: 4.4372354 | H8: -0.029881065 | I8: 0.045398743 | J8: 37.270036 | K8: 0.45079655
A9: 河南 | B9: 28.41347 | C9: 0.21707219 | D9: 0.32570916 | E9: 62.536345 | F9: 0.024253666 | G9: 4.9096086 | H9: 0.62711638 | I9: 0.056279803 | J9: 43.966161 | K9: 0.53471039
A10: 四川 | B10: 21.528037 | C10: 0.15564679 | D10: 0.29453734 | E10: 61.235858 | F10: 0.034310235 | G10: 3.2509565 | H10: 0.0075033641 | I10: 0.044478188 | J10: 23.513763 | K10: 0.64110714
A11: 云南 | B11: 16.955855 | C11: 0.1323393 | D11: 0.25749455 | E11: 43.623535 | F11: 0.036315481 | G11: 1.9821813 | H11: 0.29034743 | I11: 0.030101749 | J11: 16.103585 | K11: 0.63869889
A12: 福建 | B12: 13.15017 | C12: 0.047040234 | D12: 0.25121774 | E12: 45.820921 | F12: 0.071642387 | G12: 3.5591994 | H12: 0.035591105 | I12: 0.067994103 | J12: 27.687485 | K12: 0.42008402
A13: 江西 | B13: 15.280893 | C13: 0.16686489 | D13: 0.30628606 | E13: 37.68247 | F13: 0.034382839 | G13: 3.5430562 | H13: -0.0075264846 | I13: 0.071016056 | J13: 17.999848 | K13: 0.6290149
A14: 安徽 | B14: 13.613497 | C14: 0.19917945 | D14: 0.27772068 | E14: 38.053866 | F14: 0.061341135 | G14: 2.7133711 | H14: -0.021587011 | I14: 0.055353837 | J14: 14.232259 | K14: 0.33392837
A15: 北京 | B15: 16.819324 | C15: -0.031726108 | D15: 0.34435308 | E15: 33.892281 | F15: 0.013603772 | G15: 3.4151089 | H15: -0.052441748 | I15: 0.069919767 | J15: 38.566064 | K15: 0.21455273
A16: 湖南 | B16: 14.941913 | C16: 0.28549772 | D16: 0.31105726 | E16: 40.718512 | F16: 0.073500928 | G16: 2.5845286 | H16: -0.28191976 | I16: 0.053804112 | J16: 16.883649 | K16: 0.57506722
... A35: 西藏 | B35: 2.0802103 | C35: 0.11680696 | D35: 0.39760526 | E35: 5.9908779 | F35: 0.051897736 | G35: 0.10388915 | H35: 0.97034802 | I35: 0.019857067 | J35: 15.941707 | K35: 0.063553186
A36: 香港 | B36: - | C36: - | D36: - | E36: 10.854391 | F36: -0.0054234706 | G36: 0.81776486 | H36: 0.36582165 | I36: 0.088463375 | J36: - | K36: -
A37: 上市合计 | B37: 511.19969 | C37: 0.11892124 | D37: 0.32352832 | E37: 1518.8824 | F37: 0.06320185 | G37: 92.046303 | H37: 0.18824557 | I37: 0.058254311 | J37: 705.41443 | K37: 0.41909694
A38: 注：1.各省、自治区、直辖市按照累计通信服务收入规模排序
A39: 2.数字化转型收入包括个人市场新业务（移动云盘等）收入，家庭市场智慧家庭增值业务收入，
A40: 政企市场DICT收入、物联网收入、专线收入，以及新兴市场收入
A41: ='分省财务-收入和利润'!A40+1 -> 18

Sheet 分省财务-四轮驱动收入利润 
A1: “CHBN”收入情况表（3/36)
E2: =主要经营情况表!A2 -> 45323 | M2: 单位：亿元
A3: 单位 | B3: 个人市场收入(C) | E3: 家庭市场收入(H) | H3: 政企市场收入(B) | K3: 新兴市场收入(N)
B4: 本年累计 | C4: 比上年同期± | D4: 占通信服务收入比重 | E4: 本年累计 | F4: 比上年同期± | G4: 占通信服务收入比重 | H4: 本年累计 | I4: 比上年同期± | J4: 占通信服务收入比重 | K4: 本年累计 | L4: 比上年同期± | M4: 占通信服务收入比重
A5: 广东 | B5: 124.83689 | C5: 0.015612589 | D5: 0.58469944 | E5: 22.238875 | F5: 0.020342203 | G5: 0.10416038 | H5: 61.544809 | I5: 0.044816589 | J5: 0.28825786 | K5: 4.8855157 | L5: 0.35637428 | M5: 0.022882325
A6: 浙江 | B6: 81.025061 | C6: -0.0075891573 | D6: 0.59172877 | E6: 15.36162 | F6: 0.033709335 | G6: 0.11218643 | H6: 36.30992 | I6: 0.11526405 | J6: 0.26517258 | K6: 4.2327914 | L6: 0.3803581 | M6: 0.030912219
A7: 江苏 | B7: 75.869282 | C7: -0.0060785361 | D7: 0.54270541 | E7: 16.066826 | F7: -0.0090292147 | G7: 0.11492864 | H7: 45.2697 | I7: 0.13081208 | J7: 0.32382159 | K7: 2.5924697 | L7: 0.067027561 | M7: 0.018544361
A8: 山东 | B8: 52.851277 | C8: 0.045950481 | D8: 0.54073794 | E8: 16.118836 | F8: 0.051966123 | G8: 0.16491685 | H8: 25.934816 | I8: 0.063261817 | J8: 0.26534721 | K8: 2.8342393 | L8: 0.098730228 | M8: 0.028997989
A9: 北京 | B9: 22.288182 | C9: 0.1243622 | D9: 0.45632059 | E9: 3.5915327 | F9: 0.062296888 | G9: 0.073531808 | H9: 22.124771 | I9: -0.10063983 | J9: 0.45297497 | K9: 0.83876699 | L9: -0.081837696 | M9: 0.017172628
A10: 上海 | B10: 20.629825 | C10: -0.03339618 | D10: 0.49729401 | E10: 2.6625193 | F10: 0.11865885 | G10: 0.064181588 | H10: 17.222878 | I10: 0.033537931 | J10: 0.41516757 | K10: 0.96893891 | L10: 0.44638119 | M10: 0.02335684
A11: 天津 | B11: 5.3903955 | C11: 0.028903229 | D11: 0.5278375 | E11: 1.6044193 | F11: 0.032794937 | G11: 0.1571077 | H11: 3.0216001 | I11: 0.010563271 | J11: 0.29588067 | K11: 0.19581047 | L11: -0.47105262 | M11: 0.019174123
A12: 四川 | B12: 43.024067 | C12: -0.0038305492 | D12: 0.58863678 | E12: 13.880169 | F12: 0.15749386 | G12: 0.18990251 | H12: 14.120109 | I12: -0.041205413 | J12: 0.19318525 | K12: 2.0666827 | L12: 0.26458345 | M12: 0.028275464
A13: 辽宁 | B13: 22.007646 | C13: -0.014883397 | D13: 0.61097714 | E13: 5.0721976 | F13: 0.1342714 | G13: 0.14081455 | H13: 7.6191734 | I13: 0.05913165 | J13: 0.21152379 | K13: 1.3213916 | L13: 0.0097380159 | M13: 0.036684525
A14: 河南 | B14: 49.602981 | C14: -0.12082359 | D14: 0.56860866 | E14: 12.260075 | F14: 0.090958916 | G14: 0.14053963 | H14: 21.587712 | I14: 0.30041584 | J14: 0.24746416 | K14: 3.7849438 | L14: 0.48993729 | M14: 0.04338755
A15: 河北 | B15: 24.764974 | C15: -0.13781823 | D15: 0.54768948 | E15: 8.4822391 | F15: 0.16100994 | G15: 0.18758886 | H15: 10.367062 | I15: 0.11508402 | J15: 0.22927263 | K15: 1.6029051 | L15: -0.15874614 | M15: 0.03544903
A16: 福建 | B16: 30.945868 | C16: -0.033769885 | D16: 0.59118254 | E16: 8.1629436 | F16: 0.32497535 | G16: 0.15594294 | H16: 12.150029 | I16: -0.08524255 | J16: 0.23211128 | K16: 1.0868664 | L16: 0.39128356 | M16: 0.020763238
... A35: 西藏 | B35: 2.8581597 | C35: 0.01630538 | D35: 0.54630021 | E35: 0.52363799 | F35: 0.14732145 | G35: 0.10008662 | H35: 1.7236653 | I35: 0.091721502 | J35: 0.32945631 | K35: 0.12638501 | L35: -0.11746869 | M35: 0.024156858
A36: 香港 | B36: - | C36: - | D36: - | E36: - | F36: - | G36: - | H36: - | I36: - | J36: - | K36: 9.2490266 | L36: -0.014781363 | M36: 1.0005322
A37: 国际公司 | B37: - | C37: - | D37: - | E37: - | F37: - | G37: - | H37: - | I37: - | J37: - | K37: 27.006798 | L37: 0.21338872 | M37: 0.66266821
A38: 咪咕公司 | B38: - | C38: - | D38: - | E38: - | F38: - | G38: - | H38: - | I38: - | J38: - | K38: 3.3883751 | L38: -0.13525904 | M38: 0.20348494
A39: 金科公司 | B39: - | C39: - | D39: - | E39: - | F39: - | G39: - | H39: - | I39: - | J39: - | K39: 0.68170794 | L39: -0.28205529 | M39: 0.12224935
A40: 上市合计 | B40: 865.06444 | C40: -0.025469581 | D40: 0.54748242 | E40: 232.73656 | F40: 0.080947402 | G40: 0.14729443 | H40: 398.19082 | I40: 0.072843764 | J40: 0.25200721 | K40: 84.085281 | L40: 0.1359475 | M40: 0.053215936
A41: ='分省财务-数字化转型收入和支出'!A41+1 -> 19

Sheet 分市场驱动因素情况表
A1: 分市场收入驱动因素情况表（4/36)
A2: =主要经营情况表!A2 -> 45323
A3: 单位 | B3: 本年累计 通信服务收入增幅 （%） | C3: 个人市场拉动 （PP） | F3: 家庭市场拉动 （PP） | I3: 政企市场拉动 （PP） | L3: 新兴市场拉动 （PP）
C4: 新业务 | D4: 传统业务 | E4: 合计 | F4: 新业务 | G4: 传统业务 | H4: 合计 | I4: 新业务 | J4: 传统业务 | K4: 合计 | L4: 合计
A5: 广东 | B5: 0.030334761 | C5: 1.8422103 | D5: -0.91611027 | E5: 0.9261 | F5: 0.29762209 | G5: -0.083661874 | H5: 0.21396022 | I5: -0.23283602 | J5: 1.5068032 | K5: 1.2739672 | L5: 0.61944864
A6: 浙江 | B6: 0.036330815 | C6: -0.26024614 | D6: -0.2087002 | E6: -0.46894634 | F6: -0.59725845 | G6: 0.97639049 | H6: 0.37913204 | I6: 3.1537263 | J6: -0.31356378 | K6: 2.8401625 | L6: 0.88273328
A7: 江苏 | B7: 0.035473575 | C7: 1.1778361 | D7: -1.5215128 | E7: -0.34367671 | F7: -0.31790054 | G7: 0.2094688 | H7: -0.10843174 | I7: 3.6125337 | J7: 0.26630962 | K7: 3.8788433 | L7: 0.12062259
A8: 山东 | B8: 0.052959252 | C8: 0.22886211 | D8: 2.2725045 | E8: 2.5013666 | F8: -0.070175651 | G8: 0.92799368 | H8: 0.85781803 | I8: 1.468878 | J8: 0.19349145 | K8: 1.6623694 | L8: 0.27437119
A9: 北京 | B9: 0.0025717106 | C9: 1.9491199 | D9: 3.1110798 | E9: 5.0601997 | F9: -0.056267094 | G9: 0.48859288 | H9: 0.43232578 | I9: -3.267127 | J9: -1.8147706 | K9: -5.0818977 | L9: -0.1534568
A10: 上海 | B10: 0.010414124 | C10: 1.0472181 | D10: -2.7832629 | E10: -1.7360448 | F10: -0.11269595 | G10: 0.80057543 | H10: 0.68787948 | I10: 4.3858761 | J10: -3.0246425 | K10: 1.3612336 | L10: 0.72834412
A11: 天津 | B11: 0.0058679407 | C11: 0.73207615 | D11: 0.75938876 | E11: 1.4914649 | F11: 0.35852771 | G11: 0.14327286 | H11: 0.50180057 | I11: 2.0534899 | J11: -1.7423953 | K11: 0.31109461 | L11: -1.717566
A12: 四川 | B12: 0.021647795 | C12: 3.0110945 | D12: -3.2423416 | E12: -0.23124717 | F12: 0.46512738 | G12: 2.174708 | H12: 2.6398353 | I12: -1.1198802 | J12: 0.27166925 | K12: -0.84821096 | L12: 0.60440232
A13: 辽宁 | B13: 0.019993505 | C13: 2.2232105 | D13: -3.1647463 | E13: -0.94153573 | F13: 0.33849544 | G13: 1.3617494 | H13: 1.7002448 | I13: 1.7875388 | J13: -0.58298366 | K13: 1.2045551 | L13: 0.036086277
A14: 河南 | B14: 0.0050350576 | C14: -0.76414204 | D14: -7.089487 | E14: -7.853629 | F14: -0.088078363 | G14: 1.2657302 | H14: 1.1776518 | I14: 4.743959 | J14: 1.001624 | K14: 5.7455831 | L14: 1.4338999
A15: 河北 | B15: -0.042658241 | C15: 0.223473 | D15: -8.6047319 | E15: -8.3812589 | F15: 1.5935819 | G15: 0.89694245 | H15: 2.4905243 | I15: 2.00096 | J15: 0.26434478 | K15: 2.2653048 | L15: -0.64039431
A16: 福建 | B16: 0.0017992064 | C16: 0.47504399 | D16: -2.5449532 | E16: -2.0699092 | F16: 0.2116734 | G16: 3.6200049 | H16: 3.8316783 | I16: -1.7214811 | J16: -0.44536174 | K16: -2.1668428 | L16: 0.58499441
... A36: 上市合计 | B36: 0.020617651 | C36: 1.0599743 | D36: -2.5203334 | E36: -1.4603591 | F36: 0.21084071 | G36: 0.91492433 | H36: 1.125765 | I36: 1.6121624 | J36: 0.13419021 | K36: 1.7463526 | L36: 0.65000656
A37: ='分省财务-四轮驱动收入利润 '!A41+1 -> 20

Sheet 分省业务-行业发展、宏观经济对比
D1: 收入与行业发展、宏观经济对比情况表（5/36)
D2: =主要经营情况表!A2 -> 45323
D3: 单位 | E3: 我公司收入与行业对比 | J3: 我公司收入与GDP对比
B4: 2100 | E4: 通服收入 累计增幅 | F4: 行业平均 | G4: 与行业 增幅差 | H4: 本年累计份额 | I4: 比上年同期± | J4: 通服收入排名 | K4: GDP排名 | L4: GDP 增幅 | M4: 与GDP增幅差
A5: S0320000 | B5: 2200 | D5: 广东 | E5: 0.029243181 | F5: 0.0372 | G5: -0.79568189 | H5: 0.56950739 | I5: -0.44027177 | J5: 1 | K5: 1 | L5: 0.048 | M5: 2.8315543
A6: S0330000 | B6: 2300 | D6: 浙江 | E6: 0.037321375 | F6: 0.0557 | G6: -1.8378625 | H6: 0.62695369 | I6: -1.1107981 | J6: 3 | K6: 4 | L6: 0.06 | M6: 1.44989
A7: S0340000 | B7: 2700 | D7: 江苏 | E7: 0.032940434 | F7: 0.0388 | G7: -0.58595662 | H7: 0.5511064 | I7: -0.3126264 | J7: 2 | K7: 2 | L7: 0.058 | M7: 1.5223772
A8: S0350000 | B8: 2800 | D8: 山东 | E8: 0.05201538 | F8: 0.0587 | G8: -0.668462 | H8: 0.55816369 | I8: -0.35466327 | J8: 4 | K8: 3 | L8: 0.06 | M8: 1.0272572
A9: S0360000 | B9: 3200 | D9: 北京 | E9: 0.01023237 | F9: 0.0366 | G9: -2.636763 | H9: 0.39561611 | I9: -1.0325802 | J9: 8 | K9: 13 | L9: 0.052 | M9: -1.5934408
A10: S0370000 | B10: 3800 | D10: 上海 | E10: 0.010984334 | F10: 0.0836 | G10: -7.2615666 | H10: 0.33558517 | I10: -2.4103975 | J10: 15 | K10: 10 | L10: 0.05 | M10: 1.227074
A11: S0630000 | B11: 4300 | D11: 天津 | E11: 0.0070859823 | F11: 0.0208 | G11: -1.3714018 | H11: 0.36463908 | I11: -0.49654814 | J11: 28 | K11: 24 | L11: 0.043 | M11: 0.7142021
A12: S0640000 | B12: 2900 | D12: 四川 | E12: 0.035733692 | F12: 0.0335 | G12: 0.22336918 | H12: 0.52201393 | I12: 0.11257896 | J12: 6 | K12: 5 | L12: 0.06 | M12: 0.22908023
A13: S0000000 | B13: 3900 | D13: 辽宁 | E13: 0.017627345 | F13: 0.0175 | G13: 0.012734481 | H13: 0.50703442 | I13: 0.0063449751 | J13: 19 | K13: 16 | L13: 0.053 | M13: -3.7925595
A14: S0410000 | B14: 3100 | D14: 河南 | E14: 0.003175675 | F14: 0.0251 | G14: -2.1924325 | H14: 0.57668899 | I14: -1.2603492 | J14: 5 | K14: 6 | L14: 0.041 | M14: -1.5136707
A15: S0420000 | B15: 2500 | D15: 河北 | E15: -0.095975578 | F15: 0.0086 | G15: -10.457558 | H15: 0.42130692 | I15: -4.8735867 | J15: 10 | K15: 12 | L15: 0.055 | M15: -0.25013787
A16: S0430000 | B16: 3000 | D16: 福建 | E16: 0.030826173 | F16: 0.0433 | G16: -1.2473827 | H16: 0.53158159 | I16: -0.64325653 | J16: 11 | K16: 8 | L16: 0.045 | M16: -1.6456875
... A26: S0620000 | B26: 4400 | D26: 吉林 | E26: -0.046710741 | F26: 0.0158 | G26: -6.2510741 | H26: 0.38762357 | I26: -2.5417926 | J26: 26 | K26: 26 | L26: 0.063 | M26: -8.1438206
B27: 4500 | D27: 重庆 | E27: -0.0086106835 | F27: 0.0368 | G27: -4.5410684 | H27: 0.49920875 | I27: -2.2866305 | J27: 20 | K27: 17 | L27: 0.061 | M27: 0.3491111
A28: S0110000 | B28: 2600 | D28: 贵州 | E28: -0.022039784 | F28: 0.0165 | G28: -3.8539784 | H28: 0.57014326 | I28: -2.2468397 | J28: 17 | K28: 22 | L28: 0.049 | M28: -0.42275237
A29: S0120000 | B29: 4200 | D29: 海南 | E29: 0.022726855 | F29: 0.0381 | G29: -1.5373145 | H29: 0.51315362 | I29: -0.77134816 | J29: 27 | K29: 28 | L29: 0.092 | M29: -2.4347435
A30: S0130000 | B30: 4800 | D30: 内蒙古 | E30: 0.05335471 | F30: 0.0537 | G30: -0.034529039 | H30: 0.46679715 | I30: -0.015301642 | J30: 24 | K30: 21 | L30: 0.073 | M30: -2.1962655
A31: S0140000 | B31: 4900 | D31: 甘肃 | E31: 0.041996969 | F31: 0.0402 | G31: 0.17969686 | H31: 0.47965363 | I31: 0.082718332 | J31: 25 | K31: 27 | L31: 0.064 | M31: 0.27909118
A32: S0150000 | B32: 5000 | D32: 青海 | E32: 0.060025673 | F32: 0.0526 | G32: 0.74256727 | H32: 0.47841771 | I32: 0.33514031 | J32: 30 | K32: 30 | L32: 0.053 | M32: 2.7934702
A33: S0210000 | B33: 5100 | D33: 宁夏 | E33: 0.060793551 | F33: 0.038 | G33: 2.2793551 | H33: 0.47606265 | I33: 1.0229284 | J33: 29 | K33: 29 | L33: 0.066 | M33: 2.5847885
A34: S0220000 | B34: 4700 | D34: 新疆 | E34: 0.00011182108 | F34: 0.0456 | G34: -4.5488179 | H34: 0.42947416 | I34: -1.9533813 | J34: 23 | K34: 23 | L34: 0.068 | M34: -0.64652085
A35: S0230000 | B35: CTOT | D35: 西藏 | E35: 0.055849162 | F35: 0.0931 | G35: -3.7250838 | H35: 0.46433301 | I35: -1.6381879 | J35: 31 | K35: 31 | L35: 0.095 | M35: -7.4946002
B36: CTOT | D36: 合计 | E36: 0.020373605 | F36: 0.03752944 | G36: -1.7155835 | H36: 0.52275603 | I36: -0.87892477 | J36: - | K36: - | L36: 0.052 | M36: 1.1553976
D37: 注：1.行业对比数据根据工业和信息化部公布数据计算得出，为上月值
D38: 2.我公司收入与GDP对比均为23年四季度数据，其中GDP增幅与规模排名取自统计局网站；
D39: 通服收入排名与GDP排名均为规模排名；与GDP增幅差=通服收入增幅-GDP增幅
D40: =分市场驱动因素情况表!A37+1 -> 21

Sheet 分省业务-总连接数
A1: 总连接情况表（6/36)
A2: =主要经营情况表!$A$2 -> 45323
A3: 单位 | B3: 总连接数（万） | E3: 其中：
E4: 网络连接数（万户） | H4: 设备连接数（万个）
B5: 到达数 | C5: 比上年 同期± | D5: 本年累计净增 | E5: 到达数 | F5: 比上年 同期± | G5: 本年累计净增 | H5: 到达数 | I5: 比上年 同期± | J5: 本年累计净增
A6: 广东 | B6: 42997.771 | C6: 0.13781622 | D6: -163.5899 | E6: 35955.999 | F6: 0.11025662 | G6: -511.5273 | H6: 7041.772 | I6: 0.3029634 | J6: 347.9374
A7: 浙江 | B7: 29996.212 | C7: 0.15111212 | D7: 229.6964 | E7: 22096.962 | F7: 0.11787838 | G7: 65.3578 | H7: 7899.2501 | I7: 0.25552571 | J7: 164.3386
A8: 江苏 | B8: 33539.409 | C8: 0.13245012 | D8: 455.1298 | E8: 26422.932 | F8: 0.11140585 | G8: 276.5122 | H8: 7116.477 | I8: 0.21808588 | J8: 178.6176
A9: 山东 | B9: 23544.479 | C9: 0.18247007 | D9: 535.6426 | E9: 19304.894 | F9: 0.1600951 | G9: 454.9481 | H9: 4239.5847 | I9: 0.29631781 | J9: 80.6945
A10: 北京 | B10: 17169.915 | C10: 0.12916621 | D10: 116.3413 | E10: 14004.391 | F10: 0.14429968 | G10: 87.6572 | H10: 3165.5244 | I10: 0.06675237 | J10: 28.6841
A11: 上海 | B11: 14199.508 | C11: 0.1257373 | D11: -212.5668 | E11: 11817.271 | F11: 0.13154519 | G11: -232.0594 | H11: 2382.2373 | I11: 0.097786338 | J11: 19.4926
A12: 天津 | B12: 2171.5878 | C12: 0.15068774 | D12: 14.0643 | E12: 1651.7937 | F12: 0.14272027 | G12: 4.0945 | H12: 519.7941 | I12: 0.17676086 | J12: 9.9698
A13: 四川 | B13: 15504.235 | C13: 0.1430314 | D13: 256.6019 | E13: 10469.984 | F13: 0.069729666 | G13: 66.3257 | H13: 5034.2515 | I13: 0.33299982 | J13: 190.2762
A14: 辽宁 | B14: 7589.7904 | C14: 0.13783688 | D14: 30.5237 | E14: 5652.635 | F14: 0.098821772 | G14: -2.44 | H14: 1937.1554 | I14: 0.26935149 | J14: 32.9637
A15: 河南 | B15: 20242.803 | C15: 0.10862175 | D15: 232.2928 | E15: 16635.946 | F15: 0.086789347 | G15: 113.9054 | H15: 3606.8563 | I15: 0.22183218 | J15: 118.3874
A16: 河北 | B16: 11146.847 | C16: 0.1114117 | D16: 35.2497 | E16: 8796.6952 | F16: 0.084425092 | G16: -34.6357 | H16: 2350.1521 | I16: 0.22557086 | J16: 69.8854
A17: 福建 | B17: 9977.6576 | C17: 0.16117772 | D17: 87.4083 | E17: 7928.9607 | F17: 0.14824472 | G17: 38.278 | H17: 2048.6969 | I17: 0.21410247 | J17: 49.1303
... A37: 31省合计 | B37: 337355.29 | C37: 0.1266605 | D37: 2471.4703 | E37: 260178.22 | F37: 0.1160323 | G37: 231.6308 | H37: 77177.069 | I37: 0.16403112 | J37: 2239.8395
A38: 香港 | B38: 556.6568 | C38: 0.032766489 | D38: -3.9237 | E38: 556.6568 | F38: 0.032766489 | G38: -3.9237 | H38: 0 | I38: - | J38: 0
A39: 上市合计 | B39: 337911.95 | C39: 0.12649179 | D39: 2467.5466 | E39: 260734.88 | F39: 0.11584023 | G39: 227.7071 | H39: 77177.069 | I39: 0.16403112 | J39: 2239.8395
A40: 辛姆巴科 | B40: 4780.6622 | C40: 0.036998135 | D40: 63.8257 | E40: 4780.6622 | F40: 0.036998135 | G40: 63.8257 | H40: 0 | I40: - | J40: 0
A41: 集团合计 | B41: 342692.61 | C41: 0.12513721 | D41: 2531.3723 | E41: 265515.54 | F41: 0.11431482 | G41: 291.5328 | H41: 77177.069 | I41: 0.16403112 | J41: 2239.8395
A42: 注：1.总连接数=网络连接数+设备连接数
A43: 2.网络连接数=移动电话客户数+有线宽带客户数+物联网卡客户数
A44: 3.设备连接数=家庭设备数+行业设备数
A45: ='分省业务-行业发展、宏观经济对比'!D40+1 -> 22

Sheet 分省业务-客户到达
A1: 移动电话客户情况表（7/36)
A2: =主要经营情况表!$A$2 -> 45323
A3: 单位 | B3: 移动电话客户数 （万户） | E3: 移动电话客户市场份额 （%） | G3: 个人客户出账ARPU （元/户·月） | I3: 移动业务ARPU （元/户·月）
B4: 到达数 | C4: 比上年 同期± | D4: 本年累计净增 | E4: 本年累计 | F4: 比上年同期± | G4: 本年累计 | H4: 比上年同期± | I4: 本年累计 | J4: 比上年同期±
A5: 广东 | B5: 10627.173 | C5: 0.011282395 | D5: 42.5355 | E5: 0.62118435 | F5: -0.8293503 | G5: 74.832976 | H5: 0.0088237414 | I5: 69.422959 | J5: 0.01829762
A6: 浙江 | B6: 6313.6554 | C6: 0.010451866 | D6: -14.8944 | E6: 0.68085849 | F6: -0.76856458 | G6: 70.859797 | H6: -0.028573638 | I6: 75.047625 | J6: -0.0018269583
A7: 江苏 | B7: 6405.6449 | C7: 0.023011154 | D7: 17.446 | E7: 0.58815157 | F7: -0.049342214 | G7: 74.554439 | H7: -0.027448478 | I7: 67.782312 | J7: -0.034385152
A8: 山东 | B8: 7027.3506 | C8: 0.0031033845 | D8: -32.3963 | E8: 0.58765272 | F8: -1.022102 | G8: 50.706541 | H8: 0.013640567 | I8: 43.335918 | J8: 0.021008524
A9: 北京 | B9: 2116.2648 | C9: -0.002394096 | D9: -18.9747 | E9: 0.53084681 | F9: -1.0636534 | G9: 59.643757 | H9: -0.063676777 | I9: 78.0163 | J9: 0.03144866
A10: 上海 | B10: 2221.9174 | C10: 0.014693463 | D10: -9.237 | E10: 0.48552803 | F10: -0.73901699 | G10: 57.981809 | H10: -0.023610018 | I10: 59.314486 | J10: -0.068946644
A11: 天津 | B11: 847.4748 | C11: 0.046583424 | D11: 2.642 | E11: 0.44736246 | F11: 0.28028814 | G11: 44.602556 | H11: -0.0048483836 | I11: 36.896087 | J11: -0.06003708
A12: 四川 | B12: 5300.8088 | C12: 0.0069343255 | D12: 11.5652 | E12: 0.54856697 | F12: 0.42799013 | G12: 59.556863 | H12: 0.047559018 | I12: 46.794739 | J12: -0.020972603
A13: 辽宁 | B13: 3083.4931 | C13: 0.0066955607 | D13: -12.7628 | E13: 0.59419067 | F13: -0.48388597 | G13: 51.762965 | H13: 0.026072959 | I13: 40.837304 | J13: -0.039731531
A14: 河南 | B14: 6393.3312 | C14: 0.0080214357 | D14: 10.8751 | E14: 0.58570153 | F14: -0.41653411 | G14: 54.593551 | H14: -0.021470429 | I14: 46.616498 | J14: -0.099259045
A15: 河北 | B15: 4349.4558 | C15: -0.028490522 | D15: -10.5942 | E15: 0.49529622 | F15: -1.4680602 | G15: 42.695862 | H15: 0.013468294 | I15: 34.556661 | J15: -0.093686525
A16: 福建 | B16: 2984.5237 | C16: 0.0056888277 | D16: -6.6318 | E16: 0.60894445 | F16: 0.23060357 | G16: 69.06552 | H16: -0.003478671 | I16: 59.992733 | J16: -0.049410222
... A36: 31省合计 | B36: 98563.607 | C36: 0.012593332 | D36: 10.8385 | E36: 0.5702233 | F36: -0.52234362 | G36: 60.967651 | H36: -0.0037295455 | I36: 52.544157 | J36: -0.033075699
A37: 香港 | B37: 542.9487 | C37: 0.030325359 | D37: -4.2393 | E37: - | F37: - | G37: - | H37: - | I37: 79.847754 | J37: 0.042068752
A38: 上市合计 | B38: 99106.556 | C38: 0.012688813 | D38: 6.5992 | E38: - | F38: - | G38: - | H38: - | I38: 53.001829 | J38: -0.03174204
A39: 辛姆巴科 | B39: 4780.6622 | C39: 0.036998135 | D39: 63.8257 | E39: - | F39: - | G39: - | H39: - | I39: - | J39: -
A40: 集团合计 | B40: 103887.22 | C40: 0.01378243 | D40: 70.4249 | E40: - | F40: - | G40: - | H40: - | I40: - | J40: -
A41: 注：1.移动电话客户数为出账大于0的客户数
A42: 2.市场份额根据工业和信息化部公布数据计算得出，为上月值
A43: 3.个人客户出账ARPU=个人客户出账收入（折后税前）/个人出账客户数
A44: 4.移动业务ARPU=移动业务收入/移动电话客户数
A45: ='分省业务-总连接数'!A45+1 -> 23

Sheet 分省业务-有线宽带业务
A1: 有线宽带业务情况表（8/36)
A2: =主要经营情况表!A2 -> 45323
A3: 单位 | B3: 有线宽带业务收入 （亿元） | D3: 有线宽带客户数 （万户） | G3: 有线宽带客户市场份额 （%）
B4: 本年累计 | C4: 比去年 同期± | D4: 到达数 | E4: 比去年 同期± | F4: 本年累计净增 | G4: 到达数 | H4: 比去年 同期± | I4: 本年累计净增客户份额
A5: 广东 | B5: 20.202663 | C5: -0.041325353 | D5: 2352.2952 | E5: 0.034446074 | F5: 18.8302 | G5: 0.48369027 | H5: -0.28078404 | I5: 0.47659457
A6: 浙江 | B6: 13.545256 | C6: 0.072756461 | D6: 2019.1659 | E6: 0.059721723 | F6: 10.7215 | G6: 0.55669405 | H6: 0.67548807 | I6: 0.58426812
A7: 江苏 | B7: 14.900314 | C7: 0.027192911 | D7: 2304.1962 | E7: 0.051509589 | F7: 21.7366 | G7: 0.4800877 | H7: -0.42702215 | I7: 0.48497236
A8: 山东 | B8: 13.238406 | C8: 0.063185923 | D8: 2248.0403 | E8: 0.086807797 | F8: 25.6792 | G8: 0.48559706 | H8: 0.57077451 | I8: 0.57464261
A9: 北京 | B9: 5.3520441 | C9: 0.039657334 | D9: 388.5528 | E9: 0.10647956 | F9: 3.6531 | G9: 0.41395751 | H9: 1.9980536 | I9: 1.5214925
A10: 上海 | B10: 4.4540849 | C10: -0.07166353 | D10: 456.8946 | E10: 0.11937385 | F10: 3.6621 | G10: 0.3761097 | H10: -0.145688 | I10: 0.40133846
A11: 天津 | B11: 1.3972167 | C11: -0.097521816 | D11: 256.9179 | E11: 0.077582642 | F11: 1.1913 | G11: 0.37987738 | H11: 0.64847946 | I11: 0.40017045
A12: 四川 | B12: 11.103383 | C12: 0.17154148 | D12: 1889.7113 | E12: 0.07832205 | F12: 33.0028 | G12: 0.49481823 | H12: 1.0732289 | I12: 0.74248065
A13: 辽宁 | B13: 4.2371844 | C13: 0.14241313 | D13: 779.3476 | E13: 0.10273313 | F13: 8.995 | G13: 0.45607208 | H13: 1.076997 | I13: 0.4828597
A14: 河南 | B14: 10.779122 | C14: 0.14243854 | D14: 2175.9758 | E14: 0.079526839 | F14: 25.6735 | G14: 0.50425358 | H14: 0.4568923 | I14: 0.42169492
A15: 河北 | B15: 6.7884476 | C15: 0.065001572 | D15: 1234.2351 | E15: 0.10776769 | F15: 28.6096 | G15: 0.38277334 | H15: 1.6142805 | I15: 0.8400996
A16: 福建 | B16: 7.749613 | C16: 0.31489899 | D16: 1058.8404 | E16: 0.10257939 | F16: 12.0931 | G16: 0.46509561 | H16: 2.472048 | I16: 0.98475237
... A25: 黑龙江 | B25: 3.6811692 | C25: 0.08408277 | D25: 566.4798 | E25: 0.10565932 | F25: 7.2405 | G25: 0.46262495 | H25: 1.6471776 | I25: 0.63890653
A26: 吉林 | B26: 2.1060066 | C26: 0.12271737 | D26: 314.5993 | E26: 0.083891157 | F26: -2.1473 | G26: 0.36940969 | H26: 0.29039418 | I26: -
A27: 重庆 | B27: 5.0810441 | C27: 0.1114564 | D27: 744.4624 | E27: 0.081552604 | F27: 8.3406 | G27: 0.47489393 | H27: 1.0321129 | I27: 0.63440551
A28: 贵州 | B28: 5.1770242 | C28: 0.15657359 | D28: 756.162 | E28: 0.16721333 | F28: 18.826 | G28: 0.47115266 | H28: 1.6130984 | I28: 0.54772152
A29: 海南 | B29: 1.9470238 | C29: 0.24023009 | D29: 269.7963 | E29: 0.14007284 | F29: 4.8359 | G29: 0.4593837 | H29: 0.35110045 | I29: 0.56323333
A30: 内蒙古 | B30: 2.4403638 | C30: 0.065002377 | D30: 381.3253 | E30: 0.11565206 | F30: 4.8553 | G30: 0.39775572 | H30: 1.0025842 | I30: 0.53432526
A31: 甘肃 | B31: 2.3108747 | C31: -0.05592979 | D31: 503.6555 | E31: 0.12908939 | F31: 7.4527 | G31: 0.41978217 | H31: 1.8757076 | I31: 0.63595838
A32: 青海 | B32: 0.72003755 | C32: -0.018259652 | D32: 112.8088 | E32: 0.24070151 | F32: 2.321 | G32: 0.38220137 | H32: 2.8318865 | I32: 0.6101992
A33: 宁夏 | B33: 0.97313713 | C33: 0.17907947 | D33: 178.5581 | E33: 0.063948413 | F33: 1.3697 | G33: 0.47468626 | H33: 0.10867022 | I33: 0.40914573
A34: 新疆 | B34: 2.86521 | C34: 0.12088157 | D34: 543.9262 | E34: 0.083343093 | F34: 5.1698 | G34: 0.41677896 | H34: -0.30080407 | I34: 0.25409212
A35: 西藏 | B35: 0.71308715 | C35: 0.19819899 | D35: 63.7863 | E35: 0.12909296 | F35: 1.0438 | G35: 0.43370363 | H35: 1.106609 | I35: 0.69992806
A36: 上市合计 | B36: 206.23165 | C36: 0.07138907 | D36: 30237.259 | E36: 0.089077154 | F36: 412.7033 | G36: 0.4690676 | H36: 0.66448778 | I36: 0.54382703
A37: 注：1.有线宽带包含家庭宽带、互联网专线、企业宽带
A38: 2.市场份额根据工业和信息化部公布数据计算得出，为上月值
A39: ='分省业务-客户到达'!A45+1 -> 24

Sheet 分省业务-千兆有线宽带业务情况表
A1: 千兆有线宽带业务情况表（9/36)
A2: =主要经营情况表!$A$2 -> 45323
A3: 单位 | B3: 千兆有线宽带客户数 （万户） | G3: 千兆有线宽带客户市场份额 （%）
B4: 到达数 | C4: 比去年 同期± | D4: 本月净增 | E4: 本年累计净增 | F4: 占有线宽带客户比 | G4: 到达数 | H4: 比去年 同期± | I4: 本年累计净增客户份额
A5: 广东 | B5: 658.4308 | C5: 0.5927405 | D5: -1.8576 | E5: -11.9998 | F5: 0.27990994 | G5: 0.48784496 | H5: 3.1244177 | I5: -2.2096296
A6: 浙江 | B6: 488.394 | C6: 0.43899785 | D6: 19.0399 | E6: 21.6769 | F6: 0.24187908 | G6: 0.58395533 | H6: 2.3459884 | I6: 0.35828804
A7: 江苏 | B7: 956.7198 | C7: 0.45273008 | D7: 10.7277 | E7: 31.7759 | F7: 0.41520761 | G7: 0.60875044 | H7: 1.0170069 | I7: 0.6000057
A8: 山东 | B8: 752.6779 | C8: 0.94516098 | D8: 12.4336 | E8: 25.7533 | F8: 0.33481513 | G8: 0.53640891 | H8: 8.8607 | I8: 0.60516583
A9: 北京 | B9: 135.4096 | C9: 0.8262169 | D9: 1.3546 | E9: 10.1373 | F9: 0.3484973 | G9: 0.56108739 | H9: 12.853299 | I9: 0.85936399
A10: 上海 | B10: 112.4648 | C10: 2.2566776 | D10: 6.9085 | E10: 8.7652 | F10: 0.24615043 | G10: 0.38763284 | H10: 20.539663 | I10: 0.33037367
A11: 天津 | B11: 66.1349 | C11: 2.3136872 | D11: 2.9823 | E11: 4.8529 | F11: 0.25741647 | G11: 0.31517992 | H11: 18.966134 | I11: 0.651777
A12: 四川 | B12: 504.5135 | C12: 0.88523399 | D12: 17.8677 | E12: 50.1316 | F12: 0.26697914 | G12: 0.51210241 | H12: 8.9755877 | I12: 0.7386424
A13: 辽宁 | B13: 121.4969 | C13: 2.9070296 | D13: 3.4545 | E13: 10.2152 | F13: 0.15589565 | G13: 0.45133593 | H13: 26.28323 | I13: 0.53025098
A14: 河南 | B14: 744.64 | C14: 0.56621235 | D14: -4.4889 | E14: 11.4292 | F14: 0.34220969 | G14: 0.57068226 | H14: 6.8897085 | I14: 0.41812713
A15: 河北 | B15: 363.6376 | C15: 0.99880502 | D15: 5.769 | E15: 20.5448 | F15: 0.29462588 | G15: 0.38815224 | H15: 10.047371 | I15: 0.47510611
A16: 福建 | B16: 234.8337 | C16: 1.9527019 | D16: 5.6957 | E16: 28.0922 | F16: 0.22178385 | G16: 0.43339071 | H16: 14.833615 | I16: 0.65582723
... A36: 上市合计 | B36: 8733.0844 | C36: 0.8831645 | D36: 191.5113 | E36: 446.4166 | F36: 0.28881865 | G36: 0.50643044 | H36: 6.7337223 | I36: 0.497007
A37: 注：1.有线宽带包含家庭宽带、互联网专线、企业宽带
A38: 2.市场份额根据工业和信息化部公布数据计算得出，为上月值
A39: ='分省业务-有线宽带业务'!A39+1 -> 25

Sheet 分省业务-5G套餐客户
A1: 个人市场-5G套餐客户情况表（10/36)
A2: =主要经营情况表!A2 -> 45323
A3: 单位 | B3: 5G套餐客户数 （万户） | E3: 5G套餐客户渗透率 （%） | G3: 5G套餐客户出账ARPU （元/户·月） | I3: 5G套餐客户DOU （GB/户·月）
B4: 到达数 | C4: 比上年 同期± | D4: 本年累计 净增 | E4: 到达数 | F4: 比上年 同期± | G4: 本年累计 | H4: 比上年 同期± | I4: 本年累计 | J4: 比上年 同期±
A5: 广东 | B5: 9238.8226 | C5: 0.17133453 | D5: -41.4922 | E5: 0.86935845 | F5: 11.878987 | G5: 72.920272 | H5: -0.079573299 | I5: 14.874831 | J5: -0.089466314
A6: 浙江 | B6: 5363.5631 | C6: 0.23513977 | D6: 60.4139 | E6: 0.84951787 | F6: 15.453829 | G6: 77.8938 | H6: -0.089123773 | I6: 15.174154 | J6: -0.21733547
A7: 江苏 | B7: 5231.6329 | C7: 0.22567695 | D7: 33.1958 | E7: 0.81672228 | F7: 13.50451 | G7: 81.526567 | H7: -0.057733819 | I7: 15.013672 | J7: -0.1713446
A8: 山东 | B8: 5624.8843 | C8: 0.33466764 | D8: 100.4416 | E8: 0.80042745 | F8: 19.884586 | G8: 58.460023 | H8: -0.10890858 | I8: 13.778791 | J8: -0.071626611
A9: 北京 | B9: 1752.9809 | C9: 0.25318001 | D9: 37.3136 | E9: 0.82833722 | F9: 16.893147 | G9: 68.994536 | H9: -0.16390884 | I9: 14.252638 | J9: -0.047460339
A10: 上海 | B10: 1772.2115 | C10: 0.18784785 | D10: 8.6439 | E10: 0.79760458 | F10: 11.626803 | G10: 68.176278 | H10: -0.13356272 | I10: 11.745125 | J10: -0.077288676
A11: 天津 | B11: 591.7864 | C11: 0.23086715 | D11: -0.1538 | E11: 0.6982938 | F11: 10.454758 | G11: 52.443442 | H11: -0.095752778 | I11: 17.110991 | J11: 0.01211414
A12: 四川 | B12: 4221.0977 | C12: 0.23424996 | D12: 91.8687 | E12: 0.79631201 | F12: 14.665924 | G12: 63.868885 | H12: -0.057104785 | I12: 15.299149 | J12: 0.042709877
A13: 辽宁 | B13: 2454.3764 | C13: 0.32214769 | D13: 30.7664 | E13: 0.79597272 | F13: 18.991168 | G13: 58.015955 | H13: -0.066706911 | I13: 10.267327 | J13: -0.012796143
A14: 河南 | B14: 5112.8591 | C14: 0.28638778 | D14: 168.0429 | E14: 0.79971754 | F14: 17.305392 | G14: 63.269965 | H14: -0.14805185 | I14: 14.745141 | J14: -0.095698742
A15: 河北 | B15: 3523.9754 | C15: 0.30411761 | D15: 70.0485 | E15: 0.81021065 | F15: 20.663984 | G15: 47.860242 | H15: -0.14565348 | I15: 10.370385 | J15: -0.22183528
A16: 福建 | B16: 2435.5938 | C16: 0.16995684 | D16: -18.1272 | E16: 0.81607454 | F16: 11.45811 | G16: 71.877421 | H16: -0.067354187 | I16: 14.598595 | J16: -0.089432948
... A36: 上市合计 | B36: 80078.506 | C36: 0.25292479 | D36: 628.2272 | E36: 0.80800412 | F36: 15.492683 | G36: 65.757351 | H36: -0.11420325 | I36: 14.171997 | J36: -0.098956884
A37: ='分省业务-千兆有线宽带业务情况表'!A39+1 -> 26

Sheet 分省业务-5G网络客户
A1: 个人市场-5G网络客户情况表（11/36)
A2: =主要经营情况表!A2 -> 45323
A3: 单位 | B3: 5G网络客户数 （万户） | E3: 5G网络客户渗透率 （%） | G3: 5G流量占总流量比（%） | I3: 5G网络客户DOU （GB/户·月） | K3: 5G网络客户出账ARPU （元/户·月） | M3: 5G网络客户市场份额 （%）
B4: 到达数 | C4: 比上年 同期± | D4: 本年累计净增 | E4: 到达数 | F4: 比上年 同期± | G4: 当月 | H4: 本年 累计 | I4: 本年 累计 | J4: 比上年 同期± | K4: 本年 累计 | L4: 比上年 同期± | M4: 本年 累计 | N4: 比上年 同期±
A5: 广东 | B5: 5632.8575 | C5: 0.29781335 | D5: 14.5572 | E5: 0.53004289 | F5: 11.702276 | G5: 0.56516632 | H5: 0.57362859 | I5: 21.169496 | J5: -0.1161714 | K5: 90.499297 | L5: -0.051880065 | M5: 0.63779243 | N5: -2.0555222
A6: 浙江 | B6: 3197.7479 | C6: 0.26824758 | D6: -17.34 | E6: 0.50648122 | F6: 10.295205 | G6: 0.61355092 | H6: 0.62332799 | I6: 20.693645 | J6: -0.26801733 | K6: 90.8522 | L6: -0.063054469 | M6: 0.69136168 | N6: -3.1408464
A7: 江苏 | B7: 3109.8989 | C7: 0.33549411 | D7: 57.5896 | E7: 0.48549349 | F7: 11.359724 | G7: 0.59630743 | H7: 0.59869329 | I7: 20.549204 | J7: -0.16742075 | K7: 95.623554 | L7: -0.076277894 | M7: 0.59099887 | N7: -1.3750892
A8: 山东 | B8: 3131.7997 | C8: 0.38869599 | D8: 13.1064 | E8: 0.44565867 | F8: 12.374392 | G8: 0.58228619 | H8: 0.59345921 | I8: 19.452186 | J8: 0.022429137 | K8: 66.304112 | L8: -0.045723977 | M8: 0.58188255 | N8: -1.5448492
A9: 北京 | B9: 1050.4824 | C9: 0.24434707 | D9: -71.919 | E9: 0.49638514 | F9: 9.8428044 | G9: 0.58440386 | H9: 0.58146288 | I9: 18.816827 | J9: -0.031123779 | K9: 77.425127 | L9: -0.1454523 | M9: 0.56167728 | N9: -0.98026117
A10: 上海 | B10: 1063.272 | C10: 0.32565506 | D10: 28.4248 | E10: 0.47853804 | F10: 11.225164 | G10: 0.57925045 | H10: 0.5790074 | I10: 16.494964 | J10: -0.022335441 | K10: 84.400874 | L10: -0.080339335 | M10: 0.54604903 | N10: -1.700514
A11: 天津 | B11: 381.0077 | C11: 0.45691593 | D11: 10.302 | E11: 0.44957998 | F11: 12.662177 | G11: 0.57655719 | H11: 0.57846633 | I11: 20.0008 | J11: 0.0051118361 | K11: 58.232497 | L11: -0.059850566 | M11: 0.43268696 | N11: 0.430793
A12: 四川 | B12: 2538.4315 | C12: 0.42814758 | D12: 125.9975 | E12: 0.47887626 | F12: 14.123823 | G12: 0.5626929 | H12: 0.56334945 | I12: 20.851187 | J12: 0.014989385 | K12: 76.075271 | L12: -0.051774967 | M12: 0.54227866 | N12: -0.3721859
A13: 辽宁 | B13: 1341.8805 | C13: 0.48434201 | D13: 56.3618 | E13: 0.43518194 | F13: 14.00372 | G13: 0.56682468 | H13: 0.56534729 | I13: 14.166369 | J13: -0.045716569 | K13: 66.448519 | L13: -0.038569923 | M13: 0.58247693 | N13: -0.007595893
A14: 河南 | B14: 3189.5473 | C14: 0.42023893 | D14: 118.6269 | E14: 0.49888661 | F14: 14.479943 | G14: 0.58890705 | H14: 0.58819962 | I14: 19.298427 | J14: -0.027307391 | K14: 68.118085 | L14: -0.041421495 | M14: 0.56987614 | N14: -0.65001364
A15: 河北 | B15: 2098.3889 | C15: 0.42432681 | D15: 98.0253 | E15: 0.48244861 | F15: 15.337849 | G15: 0.65216637 | H15: 0.65031542 | I15: 13.046014 | J15: -0.30416728 | K15: 53.632485 | L15: -0.078742032 | M15: 0.50452125 | N15: -1.0968487
A16: 福建 | B16: 1456.4571 | C16: 0.38534789 | D16: 36.1247 | E16: 0.48800319 | F16: 13.373885 | G16: 0.54469374 | H16: 0.54983907 | I16: 18.165542 | J16: -0.21798807 | K16: 79.737098 | L16: -0.043302222 | M16: 0.62102433 | N16: -1.0081888
... A36: 上市合计 | B36: 47473.219 | C36: 0.37692118 | D36: 992.0444 | E36: 0.4790119 | F36: 12.671142 | G36: 0.56988297 | H36: 0.5744082 | I36: 19.467623 | J36: -0.10807211 | K36: 77.403732 | L36: -0.06665479 | M36: 0.56833512 | N36: -1.4800699
A37: 注：1.5G网络客户渗透率=5G网络客户数/移动电话客户数
A38: 2.市场份额根据工业和信息化部公布数据计算得出，为上月值
A39: ='分省业务-5G套餐客户'!A37+1 -> 27

Sheet 分省业务-5G机套网客户
A1: 个人市场-5G机套网客户情况表（12/36)
A2: =主要经营情况表!A2 -> 45323
A3: 单位 | B3: 5G机套网客户数 （万户） | E3: 5G机套网匹配率 （%） | G3: 5G机套网客户 出账ARPU （元/户·月） | I3: 5G机套网客户DOU （GB/户·月）
B4: 到达数 | C4: 比上年 同期± | D4: 本年累计 净增 | E4: 到达数 | F4: 比上年 同期± | G4: 本年累计 | H4: 比上年 同期± | I4: 本年累计 | J4: 比上年 同期±
A5: 广东 | B5: 4564.7834 | C5: 0.36881291 | D5: 7.1527 | E5: 0.66881881 | F5: 3.1407856 | G5: 97.496902 | H5: -0.053181463 | I5: 22.466249 | J5: -0.058989095
A6: 浙江 | B6: 2888.7842 | C6: 0.46252241 | D6: 75.9479 | E6: 0.76383618 | F6: 11.533872 | G6: 96.578348 | H6: -0.10296842 | I6: 21.343479 | J6: -0.27564607
A7: 江苏 | B7: 2665.998 | C7: 0.46764776 | D7: 44.8658 | E7: 0.69119833 | F7: 9.2380454 | G7: 104.01543 | H7: -0.057230998 | I7: 21.559847 | J7: -0.18500239
A8: 山东 | B8: 2728.2665 | C8: 0.60046335 | D8: 72.8222 | E8: 0.70346122 | F8: 11.850115 | G8: 71.73927 | H8: -0.08715152 | I8: 20.911891 | J8: -0.03464301
A9: 北京 | B9: 938.7641 | C9: 0.33989179 | D9: -40.8231 | E9: 0.7112934 | F9: 4.5386389 | G9: 84.190304 | H9: -0.13178593 | I9: 19.951854 | J9: -0.01218216
A10: 上海 | B10: 961.8529 | C10: 0.35130455 | D10: 32.3901 | E10: 0.78254424 | F10: 3.6972469 | G10: 89.051268 | H10: -0.090384169 | I10: 16.95371 | J10: -0.04331816
A11: 天津 | B11: 303.0463 | C11: 0.48998959 | D11: 7.2809 | E11: 0.58069275 | F11: 6.6517996 | G11: 63.831074 | H11: -0.05868655 | I11: 23.562246 | J11: 0.04569025
A12: 四川 | B12: 2012.1305 | C12: 0.54207704 | D12: 121.5285 | E12: 0.65010834 | F12: 9.9207335 | G12: 83.077803 | H12: -0.066010692 | I12: 22.972577 | J12: 0.0041712504
A13: 辽宁 | B13: 1156.8854 | C13: 0.7180842 | D13: 57.1278 | E13: 0.66738346 | F13: 17.272622 | G13: 70.450173 | H13: -0.064292967 | I13: 14.95753 | J13: -0.023196425
A14: 河南 | B14: 2698.4101 | C14: 0.55534127 | D14: 149.681 | E14: 0.70966847 | F14: 11.881773 | G14: 75.445274 | H14: -0.10053393 | I14: 20.358398 | J14: -0.080589047
A15: 河北 | B15: 1822.1101 | C15: 0.58851721 | D15: 97.2896 | E15: 0.71633041 | F15: 13.009742 | G15: 58.642373 | H15: -0.12102087 | I15: 14.727997 | J15: -0.24271185
A16: 福建 | B16: 1244.1936 | C16: 0.42773623 | D16: 26.9212 | E16: 0.73038975 | F16: 5.9410738 | G16: 85.968384 | H16: -0.043548594 | I16: 20.064281 | J16: -0.10809492
... A36: 上市合计 | B36: 39588.919 | C36: 0.50178712 | D36: 1152.641 | E36: 0.68969711 | F36: 9.7685409 | G36: 83.882244 | H36: -0.091655203 | I36: 20.843632 | J36: -0.097657897
A37: ='分省业务-5G网络客户'!A39+1 -> 28

Sheet 分省业务-个人上网
A1: 个人市场-个人上网业务情况表（13/36)
A2: =主要经营情况表!A2 -> 45323
A3: 单位 | B3: 个人上网客户数 （万户） | D3: 个人上网流量 （亿MB） | F3: 个人上网DOU （GB/户·月） | H3: 个人上网资费 （元/GB） | J3: 个人上网流量份额 （%）
B4: 到达数 | C4: 比上年 同期± | D4: 本年累计 | E4: 比上年 同期± | F4: 本年累计 | G4: 比上年 同期± | H4: 本年累计 | I4: 比上年 同期± | J4: 本年累计 | K4: 比上年 同期±
A5: 广东 | B5: 10005.124 | C5: 0.0084195793 | D5: 32632.407 | E5: 0.034965867 | F5: 16.152249 | G5: 0.0062492386 | H5: 3.2576416 | I5: -0.053318886 | J5: 0.57429816 | K5: -5.2976287
A6: 浙江 | B6: 5382.375 | C6: -0.0024815019 | D6: 17574.753 | E6: -0.11518465 | F6: 16.171475 | G6: -0.12885973 | H6: 3.7591755 | I6: 0.072351736 | J6: 0.62632124 | K6: -10.892394
A7: 江苏 | B7: 5592.3993 | C7: 0.014321664 | D7: 17426.853 | E7: -0.040621672 | F7: 15.439816 | G7: -0.0708222 | H7: 3.4356476 | I7: 0.021013406 | J7: 0.56372635 | K7: -5.4691189
A8: 山东 | B8: 5988.0589 | C8: 0.038238964 | D8: 16559.818 | E8: 0.1483065 | F8: 13.665126 | G8: 0.082086049 | H8: 2.6640227 | I8: -0.091503189 | J8: 0.55801928 | K8: -1.5674021
A9: 北京 | B9: 1804.5508 | C9: 0.005662369 | D9: 5183.121 | E9: 0.081653154 | F9: 14.246035 | G9: 0.061964097 | H9: 2.8192856 | I9: -0.16039515 | J9: 0.45459913 | K9: -5.8181039
A10: 上海 | B10: 1742.1903 | C10: 0.0029764768 | D10: 4571.8225 | E10: 0.097240682 | F10: 12.986726 | G10: 0.069836317 | H10: 4.1248174 | I10: -0.13406547 | J10: 0.46641585 | K10: -6.9682097
A11: 天津 | B11: 738.7393 | C11: 0.033225373 | D11: 2175.167 | E11: 0.16868957 | F11: 14.603405 | G11: 0.10759004 | H11: 1.6869995 | I11: -0.16051897 | J11: 0.39121036 | K11: -1.4686349
A12: 四川 | B12: 4980.2759 | C12: 0.033560893 | D12: 15083.75 | E12: 0.17857174 | F12: 15.053266 | G12: 0.12799833 | H12: 2.1276931 | I12: -0.20398537 | J12: 0.51455267 | K12: -1.9979105
A13: 辽宁 | B13: 2664.255 | C13: -0.023127193 | D13: 5573.6881 | E13: 0.11846563 | F13: 10.346765 | G13: 0.12286252 | H13: 2.87866 | I13: -0.14068526 | J13: 0.55211846 | K13: 0.024142724
A14: 河南 | B14: 5783.6158 | C14: 0.00074701106 | D14: 16946.567 | E14: 0.12569208 | F14: 14.571917 | G14: 0.11111787 | H14: 2.5620129 | I14: -0.19736978 | J14: 0.5219932 | K14: -4.5318001
A15: 河北 | B15: 3830.8731 | C15: -0.016771215 | D15: 7481.1388 | E15: -0.091819415 | F15: 9.7183307 | G15: -0.085752752 | H15: 2.4108226 | I15: -0.088118261 | J15: 0.38154381 | K15: -8.7733721
A16: 福建 | B16: 2727.0516 | C16: 0.013231204 | D16: 7548.892 | E16: -0.025275594 | F16: 13.764476 | G16: -0.051908653 | H16: 3.1689983 | I16: -0.024034551 | J16: 0.58716912 | K16: -3.4689349
... A37: 上市合计 | B37: 87367.508 | C37: 0.013768713 | D37: 255611.46 | E37: 0.057416682 | F37: 14.516626 | G37: 0.02620869 | H37: 2.7439438 | I37: -0.093508927 | J37: 0.51420546 | K37: -5.0367677
A38: 注：1.个人上网包含手机上网、数据卡两部分
A39: 2.市场份额根据工业和信息化部公布数据计算得出，为上月值
A40: ='分省业务-5G机套网客户'!A37+1 -> 29

Sheet 分省业务-手机上网
A1: 个人市场-手机上网业务情况表（14/36)
A2: =主要经营情况表!A2 -> 45323
A3: 单位 | B3: 手机上网业务收入 （亿元） | D3: 手机上网业务客户数 （万户） | F3: 手机上网业务流量 （亿MB） | H3: 手机上网业务DOU （GB/户·月） | J3: 手机上网业务资费 （元/GB）
B4: 本年累计 | C4: 比上年 同期± | D4: 到达数 | E4: 比上年 同期± | F4: 本年累计 | G4: 比上年 同期± | H4: 本年累计 | I4: 比上年 同期± | J4: 本年累计 | K4: 比上年 同期±
A5: 广东 | B5: 103.81245 | C5: -0.020216639 | D5: 10004.822 | E5: 0.0084220313 | F5: 32632.327 | G5: 0.034964845 | H5: 16.152708 | I5: 0.0062444928 | J5: 3.2576269 | K5: -0.053317254
A6: 浙江 | B6: 64.515037 | C6: -0.051160191 | D6: 5331.8762 | E6: -0.0039093729 | F6: 17557.585 | G6: -0.1146082 | H6: 16.30697 | I6: -0.12707497 | J6: 3.7626699 | K6: 0.071660943
A7: 江苏 | B7: 58.469601 | C7: -0.020454941 | D7: 5592.3973 | E7: 0.014321742 | F7: 17426.852 | G7: -0.040621652 | H7: 15.439821 | I7: -0.070822254 | J7: 3.4356676 | K7: 0.021020603
A8: 山东 | B8: 43.080869 | C8: 0.04323797 | D8: 5986.6207 | E8: 0.038181793 | F8: 16559.696 | G8: 0.14830202 | H8: 13.668341 | I8: 0.082143461 | J8: 2.6639867 | K8: -0.091495133
A9: 北京 | B9: 14.235014 | C9: -0.092064825 | D9: 1804.0892 | E9: 0.0054339794 | F9: 5183.0873 | G9: 0.081659571 | H9: 14.248619 | I9: 0.062138753 | J9: 2.8123497 | K9: -0.16060912
A10: 上海 | B10: 18.414319 | C10: -0.049850571 | D10: 1742.0869 | E10: 0.0029928805 | F10: 4571.7535 | G10: 0.0972437 | H10: 12.98732 | I10: 0.069822955 | J10: 4.1245142 | K10: -0.13405798
A11: 天津 | B11: 3.5828251 | C11: -0.018818393 | D11: 736.8113 | E11: 0.033810472 | F11: 2175.1527 | G11: 0.16872196 | H11: 14.64165 | I11: 0.10695011 | J11: 1.6866921 | K11: -0.16046618
A12: 四川 | B12: 31.341387 | C12: -0.061839665 | D12: 4979.0226 | E12: 0.033421454 | F12: 15082.965 | G12: 0.17857549 | H12: 15.057565 | I12: 0.12824706 | J12: 2.1278031 | K12: -0.20398792
A13: 辽宁 | B13: 15.66866 | C13: -0.038884933 | D13: 2664.1443 | E13: -0.023101804 | F13: 5572.6375 | G13: 0.11862537 | H13: 10.345254 | I13: 0.12299214 | J13: 2.8791947 | K13: -0.14080702
A14: 河南 | B14: 42.399529 | C14: -0.096489014 | D14: 5783.6158 | E14: 0.00074701106 | F14: 16946.567 | G14: 0.12569208 | H14: 14.571917 | I14: 0.11111787 | J14: 2.5620007 | K14: -0.19737289
A15: 河北 | B15: 17.611896 | C15: -0.17182824 | D15: 3830.5771 | E15: -0.016706111 | F15: 7474.9627 | G15: -0.09150475 | H15: 9.711101 | I15: -0.085488371 | J15: 2.4126651 | K15: -0.088413772
A16: 福建 | B16: 23.360335 | C16: -0.048735617 | D16: 2727.0516 | E16: 0.013568854 | F16: 7548.892 | G16: -0.025132698 | H16: 13.764476 | I16: -0.05208935 | J16: 3.1688072 | K16: -0.024211417
... A37: 上市合计 | B37: 683.59321 | C37: -0.04225454 | D37: 87295.742 | E37: 0.013713727 | F37: 255324.53 | G37: 0.057741259 | H37: 14.512243 | I37: 0.026578421 | J37: 2.7416067 | K37: -0.094537107
A38: ='分省业务-个人上网'!A40+1 -> 30

Sheet 分省业务-携号转网
A1: 个人市场-携号转网情况表（15/36）
A2: =主要经营情况表!A2 -> 45323
B3: 中国移动 | F3: 中国电信 | G3: 中国联通
A4: 省份 | B4: 携入合计 （万户） | C4: 携出合计 （万户） | D4: 净携入合计 （万户） | E4: 携入携出比 | F4: 净携入合计 （万户） | G4: 净携入合计 （万户）
A5: 广东 | B5: 6.3282 | C5: 8.497 | D5: -2.1688 | E5: 0.74475697 | F5: 3.97 | G5: -1.8012
A6: 浙江 | B6: 7.4511 | C6: 7.0656 | D6: 0.3855 | E6: 1.0545601 | F6: 1.0359 | G6: -1.4214
A7: 江苏 | B7: 7.1499 | C7: 7.8433 | D7: -0.6934 | E7: 0.91159333 | F7: 2.6589 | G7: -1.9655
A8: 山东 | B8: 5.5911 | C8: 7.1621 | D8: -1.571 | E8: 0.78065093 | F8: 0.3701 | G8: 1.2009
A9: 北京 | B9: 3.0741 | C9: 4.4672 | D9: -1.3931 | E9: 0.68814918 | F9: 0.6594 | G9: 0.7337
A10: 上海 | B10: 4.3846 | C10: 8.3372 | D10: -3.9526 | E10: 0.52590798 | F10: 3.4229 | G10: 0.5297
A11: 天津 | B11: 3.4023 | C11: 4.0669 | D11: -0.6646 | E11: 0.83658315 | F11: -0.3865 | G11: 1.0511
A12: 四川 | B12: 13.2788 | C12: 12.0768 | D12: 1.202 | E12: 1.0995297 | F12: 1.9962 | G12: -3.1982
A13: 辽宁 | B13: 7.4457 | C13: 11.726 | D13: -4.2803 | E13: 0.63497356 | F13: 0.3257 | G13: 3.9546
A14: 河南 | B14: 10.4435 | C14: 11.3419 | D14: -0.8984 | E14: 0.92078929 | F14: 0.5754 | G14: 0.323
A15: 河北 | B15: 11.3184 | C15: 14.927 | D15: -3.6086 | E15: 0.75825015 | F15: 0.9245 | G15: 2.6841
A16: 福建 | B16: 2.9335 | C16: 2.9649 | D16: -0.0314 | E16: 0.98940942 | F16: 0.5414 | G16: -0.51
... A36: 上市合计 | B36: 159.3991 | C36: 193.1549 | D36: -33.7558 | E36: 0.82523974 | F36: 33.4282 | G36: 0.3276
A37: 注：1.携号转网数据为本年累计数据，取自工信部携号转网平台反馈的数据
A38: 2.携入携出比=携入用户数/携出用户数
A39: ='分省业务-手机上网'!A38+1 -> 31

Sheet 分省业务-个人市场重点产品
A1: 个人市场-重点产品情况表（16/36)
B2: =主要经营情况表!A2 -> 45323 | K2: 单位：万户
A3: 单位 | B3: 权益融合客户数 | D3: 移动云盘会员用户数 | F3: 移动云盘全场景月活用户数 | H3: 移动认证核心功能 月活用户数 | J3: 和多号（含中间号） 月服务人次
B4: 本月 | C4: 环比变化 ± | D4: 本月 | E4: 环比变化 ± | F4: 本月 | G4: 环比 变化± | H4: 本月 | I4: 环比 变化± | J4: 本月 | K4: 环比变化 ±
A5: 广东 | B5: 3671.06 | C5: -0.0022748089 | D5: 2288.5259 | E5: -0.046983653 | F5: 2679.4312 | G5: -0.13062253 | H5: 4713.7841 | I5: -0.014333531 | J5: 6133.6324 | K5: -0.091109184
A6: 浙江 | B6: 1150.86 | C6: -0.5432334 | D6: 1819.2067 | E6: 0.011829214 | F6: 1536.0187 | G6: -0.056935013 | H6: 2601.7872 | I6: 0.0048873888 | J6: 2516.0556 | K6: -0.12654949
A7: 江苏 | B7: 2194.67 | C7: 0.0085753282 | D7: 1932.221 | E7: 0.027456867 | F7: 1247.5433 | G7: -0.071725418 | H7: 2405.0961 | I7: 0.0029974455 | J7: 3233.4233 | K7: -0.10543883
A8: 山东 | B8: 2213.6 | C8: -0.00023485629 | D8: 1426.7002 | E8: -0.036543019 | F8: 939.0502 | G8: -0.083156842 | H8: 2343.2725 | I8: -0.003736722 | J8: 3647.2644 | K8: -0.077647428
A9: 北京 | B9: 760.57 | C9: -0.011129458 | D9: 473.8251 | E9: 0.0079281324 | F9: 376.7723 | G9: -0.21797353 | H9: 877.933 | I9: -0.028229325 | J9: 1644.9467 | K9: -0.019689445
A10: 上海 | B10: 699.79 | C10: -0.0063188686 | D10: 90.9803 | E10: -0.083980894 | F10: 367.2698 | G10: -0.094814906 | H10: 811.4116 | I10: -0.0010184197 | J10: 1473.567 | K10: -0.083130721
A11: 天津 | B11: 295.07 | C11: -0.0042184125 | D11: 167.9541 | E11: 0.010737203 | F11: 143.543 | G11: -0.20832865 | H11: 308.3227 | I11: -0.021290367 | J11: 630.7655 | K11: -0.085740968
A12: 四川 | B12: 1482.88 | C12: -0.025081688 | D12: 1555.9014 | E12: 0.0097332513 | F12: 825.4084 | G12: 0.017058412 | H12: 2037.8278 | I12: -0.00076439647 | J12: 2617.2115 | K12: -0.12913107
A13: 辽宁 | B13: 1473.15 | C13: 0.011292648 | D13: 451.1102 | E13: -0.17210822 | F13: 418.2741 | G13: -0.035827352 | H13: 944.6317 | I13: -0.014010991 | J13: 1053.1713 | K13: -0.20169705
A14: 河南 | B14: 1989.85 | C14: -0.015539812 | D14: 1330.0914 | E14: 0.024541711 | F14: 1309.3187 | G14: -0.027363941 | H14: 2553.9881 | I14: 0.013024285 | J14: 2515.212 | K14: -0.20806805
A15: 河北 | B15: 1375.5 | C15: 0.001157281 | D15: 1450.2454 | E15: -0.010267184 | F15: 731.8182 | G15: -0.11523334 | H15: 1321.9937 | I15: 0.023563758 | J15: 1757.097 | K15: -0.21747196
A16: 福建 | B16: 914.46 | C16: -0.014250604 | D16: 960.097 | E16: 0.01074205 | F16: 505.9366 | G16: -0.00089476543 | H16: 1179.7933 | I16: -0.0029924762 | J16: 1675.8297 | K16: -0.059960531
... A36: 上市合计 | B36: 31666.01 | C36: -0.043791243 | D36: 23484.974 | E36: -0.0030371084 | F36: 17872.888 | G36: -0.064057313 | H36: 36601.92 | I36: 0.0054305979 | J36: 44128.679 | K36: -0.1430403
A37: ='分省业务-携号转网'!A39+1 -> 32

Sheet 分省业务-个人市场重点产品（续）
A1: 个人市场-重点产品情况表（续）（17/36)
D2: ='分省业务-个人市场重点产品'!B2 -> 45323 | K2: 单位：万户
A3: 单位 | B3: 139邮箱月活用户数 | D3: 和留言使用用户数 | F3: 5G新通话全场景月活用户数 | H3: 和彩印订购用户数 | J3: 超级SIM全场景月活用户数
B4: 本月 | C4: 环比变化± | D4: 本月 | E4: 环比变化 ± | F4: 本月 | G4: 环比变化 ± | H4: 本月 | I4: 环比变化 ± | J4: 本月 | K4: 环比变化 ±
A5: 广东 | B5: 3412.5395 | C5: -0.020383087 | D5: 5383.868 | E5: -0.0087419176 | F5: 1321.09 | G5: -0.043976959 | H5: 1717.101 | I5: -0.0020323169 | J5: 127.2735 | K5: 0.018064203
A6: 浙江 | B6: 1973.9984 | C6: -0.031935085 | D6: 85.8552 | E6: -0.026491215 | F6: 477.55 | G6: -0.05564674 | H6: 618.2575 | I6: -0.022672768 | J6: 339.4882 | K6: 0.012702022
A7: 江苏 | B7: 1469.4924 | C7: 0.013734571 | D7: 1418.8407 | E7: 0.024845358 | F7: 1024.29 | G7: 0.044245532 | H7: 1322.6112 | I7: 0.0089531822 | J7: 184.8707 | K7: 0.013604965
A8: 山东 | B8: 1063.846 | C8: -0.022123252 | D8: 1583.9413 | E8: -0.0085285975 | F8: 794.97 | G8: 0.0012847157 | H8: 615.4474 | I8: -0.0057824628 | J8: 145.6205 | K8: -0.10431204
A9: 北京 | B9: 566.5244 | C9: -0.19342983 | D9: 233.9592 | E9: -0.0063329713 | F9: 122.62 | G9: -0.072115021 | H9: 231.2207 | I9: -0.0010286928 | J9: 20.0235 | K9: 0.0029451983
A10: 上海 | B10: 577.9552 | C10: 0.032536902 | D10: 335.8368 | E10: 0.080883936 | F10: 100.22 | G10: -0.059938092 | H10: 97.5822 | I10: -0.025202512 | J10: 125.4634 | K10: 0.023403209
A11: 天津 | B11: 230.5207 | C11: 0.089100758 | D11: 36.4704 | E11: -0.014188289 | F11: 70.77 | G11: -0.086720867 | H11: 13.6806 | I11: 0.0011928895 | J11: 8.1841 | K11: 0.057377261
A12: 四川 | B12: 906.2454 | C12: 0.005549329 | D12: 572.0584 | E12: 0.002113859 | F12: 839.6 | G12: -0.0028503563 | H12: 1057.9399 | I12: 0.015036052 | J12: 130.0287 | K12: 0.02364572
A13: 辽宁 | B13: 424.3429 | C13: 0.081205538 | D13: 23.9788 | E13: 0.0064976494 | F13: 514.73 | G13: -0.014927373 | H13: 221.4835 | I13: 0.02261557 | J13: 61.6747 | K13: 0.0016289237
A14: 河南 | B14: 2106.6053 | C14: 0.044052139 | D14: 953.4982 | E14: -0.014546296 | F14: 791.2 | G14: -0.061302455 | H14: 436.3388 | I14: 0.20593078 | J14: 79.5439 | K14: 0.050120532
A15: 河北 | B15: 837.8626 | C15: -0.091829274 | D15: 1250.2644 | E15: 0.0094293054 | F15: 584.31 | G15: -0.009677638 | H15: 236.1355 | I15: -0.0036821511 | J15: 56.7091 | K15: 0.015700533
A16: 福建 | B16: 686.6948 | C16: 0.16895005 | D16: 170.9745 | E16: -0.026059361 | F16: 239.89 | G16: 0.04137003 | H16: 115.0191 | I16: -0.0024855666 | J16: 29.3574 | K16: 0.037917758
... A36: 上市合计 | B36: 21937.092 | C36: -0.0060277502 | D36: 16935.463 | E36: -0.0038628361 | F36: 12184.09 | G36: -0.014492132 | H36: 10713.88 | I36: 0.010117314 | J36: 1707.0264 | K36: 0.0048281038
A37: ='分省业务-个人市场重点产品'!A37+1 -> 33

Sheet 分省业务-家庭宽带业务
A1: 家庭市场-家庭宽带业务情况表（18/36)
A2: =主要经营情况表!A2 -> 45323
A3: 单位 | B3: 家庭宽带业务收入 （亿元） | D3: 家庭宽带客户数 （万户） | H3: 其中：千兆家庭宽带客户数 （万户）
B4: 本年累计 | C4: 比去年 同期± | D4: 到达数 | E4: 本年累计 净增 | F4: 活跃率 | G4: 活跃率比上月± | H4: 到达数 | I4: 本年累计 净增 | J4: 活跃率 | K4: 活跃率比上月± | L4: 渗透率
A5: 广东 | B5: 15.866914 | C5: -0.014777193 | D5: 2006.7704 | E5: 8.624 | F5: 0.85321709 | G5: -0.51511082 | H5: 617.7308 | I5: -12.9359 | J5: 0.88014229 | K5: -0.33642388 | L5: 0.30782336
A6: 浙江 | B6: 11.223177 | C6: 0.13049373 | D6: 1743.1672 | E6: 6.8816 | F6: 0.80211284 | G6: -1.2736973 | H6: 460.381 | I6: 21.7215 | J6: 0.81815561 | K6: -0.64617365 | L6: 0.26410605
A7: 江苏 | B7: 12.062948 | C7: 0.024308072 | D7: 2031.2749 | E7: 13.4129 | F7: 0.80819706 | G7: -0.17656648 | H7: 930.8285 | I7: 29.1117 | J7: 0.90946678 | K7: -0.0663673 | L7: 0.45824841
A8: 山东 | B8: 11.274052 | C8: 0.084122767 | D8: 1985.4088 | E8: 16.4283 | F8: 0.84973981 | G8: -0.02075729 | H8: 733.6552 | I8: 25.1984 | J8: 0.9143963 | K8: -0.14247573 | L8: 0.3695235
A9: 北京 | B9: 3.1822023 | C9: 0.082326842 | D9: 380.8949 | E9: 3.2629 | F9: 0.80379443 | G9: -0.61787543 | H9: 135.2711 | I9: 10.1397 | J9: 0.88156228 | K9: -0.35301894 | L9: 0.35514022
A10: 上海 | B10: 2.5018525 | C10: 0.15209869 | D10: 423.818 | E10: 3.1186 | F10: 0.74351019 | G10: -0.62397582 | H10: 112.4083 | I10: 8.7596 | J10: 0.76194285 | K10: 0.76630895 | L10: 0.26522776
A11: 天津 | B11: 1.1271952 | C11: 0.070810369 | D11: 244.5885 | E11: 0.988 | F11: 0.79264806 | G11: -0.66129383 | H11: 65.6936 | I11: 4.8112 | J11: 0.93957554 | K11: -0.21022434 | L11: 0.26858826
A12: 四川 | B12: 8.7795457 | C12: 0.21616831 | D12: 1692.3131 | E12: 31.0844 | F12: 0.84688229 | G12: -0.17590456 | H12: 497.9966 | I12: 49.1295 | J12: 0.94127831 | K12: 0.058219066 | L12: 0.29426978
A13: 辽宁 | B13: 3.6726122 | C13: 0.1516554 | D13: 732.6358 | E13: 10.6451 | F13: 0.90591792 | G13: -0.11073325 | H13: 120.1131 | I13: 9.9765 | J13: 0.95999354 | K13: 0.0039543129 | L13: 0.16394653
A14: 河南 | B14: 9.3268825 | C14: 0.1606958 | D14: 2027.8142 | E14: 19.2451 | F14: 0.86155374 | G14: -1.0752915 | H14: 742.8691 | I14: 36.2928 | J14: 0.90503037 | K14: -0.22943523 | L14: 0.36633983
A15: 河北 | B15: 6.1078276 | C15: 0.074618067 | D15: 1121.2199 | E15: 23.1337 | F15: 0.8267388 | G15: 0.085870635 | H15: 350.5887 | I15: 18.6937 | J15: 0.9015262 | K15: 0.2549004 | L15: 0.31268505
A16: 福建 | B16: 6.9136218 | C16: 0.38080839 | D16: 924.7612 | E16: 11.6232 | F16: 0.80783028 | G16: -0.4844148 | H16: 230.7218 | I16: 27.8759 | J16: 0.90765372 | K16: -0.43797322 | L16: 0.24949338
... A36: 上市合计 | B36: 169.06797 | C36: 0.095145836 | D36: 26711.157 | E36: 329.1526 | F36: 0.82445529 | G36: -0.38114779 | H36: 8361.9596 | I36: 449.3631 | J36: 0.89035726 | K36: -0.11659876 | L36: 0.3130512
A37: 注：1.家庭宽带客户活跃率=家庭宽带活跃客户数/家庭宽带客户数*100%
A38: 2.千兆家庭宽带客户渗透率=千兆家庭宽带客户数/家庭宽带客户数*100%
A39: ='分省业务-个人市场重点产品（续）'!A37+1 -> 34

Sheet 分省业务-家庭宽带业务(续)
A1: 家庭市场-家庭宽带业务情况表（续）（19/36)
A2: =主要经营情况表!A2 -> 45323
A3: 单位 | B3: 家庭客户综合ARPU （元/户·月） | D3: 家庭宽带ARPU （元/户·月） | F3: 家庭宽带客户市场份额 （%） | I3: 家庭宽带端口实装率 （%）
B4: 本年累计 | C4: 比去年 同期± | D4: 本年累计 | E4: 比去年 同期± | F4: 本年累计 | G4: 比去年 同期± | H4: 本年累计 净增份额 | I4: 到达数 | J4: 比去年 同期±
A5: 广东 | B5: 55.511322 | C5: 0.0066981708 | D5: 37.153294 | E5: -0.036650862 | F5: 0.49321318 | G5: -1.0410189 | H5: 0.33572894 | I5: 0.43835737 | J5: -1.2271412
A6: 浙江 | B6: 44.134642 | C6: -0.024653904 | D6: 28.516826 | E6: 0.0067358759 | F6: 0.59737749 | G6: -0.97631405 | H6: 0.38757079 | I6: 0.58005496 | J6: -1.3651024
A7: 江苏 | B7: 39.665351 | C7: -0.050963095 | D7: 25.695228 | E7: -0.00511688 | F7: 0.51111243 | G7: -0.16382017 | H7: 0.50242938 | I7: 0.62601391 | J7: 1.3584047
A8: 山东 | B8: 40.746317 | C8: -0.018789248 | D8: 23.69882 | E8: 0.036655504 | F8: 0.49672175 | G8: 0.41364745 | H8: 0.4452209 | I8: 0.60649676 | J8: 2.4650309
A9: 北京 | B9: 47.342966 | C9: -0.047187176 | D9: 38.909054 | E9: 0.0084951102 | F9: 0.4465512 | G9: 1.872606 | H9: 1.5011017 | I9: 0.58184156 | J9: 2.1646891
A10: 上海 | B10: 31.515992 | C10: 0.0014435067 | D10: 27.626972 | E10: 0.011443342 | F10: 0.39354033 | G10: -0.13387278 | H10: 0.35134851 | I10: 0.54326698 | J10: 0.88989275
A11: 天津 | B11: 32.831122 | C11: -0.048707676 | D11: 18.621857 | E11: -0.03860051 | F11: 0.40303506 | G11: 0.99055262 | H11: 0.57560185 | I11: 0.54110034 | J11: -1.0864437
A12: 四川 | B12: 41.342445 | C12: 0.085005905 | D12: 23.283425 | E12: 0.17652355 | F12: 0.51125247 | G12: 0.6469028 | H12: 0.78226471 | I12: 0.6065129 | J12: 1.6243492
A13: 辽宁 | B13: 34.875306 | C13: 0.029334882 | D13: 22.220145 | E13: 0.071711595 | F13: 0.4734439 | G13: 1.1348348 | H13: 0.47957406 | I13: 0.4737523 | J13: -0.16187233
A14: 河南 | B14: 30.394824 | C14: 0.0076115578 | D14: 20.80838 | E14: 0.099729224 | F14: 0.53350829 | G14: 0.51277615 | H14: 0.28659139 | I14: 0.65557963 | J14: -2.0156303
A15: 河北 | B15: 38.144216 | C15: 0.065266068 | D15: 23.021623 | E15: -0.04694963 | F15: 0.39547906 | G15: 1.4297232 | H15: 0.76378095 | I15: 0.53783815 | J15: 1.9529046
A16: 福建 | B16: 44.367605 | C16: 0.20948234 | D16: 34.98808 | E16: 0.30313909 | F16: 0.49439069 | G16: 3.3703753 | H16: 0.78627027 | I16: 0.59531918 | J16: 1.2831245
... A36: 上市合计 | B36: 43.814265 | C36: 0.00085963436 | D36: 28.288796 | E36: 0.0074738962 | F36: 0.48455184 | G36: 0.32536135 | H36: 0.50806972 | I36: 0.56739544 | J36: 0.52393955
A37: 注：1.家庭市场综合ARPU=家庭市场收入/家庭宽带客户数
A38: 2.家庭宽带ARPU=（家庭裸宽带收入+融合宽带收入）/家庭宽带客户数
A39: 3.市场份额根据工业和信息化部公布数据计算得出，为上月值
A40: ='分省业务-家庭宽带业务'!A39+1 -> 35

Sheet 分省业务-移动高清业务
A1: 家庭市场-移动高清业务情况表（20/36)
A2: =主要经营情况表!A2 -> 45323
A3: 单位 | B3: 移动高清业务收入 （亿元） | D3: 大屏点播业务收入 （亿元） | F3: 移动高清客户数 （万户） | I3: 移动高清客户渗透率 (%) | K3: 移动高清客户份额 （%）
B4: 本年累计 | C4: 比去年 同期± | D4: 本年累计 | E4: 比去年 同期± | F4: 到达数 | G4: 比去年 同期± | H4: 本年累计 净增 | I4: 本年到达 | J4: 比去年 同期± | K4: 本年累计 | L4: 比去年 同期± | M4: 本年累计净增份额
A5: 广东 | B5: 2.4970059 | C5: 0.10110829 | D5: 1.8160377 | E5: 0.55173444 | F5: 1740.7779 | G5: -0.069662969 | H5: -18.2149 | I5: 0.86745245 | J5: -7.6009832 | K5: 0.60776731 | L5: -1.5108155 | M5: -
A6: 浙江 | B6: 0.96431652 | C6: -0.27337075 | D6: 2.6925127 | E6: -0.088706774 | F6: 1377.782 | G6: 0.10145405 | H6: 14.9122 | I6: 0.79039004 | J6: 3.6158951 | K6: 0.66541479 | L6: 2.7452457 | M6: 0.87940299
A7: 江苏 | B7: 1.1014506 | C7: -0.10625611 | D7: 2.3275378 | E7: -0.083051874 | F7: 1540.2436 | G7: 0.06824596 | H7: 20.1221 | I7: 0.75826448 | J7: 1.9877159 | K7: 0.51740303 | L7: 1.3761637 | M7: 1.0525847
A8: 山东 | B8: 0.95476398 | C8: -0.4785634 | D8: 3.0235702 | E8: 0.64578488 | F8: 1562.8999 | G8: 0.047769131 | H8: -3.412 | I8: 0.787193 | J8: -1.7996345 | K8: 0.55634106 | L8: -0.048325518 | M8: -0.079025907
A9: 北京 | B9: 0.07480496 | C9: -0.44698024 | D9: 0.15032328 | E9: 0.16162543 | F9: 266.9977 | G9: 0.21341742 | H9: 4.6141 | I9: 0.70097473 | J9: 6.1460097 | K9: 0.58159887 | L9: 5.2901493 | M9: 0.80900602
A10: 上海 | B10: 0.044161988 | C10: -0.71310658 | D10: 0.029263843 | E10: 0.73934028 | F10: 262.847 | G10: 0.20389556 | H10: 3.1268 | I10: 0.62018838 | J10: 4.7541462 | K10: 0.41236043 | L10: 4.1083085 | M10: 0.79969283
A11: 天津 | B11: 0.15905026 | C11: -0.14455237 | D11: 0.18380796 | E11: 1.6237832 | F11: 149.2522 | G11: 0.1642882 | H11: 1.0985 | I11: 0.61021757 | J11: 4.5009706 | K11: 0.33358655 | L11: 2.5562136 | M11: 0.28565836
A12: 四川 | B12: 3.2042106 | C12: 0.048476006 | D12: 1.5854115 | E12: 0.34871491 | F12: 1685.3471 | G12: 0.089417733 | H12: 36.5943 | I12: 0.99588374 | J12: 2.1839386 | K12: 0.49721066 | L12: 2.1549617 | M12: 0.88693339
A13: 辽宁 | B13: 0.77262013 | C13: 0.14067804 | D13: 0.28168457 | E13: 0.025884204 | F13: 526.8188 | G13: 0.096963033 | H13: 7.8187 | I13: 0.71907324 | J13: -0.39500525 | K13: 0.58691701 | L13: 0.02021999 | M13: 0.38649587
A14: 河南 | B14: 0.39503414 | C14: -0.0084011695 | D14: 1.609824 | E14: -0.16230393 | F14: 1227.6238 | G14: 0.010069896 | H14: 6.9539 | I14: 0.60539264 | J14: -3.8839649 | K14: 0.59754426 | L14: 0.316158 | M14: 0.73512735
A15: 河北 | B15: 0.80461598 | C15: 0.0054315652 | D15: 0.69475682 | E15: 0.83430518 | F15: 791.4508 | G15: 0.13143358 | H15: 11.5872 | I15: 0.70588365 | J15: 2.6723395 | K15: 0.41415205 | L15: 3.8215318 | M15: 0.92585586
A16: 福建 | B16: 0.54615044 | C16: 0.096336531 | D16: 0.4899462 | E16: 0.040522624 | F16: 681.6888 | G16: -0.02176701 | H16: 7.6738 | I16: 0.73715117 | J16: -8.2829509 | K16: 0.56782888 | L16: 1.0997429 | M16: 1.2450916
A17: 湖南 | B17: 2.1831399 | C17: 0.8303036 | D17: 0.82185281 | E17: 0.33933085 | F17: 773.673 | G17: 0.02973519 | H17: 5.6408 | I17: 0.73715788 | J17: -6.6618259 | K17: 0.41896596 | L17: -0.47560756 | M17: 0.18650568
... A36: 上市合计 | B36: 24.12373 | C36: 0.0030644966 | D36: 25.907453 | E36: 0.10233757 | F36: 20968.545 | G36: 0.069170717 | H36: 223.2983 | I36: 0.78501075 | J36: -0.51635583 | K36: 0.51743887 | L36: 1.0165663 | M36: 0.53577847
A37: 注：1.移动高清渗透率=移动高清客户数/家庭宽带客户数*100%
A38: 2.市场份额根据工业和信息化部公布数据计算得出，为上月值
A39: ='分省业务-家庭宽带业务(续)'!A40+1 -> 36

Sheet 分省业务-家庭市场重点产品
A1: 家庭市场-重点产品情况表（21/36)
B2: =主要经营情况表!A2 -> 45323 | G2: 单位：万户 | I2: 单位：万户
A3: 单位 | B3: 大屏点播 | D3: 智能组网 | F3: 家庭安防 | H3: 健康养老
B4: 到达用户数 | C4: 本年累计净增用户数 | D4: 到达用户数 | E4: 本年累计净增用户数 | F4: 订购用户数 | G4: 本年累计净增用户数 | H4: 到达用户数 | I4: 本年累计净增用户数
A5: 广东 | B5: 802.5599 | C5: 39.8772 | D5: 1385.9401 | E5: 47.7332 | F5: 426.6053 | G5: -3.9806 | H5: 295.16 | I5: 47.054
A6: 浙江 | B6: 1314.1405 | C6: 15.7721 | D6: 1063.6427 | E6: 38.2056 | F6: 465.0058 | G6: 5.9214 | H6: 280.9985 | I6: 24.9546
A7: 江苏 | B7: 1027.629 | C7: -3.3579 | D7: 1415.5772 | E7: 46.1733 | F7: 228.5533 | G7: 8.3315 | H7: 444.9177 | I7: -4.3741
A8: 山东 | B8: 1504.0461 | C8: 15.7874 | D8: 1080.4169 | E8: 44.0564 | F8: 174.3812 | G8: -27.8626 | H8: 231.9292 | I8: -13.8226
A9: 北京 | B9: 96.9832 | C9: 10.2343 | D9: 150.9477 | E9: 9.5427 | F9: 38.2173 | G9: 3.5865 | H9: 76.4472 | I9: 15.6057
A10: 上海 | B10: 164.5614 | C10: 3.1093 | D10: 187.5756 | E10: 12.2722 | F10: 63.5296 | G10: -10.3179 | H10: 59.7256 | I10: 3.6748
A11: 天津 | B11: 33.9114 | C11: 1.6933 | D11: 116.8692 | E11: 4.0846 | F11: 48.372 | G11: 6.2404 | H11: 6.078 | I11: 1.2455
A12: 四川 | B12: 798.3796 | C12: 42.4456 | D12: 839.4516 | E12: 46.5907 | F12: 310.6011 | G12: 14.0739 | H12: 18.0895 | I12: 3.2353
A13: 辽宁 | B13: 213.0127 | C13: 8.8204 | D13: 275.7504 | E13: 10.0254 | F13: 95.5728 | G13: -3.2957 | H13: 84.293 | I13: 6.4305
A14: 河南 | B14: 1165.1949 | C14: 19.7307 | D14: 1097.58 | E14: 67.0419 | F14: 473.5549 | G14: 45.0378 | H14: 574.0849 | I14: 14.2662
A15: 河北 | B15: 337.4897 | C15: 16.5286 | D15: 524.1794 | E15: 15.2153 | F15: 219.0104 | G15: -10.4309 | H15: 134.5265 | I15: 7.5371
A16: 福建 | B16: 323.9798 | C16: 23.6261 | D16: 418.188 | E16: 19.3079 | F16: 208.2671 | G16: -0.1456 | H16: 291.0163 | I16: -15.0794
... A36: 上市合计 | B36: 13056.834 | C36: 323.2283 | D36: 14109.73 | E36: 599.8418 | F36: 5725.3337 | G36: 98.993 | H36: 4234.1579 | I36: 200.3947
A37: ='分省业务-移动高清业务'!A39+1 -> 37

Sheet 分省业务-政企业务
A1: 政企市场-客户和DICT收入情况表（22/36)
B2: =主要经营情况表!A2 -> 45323
A3: 单位 | B3: 政企客户数 （万家） | D3: 政企成员数 （万户） | F3: DICT收入 (亿元) | H3: 其中：
H4: 行业云 | J4: ICT
B5: 到达数 | C5: 比上年 同期± | D5: 到达数 | E5: 比上年 同期± | F5: 本年 累计 | G5: 比上年 同期± | H5: 本年 累计 | I5: 比上年 同期± | J5: 本年 累计 | K5: 比上年 同期±
A6: 广东 | B6: 288.6394 | C6: 0.13386279 | D6: 1506.8057 | E6: 0.022063824 | F6: 34.987665 | G6: 0.0028705977 | H6: 18.445798 | I6: -0.031789445 | J6: 6.6906874 | K6: -0.31655172
A7: 浙江 | B7: 170.8207 | C7: 0.25828189 | D7: 1336.9598 | E7: -0.0013853301 | F7: 26.194641 | G7: 0.18144059 | H7: 17.668004 | I7: 0.25732158 | J7: 5.0403708 | K7: 0.1116436
A8: 江苏 | B8: 211.9356 | C8: 0.22149071 | D8: 1183.5128 | E8: 0.0009405441 | F8: 31.906519 | G8: 0.10737183 | H8: 19.833448 | I8: 0.13315085 | J8: 6.4987182 | K8: 0.066447313
A9: 山东 | B9: 252.4436 | C9: 0.24907338 | D9: 808.6144 | E9: 0.017447031 | F9: 16.23395 | G9: 0.1108518 | H9: 10.484943 | I9: -0.0084629354 | J9: 4.5982114 | K9: 0.30720314
A10: 北京 | B10: 51.2306 | C10: 0.18672313 | D10: 351.0958 | E10: 0.015084786 | F10: 7.6512545 | G10: -0.16774485 | H10: 3.0152923 | I10: -0.29287545 | J10: 0.099917841 | K10: -0.8345909
A11: 上海 | B11: 24.3374 | C11: -0.13590223 | D11: 469.6351 | E11: 0.00043520792 | F11: 8.8326112 | G11: 0.26426326 | H11: 5.7772427 | I11: 0.63972562 | J11: 0.55054301 | K11: -0.12255431
A12: 天津 | B12: 8.3786 | C12: -0.19169175 | D12: 153.1958 | E12: 0.11116607 | F12: 1.844528 | G12: 0.11786437 | H12: 1.313146 | I12: 0.062493289 | J12: 0.08949484 | K12: 0.18634598
A13: 四川 | B13: 212.0933 | C13: 0.10942486 | D13: 630.794 | E13: 0.10212987 | F13: 7.295235 | G13: -0.067070604 | H13: 4.4725784 | I13: 0.027423965 | J13: 1.4842486 | K13: -0.19213759
A14: 辽宁 | B14: 59.9029 | C14: 0.11556841 | D14: 576.8416 | E14: 0.0092576263 | F14: 4.0320741 | G14: 0.095081486 | H14: 3.1318067 | I14: 0.10442522 | J14: 0.64711527 | K14: 0.33041816
A15: 河南 | B15: 165.645 | C15: 0.045231857 | D15: 631.9214 | E15: -0.017136765 | F15: 15.25571 | G15: 0.37339712 | H15: 9.007992 | I15: 0.76615109 | J15: 3.8456081 | K15: 0.17071334
A16: 河北 | B16: 97.6206 | C16: 0.19220346 | D16: 603.5459 | E16: -0.011171033 | F16: 6.0297137 | G16: 0.21301436 | H16: 3.3448695 | I16: 0.07554159 | J16: 0.45852419 | K16: 0.47372681
A17: 福建 | B17: 149.541 | C17: 0.37930939 | D17: 639.0645 | E17: -0.022906778 | F17: 6.2071968 | G17: -0.086832013 | H17: 5.4925822 | I17: -0.051560141 | J17: 0.69037507 | K17: 0.32310022
... A37: 上市合计 | B37: 2779.3216 | C37: 0.21174131 | D37: 14526.877 | E37: 0.016708938 | F37: 235.5044 | G37: 0.068604181 | H37: 141.75076 | I37: 0.092528939 | J37: 56.155099 | K37: 0.098746852
A38: 注：1.政企客户数即有效集团客户数，指截至统计周期末，订购了集团单位产品（包含集团V网，不含校园V网、乡情网、家庭V网）
A39: 或集团代付业务，且近三个月累计通信和信息化收入大于0，处于在网状态的A、B、C、D类集团客户数
A40: 2.政企成员数为A、B、C类集团客户所包含的成员数,为集团在网、成员在网、剔除非18-60岁年龄、剔除物联网和IMS固话用户
A41: 3.DICT业务收入=行业云业务收入+IDC业务收入+ICT业务收入+政企市场其他应用及信息服务收入,取自管理会计报表
A42: 4.行业云收入=公有云+私有云收入，其中公有云收入=云标准化产品[IaaS+PaaS（含9one标准产品、云视讯）+SaaS]+云网收入（含
A43: IDC入云带宽）+云数+云智+云边+云通信;私有云收入=云定制化项目收入（含ICT9one）+云边_局域边缘云+云数_ICT大数据收入
A45: ='分省业务-家庭市场重点产品'!A37+1 -> 38

Sheet 分省业务-政企市场行业份额
A1: 政企市场-行业份额情况表（23/36)
A2: =主要经营情况表!A2 -> 45323
A3: 单位 | B3: 政企市场收入份额 | D3: DICT收入份额 | F3: 行业云收入份额 | H3: 专线收入份额
B4: 本年累计 | C4: 比上年 同期± | D4: 本年累计 | E4: 比上年 同期± | F4: 本年累计 | G4: 比上年 同期± | H4: 本年累计 | I4: 比上年 同期±
A5: 广东 | B5: 0.47550779 | C5: 1.0164619 | D5: 0.46980443 | E5: 0.72172225 | F5: 0.49502471 | G5: 6.2083699 | H5: 0.35757108 | I5: 2.6194443
A6: 浙江 | B6: 0.50960796 | C6: 1.5110503 | D6: 0.53005472 | E6: 2.8244195 | F6: 0.58531273 | G6: 7.4517404 | H6: 0.40340113 | I6: 3.2547643
A7: 江苏 | B7: 0.46426953 | C7: 0.51688838 | D7: 0.47059513 | E7: -0.77795376 | F7: 0.546036 | G7: 0.97172719 | H7: 0.3230787 | I7: 1.1162966
A8: 山东 | B8: 0.46345279 | C8: -0.38414655 | D8: 0.50512465 | E8: 0.15751668 | F8: 0.56060606 | G8: -8.4978951 | H8: 0.35142717 | I8: 1.3830203
A9: 北京 | B9: 0.30941525 | C9: -5.4427808 | D9: 0.22962456 | E9: -9.7684042 | F9: 0.2479605 | G9: -27.650646 | H9: 0.21927383 | I9: -0.23552514
A10: 上海 | B10: 0.2424418 | C10: -2.5748255 | D10: 0.20878755 | E10: -1.1138068 | F10: 0.15206987 | G10: -2.5373138 | H10: 0.18529907 | I10: -4.364019
A11: 天津 | B11: 0.29644351 | C11: -0.55601368 | D11: 0.33932059 | E11: 1.4686918 | F11: 0.47512209 | G11: 6.7315576 | H11: 0.17000496 | I11: -4.0117945
A12: 四川 | B12: 0.45367381 | C12: 0.76926002 | D12: 0.50136191 | E12: -3.0149907 | F12: 0.48468584 | G12: -2.6075384 | H12: 0.29583494 | I12: 3.3991084
A13: 辽宁 | B13: 0.36455565 | C13: 1.7715701 | D13: 0.33477229 | E13: 0.42165416 | F13: 0.4123632 | G13: 3.0724384 | H13: 0.35768899 | I13: 8.8491494
A14: 河南 | B14: 0.49120587 | C14: 1.0817507 | D14: 0.53359641 | E14: 1.5834524 | F14: 0.58888767 | G14: 21.871053 | H14: 0.33513536 | I14: 1.5463994
A15: 河北 | B15: 0.31816136 | C15: -5.7148929 | D15: 0.31113706 | E15: -8.3704219 | F15: 0.28109598 | G15: -18.023536 | H15: 0.25450478 | I15: 4.06853
A16: 福建 | B16: 0.375351 | C16: -1.5926535 | D16: 0.32746613 | E16: -2.6857541 | F16: 0.36860222 | G16: -5.42991 | H16: 0.35889722 | I16: 8.8740719
... A36: 合计 | B36: 0.40367639 | C36: -0.37351247 | D36: 0.41362015 | E36: -1.1773593 | F36: 0.45885283 | G36: 0.46657944 | H36: 0.29690013 | I36: 1.7822262
A37: 注：1.市场份额取自政企事业部，为上月值
A38: 2.本表市场份额均指在三家运营商中所占份额
A39: ='分省业务-政企业务'!A45+1 -> 39

Sheet 分省业务-5G 2B业务 
A1: 政企市场-5G 2B业务情况表（24/37)
A2: =主要经营情况表!A2 -> 45323
A3: 单位 | B3: 5G专网合同签约数 （个） | D3: 5G专网合同签约额 （万元） | F3: 5G专网收入 （万元） | H3: 5G物联卡客户数 （万户）
B4: 本年到达 | C4: 比去年 同期± | D4: 本年累计 | E4: 比去年 同期± | F4: 本年累计 | G4: 比去年 同期± | H4: 本年到达 | I4: 比去年 同期±
A5: 广东 | B5: 0 | C5: - | D5: 0 | E5: - | F5: 14353.215 | G5: 0.75804194 | H5: 354.7763 | I5: 1.892235
A6: 浙江 | B6: 0 | C6: -1 | D6: 0 | E6: -1 | F6: 19738.043 | G6: 0.46275064 | H6: 38.7381 | I6: 5.9580235
A7: 江苏 | B7: 0 | C7: -1 | D7: 0 | E7: -1 | F7: 23186.669 | G7: 0.34358248 | H7: 117.6781 | I7: 12.631352
A8: 山东 | B8: 0 | C8: -1 | D8: 0 | E8: -1 | F8: 10655.606 | G8: 0.52768584 | H8: 243.2995 | I8: 4.4977595
A9: 北京 | B9: 0 | C9: - | D9: 0 | E9: - | F9: 72.476111 | G9: -0.90659403 | H9: 142.6152 | I9: 6.0806643
A10: 上海 | B10: 0 | C10: -1 | D10: 0 | E10: -1 | F10: 886.57714 | G10: 0.23213499 | H10: 135.2054 | I10: 2.8379877
A11: 天津 | B11: 0 | C11: - | D11: 0 | E11: - | F11: 550.91963 | G11: -0.29903167 | H11: 9.5071 | I11: 35.692783
A12: 四川 | B12: 0 | C12: -1 | D12: 0 | E12: -1 | F12: 2228.7234 | G12: -0.10059971 | H12: 3.7411 | I12: 1.0143765
A13: 辽宁 | B13: 0 | C13: -1 | D13: 0 | E13: -1 | F13: 883.96109 | G13: -0.35267355 | H13: 2.3092 | I13: 0.2375134
A14: 河南 | B14: 0 | C14: -1 | D14: 0 | E14: -1 | F14: 3071.7706 | G14: 1.51724 | H14: 19.5852 | I14: 0.61507442
A15: 河北 | B15: 0 | C15: -1 | D15: 0 | E15: -1 | F15: 752.86637 | G15: -0.38249103 | H15: 4.0594 | I15: 1.0498914
A16: 福建 | B16: 0 | C16: -1 | D16: 0 | E16: -1 | F16: 4962.4481 | G16: -0.042027652 | H16: 6.7244 | I16: 2.7297687
A17: 湖南 | B17: 0 | C17: -1 | D17: 0 | E17: -1 | F17: 1683.6564 | G17: 0.71650034 | H17: 3.9439 | I17: 1.7117024
A18: 湖北 | B18: 0 | C18: -1 | D18: 0 | E18: -1 | F18: 3051.8679 | G18: 0.98544175 | H18: 3.6364 | I18: 1.200811
A19: 安徽 | B19: 0 | C19: - | D19: 0 | E19: - | F19: 2111.483 | G19: 1.0645149 | H19: 4.0929 | I19: 1.7469128
A20: 广西 | B20: 0 | C20: -1 | D20: 0 | E20: -1 | F20: 1346.515 | G20: 0.25275386 | H20: 9.6544 | I20: 0.31166784
A21: 江西 | B21: 0 | C21: -1 | D21: 0 | E21: -1 | F21: 2185.3563 | G21: 0.99406588 | H21: 9.5207 | I21: 0.80398287
A22: 陕西 | B22: 0 | C22: -1 | D22: 0 | E22: -1 | F22: 3598.5071 | G22: 0.19453113 | H22: 3.3358 | I22: 1.4931241
A23: 山西 | B23: 0 | C23: - | D23: 0 | E23: - | F23: 7358.537 | G23: 29.529577 | H23: 1.285 | I23: 1.8235553
A24: 云南 | B24: 0 | C24: - | D24: 0 | E24: - | F24: 1135.9625 | G24: 0.43262786 | H24: 5.3982 | I24: 0.71703935
A25: 黑龙江 | B25: 0 | C25: - | D25: 0 | E25: - | F25: 182.84424 | G25: 0.76714971 | H25: 4.6541 | I25: -0.82027726
A26: 吉林 | B26: 0 | C26: - | D26: 0 | E26: - | F26: 157.35281 | G26: 6.9448022 | H26: 0.3095 | I26: 1.4563492
A27: 重庆 | B27: 0 | C27: -1 | D27: 0 | E27: -1 | F27: 635.18484 | G27: 0.15793451 | H27: 25.7753 | I27: 13.234992
A28: 贵州 | B28: 0 | C28: - | D28: 0 | E28: - | F28: 1985.3871 | G28: 4.0890207 | H28: 13.6701 | I28: 36.197551
A29: 海南 | B29: 0 | C29: -1 | D29: 0 | E29: -1 | F29: 50.96322 | G29: 0.78057044 | H29: 0.6516 | I29: 1.2201022
A30: 内蒙古 | B30: 0 | C30: -1 | D30: 0 | E30: -1 | F30: 1430.0865 | G30: 0.080621318 | H30: 17.8591 | I30: 1.5417141
A31: 甘肃 | B31: 0 | C31: - | D31: 0 | E31: - | F31: 720.96646 | G31: 1.6942056 | H31: 2.2768 | I31: 0.95921177
A32: 青海 | B32: 0 | C32: - | D32: 0 | E32: - | F32: 69.108521 | G32: -0.63309376 | H32: 0.4035 | I32: 25.9
A33: 宁夏 | B33: 0 | C33: - | D33: 0 | E33: - | F33: 505.54943 | G33: 1.2960609 | H33: 0.2192 | I33: 0.12122762
A34: 新疆 | B34: 0 | C34: - | D34: 0 | E34: - | F34: 453.10342 | G34: 0.769552 | H34: 2.8462 | I34: 0.69750104
A35: 西藏 | B35: 0 | C35: - | D35: 0 | E35: - | F35: 158.29732 | G35: -0.45094989 | H35: 0.0702 | I35: 0.54966887
A36: 上市合计 | B36: 0 | C36: -1 | D36: 0 | E36: -1 | F36: 126698.55 | G36: 0.58498971 | H36: 1187.8419 | I36: 2.7451529
A37: 注：5G专网合同签约数、5G专网项目签约额为上月值
A38: ='分省业务-政企市场行业份额'!A39+1 -> 40

Sheet 分省业务-专线
A1: 政企市场-专线业务情况表（24/36)
A2: =主要经营情况表!A2 -> 45323
A3: 单位 | B3: 专线业务收入 （亿元） | D3: 专线订购条数 （万条） | G3: 其中：
G4: 互联网专线 （万条） | H4: 企业宽带 （万条） | I4: 数据专线 （万条）
B5: 本年累计 | C5: 比去年 同期± | D5: 到达数 | E5: 比去年 同期± | F5: 本年累计 净增 | G5: 到达数 | H5: 到达数 | I5: 到达数
A6: 广东 | B6: 9.5703696 | C6: 0.094579085 | D6: 375.8847 | E6: 0.18765302 | F6: 11.2287 | G6: 28.4842 | H6: 317.0406 | I6: 30.3599
A7: 浙江 | B7: 3.8156491 | C7: -0.13946016 | D7: 316.3742 | E7: 0.1075527 | F7: 5.1129 | G7: 7.5699 | H7: 268.4288 | I7: 40.3755
A8: 江苏 | B8: 4.7644342 | C8: 0.027537633 | D8: 315.9991 | E8: 0.14862234 | F8: 10.5256 | G8: 11.4598 | H8: 261.4615 | I8: 43.0778
A9: 山东 | B9: 3.6391227 | C9: -0.013388141 | D9: 304.4575 | E9: 0.20471213 | F9: 11.2042 | G9: 7.0245 | H9: 255.607 | I9: 41.826
A10: 北京 | B10: 4.7941174 | C10: 0.0039684959 | D10: 9.7589 | E10: 0.068953053 | F10: 0.4184 | G10: 0.7374 | H10: 6.9205 | I10: 2.101
A11: 上海 | B11: 3.4400479 | C11: -0.13419456 | D11: 34.5891 | E11: 0.21900341 | F11: 0.543 | G11: 0.9313 | H11: 32.1453 | I11: 1.5125
A12: 天津 | B12: 0.59116286 | C12: -0.26892948 | D12: 13.9492 | E12: 0.059929334 | F12: 0.2474 | G12: 0.5079 | H12: 11.8215 | I12: 1.6198
A13: 四川 | B13: 3.668612 | C13: 0.025996838 | D13: 230.3182 | E13: 0.19717213 | F13: 2.5397 | G13: 28.3709 | H13: 169.0273 | I13: 32.92
A14: 辽宁 | B14: 1.9157787 | C14: 0.088331342 | D14: 59.4367 | E14: 0.094153208 | F14: -1.4107 | G14: 3.9224 | H14: 42.7894 | I14: 12.7249
A15: 河南 | B15: 2.2714856 | C15: 0.042422682 | D15: 170.2242 | E15: 0.12457636 | F15: 6.7644 | G15: 16.9242 | H15: 131.2374 | I15: 22.0626
A16: 河北 | B16: 1.6574347 | C16: 0.071968194 | D16: 126.636 | E16: 0.30258355 | F16: 5.8458 | G16: 5.2027 | H16: 107.8125 | I16: 13.6208
A17: 福建 | B17: 2.183555 | C17: 0.064151972 | D17: 148.2351 | E17: 0.20211512 | F17: 0.7529 | G17: 2.7548 | H17: 131.3244 | I17: 14.1559
... A37: 上市合计 | B37: 66.553873 | C37: 0.026549739 | D37: 3958.1642 | E37: 0.18756934 | F37: 96.2492 | G37: 176.3126 | H37: 3349.7899 | I37: 432.0612
A38: 注：专线包括互联网专线、企业宽带、数据专线
A39: ='分省业务-政企市场行业份额'!A39+1 -> 40

Sheet 分省业务-IDC
A1: 政企市场-IDC业务情况表（25/36)
A2: =主要经营情况表!A2 -> 45323
A3: 单位 | B3: IDC业务收入 （亿元） | D3: IDC外部客户
D4: 已计费机架数 （架） | F4: 已计费机架总功率数 （千瓦） | G4: 已计费带宽量 （Gbps）
B5: 本年累计 | C5: 比去年 同期± | D5: 本年到达 | E5: 本年累计 净增 | F5: 本年到达 | G5: 本年到达 | H5: 本年累计 净增
A6: 广东 | B6: 12.576118 | C6: 0.22076408 | D6: 27736 | E6: -2530 | F6: 158570.34 | G6: 24093.94 | H6: 647.37
A7: 浙江 | B7: 4.5266297 | C7: -0.13020706 | D7: 11163 | E7: 185 | F7: 65018.4 | G7: 14377 | H7: -1308.36
A8: 江苏 | B8: 9.1532743 | C8: 0.031207841 | D8: 21465 | E8: 1207 | F8: 101653.92 | G8: 20478.15 | H8: -1899.81
A9: 山东 | B9: 3.7059504 | C9: -0.017808431 | D9: 5077 | E9: 944 | F9: 21986 | G9: 7510.67 | H9: -175.91
A10: 北京 | B10: 5.727595 | C10: 0.083622382 | D10: 26908 | E10: -1562 | F10: 158133.2 | G10: 1742.41 | H10: -39.31
A11: 上海 | B11: 5.458282 | C11: 0.21251839 | D11: 16731 | E11: 230 | F11: 97105.89 | G11: 1230.53 | H11: 271.62
A12: 天津 | B12: 0.73618591 | C12: -0.10542448 | D12: 2660 | E12: 110 | F12: 12471 | G12: 3755.58 | H12: -181.67
A13: 四川 | B13: 1.9512585 | C13: 0.025660813 | D13: 3745 | E13: 527 | F13: 21119.5 | G13: 5112.03 | H13: -237.09
A14: 辽宁 | B14: 0.78880499 | C14: 0.12398728 | D14: 2457 | E14: 113 | F14: 8881 | G14: 4326.83 | H14: -525.52
A15: 河南 | B15: 2.6392135 | C15: 0.016705318 | D15: 2421 | E15: 186 | F15: 10246 | G15: 8068.06 | H15: 92.43
A16: 河北 | B16: 3.3124505 | C16: 0.20972916 | D16: 9844 | E16: 390 | F16: 51584.7 | G16: 6984.84 | H16: 286.78
A17: 福建 | B17: 1.4696338 | C17: 0.11758511 | D17: 3726 | E17: -107 | F17: 15255.25 | G17: 8495.08 | H17: 94.96
... A37: 上市合计 | B37: 56.745273 | C37: 0.041271252 | D37: 166955 | E37: 850 | F37: 919750.58 | G37: 157358.22 | H37: -6531.2
A38: 注：IDC收入取自管理会计报表，包含IDC入云带宽收入
A39: ='分省业务-专线'!A39+1 -> 41

Sheet 分省业务-物联网
A1: 政企市场-物联网业务情况表（26/36)
A2: =主要经营情况表!$A$2 -> 45323
A3: 单位 | B3: 物联网业务收入 （万元） | D3: 物联网卡客户数 （万户） | G3: 5G物联卡客户数 （万户） | I3: 其中：NB-IoT客户数 （万户） | K3: 物联网卡客户份额 （%）
B4: 本年累计 | C4: 比去年 同期± | D4: 到达数 | E4: 比去年 同期± | F4: 本年累计 净增 | G4: 本年到达 | H4: 比去年 同期± | I4: 到达数 | J4: 比去年 同期± | K4: 本年累计 | L4: 比上年 同期± | M4: 本年累计净增客户份额
A6: 广东 | B6: 88157.974 | C6: 0.055438334 | D6: 22976.531 | E6: 0.17210884 | F6: -572.893 | G6: 354.7763 | H6: 1.892235 | I6: 892.2098 | J6: -0.18739028 | K6: 0.55817529 | L6: -2.1278918 | M6: -1.0992684
A7: 浙江 | B7: 53632.095 | C7: 0.32450447 | D7: 13764.141 | E7: 0.18521999 | F7: 69.5307 | G7: 38.7381 | H7: 5.9580235 | I7: 1744.8845 | J7: -0.20311242 | K7: 0.60342149 | L7: -0.65475297 | M7: 0.52825486
A8: 江苏 | B8: 75920.519 | C8: 0.31824007 | D8: 17713.091 | E8: 0.15609748 | F8: 237.3296 | G8: 117.6781 | H8: 12.631352 | I8: 2756.3601 | J8: -0.00029849305 | K8: 0.60965105 | L8: -3.5479972 | M8: 0.38004677
A9: 山东 | B9: 45120.81 | C9: 0.1372046 | D9: 10029.503 | E9: 0.32547983 | F9: 461.6652 | G9: 243.2995 | H9: 4.4977595 | I9: 3183.785 | J9: 0.092660467 | K9: 0.4232472 | L9: 1.7055917 | M9: 0.3472068
A10: 北京 | B10: 8146.2713 | C10: -0.16476368 | D10: 11499.573 | E10: 0.17752439 | F10: 102.9788 | G10: 142.6152 | H10: 6.0806643 | I10: 767.4631 | J10: 0.24577488 | K10: 0.72260821 | L10: -0.37114068 | M10: 0.56603954
A11: 上海 | B11: 11385.712 | C11: 0.15010812 | D11: 9138.4589 | E11: 0.16479238 | F11: -226.4845 | G11: 135.2054 | H11: 2.8379877 | I11: 237.3125 | J11: -0.3143447 | K11: 0.55912401 | L11: -1.2354426 | M11: -
A12: 天津 | B12: 2296.6611 | C12: -0.25657672 | D12: 547.401 | E12: 0.37773921 | F12: 0.2612 | G12: 9.5071 | H12: 35.692783 | I12: 408.428 | J12: 0.051952701 | K12: 0.37168817 | L12: 3.4548681 | M12: 0.38235546
A13: 四川 | B13: 7593.7377 | C13: -0.14096764 | D13: 3279.4635 | E13: 0.18360376 | F13: 21.7577 | G13: 3.7411 | H13: 1.0143765 | I13: 145.3401 | J13: 0.89449666 | K13: 0.70425802 | L13: -1.9560511 | M13: 0.053582539
A14: 辽宁 | B14: 8480.5123 | C14: 0.29396629 | D14: 1789.7943 | E14: 0.30210164 | F14: 1.3278 | G14: 2.3092 | H14: 0.2375134 | I14: 310.3531 | J14: 1.1580683 | K14: 0.63217852 | L14: 6.1133463 | M14: 0.59328662
A15: 河南 | B15: 18827.883 | C15: 0.69534871 | D15: 8066.6392 | E15: 0.16078548 | F15: 77.3568 | G15: 19.5852 | H15: 0.61507442 | I15: 873.8073 | J15: 0.017240203 | K15: 0.77021939 | L15: -0.73010319 | M15: 0.33124151
A16: 河北 | B16: 8871.6635 | C16: 0.012420708 | D16: 3213.0043 | E16: 0.27465821 | F16: -52.6511 | G16: 4.0594 | H16: 1.0498914 | I16: 673.79 | J16: 0.25748005 | K16: 0.36122467 | L16: -1.5650397 | M16: -1.107061
A17: 福建 | B17: 11309.577 | C17: -0.12577652 | D17: 3885.5966 | E17: 0.30506665 | F17: 32.8167 | G17: 6.7244 | H17: 2.7297687 | I17: 258.9828 | J17: 0.99884384 | K17: 0.51994499 | L17: 5.2712185 | M17: -0.1041424
A18: 湖南 | B18: 7108.2005 | C18: 0.62357598 | D18: 2178.8768 | E18: 0.50366151 | F18: 13.5782 | G18: 3.9439 | H18: 1.7117024 | I18: 296.0796 | J18: 0.30578515 | K18: 0.36645042 | L18: 0.94751416 | M18: 0.30922018
A19: 湖北 | B19: 7585.9066 | C19: 0.44450437 | D19: 1486.7464 | E19: 0.45642822 | F19: 9.0927 | G19: 3.6364 | H19: 1.200811 | I19: 119.1939 | J19: 0.47899765 | K19: 0.20985452 | L19: -1.2691586 | M19: 0.059494182
A20: 安徽 | B20: 9152.5137 | C20: 0.32033748 | D20: 2350.772 | E20: 0.46932617 | F20: 35.211 | G20: 4.0929 | H20: 1.7469128 | I20: 305.5989 | J20: 1.2096923 | K20: 0.53551848 | L20: 5.4355563 | M20: 7.1262316
A21: 广西 | B21: 8692.5172 | C21: 0.016328831 | D21: 4322.8084 | E21: 0.22361986 | F21: -249.3573 | G21: 9.6544 | H21: 0.31166784 | I21: 379.0402 | J21: 0.040251544 | K21: 0.77022813 | L21: 1.5305158 | M21: -
A22: 江西 | B22: 11274.615 | C22: 1.184524 | D22: 1751.6814 | E22: 0.39123231 | F22: -76.4775 | G22: 9.5207 | H22: 0.80398287 | I22: 177.1787 | J22: 0.064611415 | K22: 0.49766079 | L22: 2.1432526 | M22: -
A23: 陕西 | B23: 13126.989 | C23: 0.062726391 | D23: 5219.189 | E23: 0.33691794 | F23: 185.8603 | G23: 3.3358 | H23: 1.4931241 | I23: 255.3996 | J23: 0.11587414 | K23: 0.67470104 | L23: -6.2650916 | M23: 0.84899208
A24: 山西 | B24: 9882.612 | C24: 2.1630536 | D24: 1946.5326 | E24: 0.15434896 | F24: -171.7621 | G24: 1.285 | H24: 1.8235553 | I24: 133.6282 | J24: -0.18063594 | K24: 0.82471474 | L24: 1.3869854 | M24: -
A25: 云南 | B25: 6191.4854 | C25: -0.21395927 | D25: 728.5123 | E25: 0.36664739 | F25: 2.522 | G25: 5.3982 | H25: 0.71703935 | I25: 144.4121 | J25: 0.6517983 | K25: 0.47298671 | L25: 8.8721935 | M25: -
A26: 黑龙江 | B26: 1945.7018 | C26: 0.5005995 | D26: 745.9511 | E26: 0.24318615 | F26: -19.199 | G26: 4.6541 | H26: -0.82027726 | I26: 127.8336 | J26: 0.23357452 | K26: 0.51620491 | L26: 7.0459543 | M26: -
A27: 吉林 | B27: 1823.2494 | C27: 0.67528558 | D27: 619.7804 | E27: 0.18529877 | F27: -4.3024 | G27: 0.3095 | H27: 1.4563492 | I27: 80.9975 | J27: 1.0815505 | K27: 0.37956558 | L27: -7.0916819 | M27: -0.012302521
A28: 重庆 | B28: 4651.8959 | C28: 0.296182 | D28: 1489.3448 | E28: 0.29607636 | F28: -11.7417 | G28: 25.7753 | H28: 13.234992 | I28: 71.3858 | J28: 0.048120349 | K28: 0.35244809 | L28: 2.1760794 | M28: 0.019637775
A29: 贵州 | B29: 5096.2517 | C29: 0.86275537 | D29: 764.266 | E29: 0.66528921 | F29: 43.7054 | G29: 13.6701 | H29: 36.197551 | I29: 12.5428 | J29: 0.31606946 | K29: 0.70655748 | L29: 16.000596 | M29: 1.1620034
A30: 海南 | B30: 926.41487 | C30: 0.012968129 | D30: 221.7953 | E30: 0.18700803 | F30: -47.876 | G30: 0.6516 | H30: 1.2201022 | I30: 10.4341 | J30: -0.058668038 | K30: 0.63971515 | L30: 7.8738637 | M30: 0.1126087
A31: 内蒙古 | B31: 3900.1622 | C31: -0.015470253 | D31: 707.6089 | E31: 0.059149999 | F31: -59.9681 | G31: 17.8591 | H31: 1.5417141 | I31: 104.7617 | J31: 0.26149306 | K31: 0.58481235 | L31: 0.74669727 | M31: -
A32: 甘肃 | B32: 3560.3432 | C32: 0.8625733 | D32: 239.2931 | E32: 0.33546392 | F32: 4.4729 | G32: 2.2768 | H32: 0.95921177 | I32: 94.7456 | J32: 0.33814854 | K32: 0.4423336 | L32: 4.2812196 | M32: 0.53173853
A33: 青海 | B33: 404.21458 | C33: -0.1540477 | D33: 70.0206 | E33: 0.23482015 | F33: -2.3797 | G33: 0.4035 | H33: 25.9 | I33: 27.4166 | J33: 0.22898652 | K33: 0.61898714 | L33: -0.59454165 | M33: -0.10579439
A34: 宁夏 | B34: 1425.4557 | C34: 0.62891991 | D34: 110.9769 | E34: 0.29641973 | F34: 2.3044 | G34: 0.2192 | H34: 0.12122762 | I34: 63.4533 | J34: 0.35795793 | K34: 0.36797154 | L34: -9.4257719 | M34: 0.65010638
A35: 新疆 | B35: 4036.5335 | C35: 0.0076612778 | D35: 507.2066 | E35: 0.22206061 | F35: 2.04 | G35: 2.8462 | H35: 0.69750104 | I35: 223.9094 | J35: 0.35321879 | K35: 0.49750937 | L35: 1.1128643 | M35: 0.42070896
A36: 西藏 | B36: 1263.0297 | C36: 0.38192608 | D36: 26.5058 | E36: 0.048966104 | F36: -0.3144 | G36: 0.0702 | H36: 0.54966887 | I36: 6.5261 | J36: -0.023155909 | K36: 0.17965822 | L36: -0.018791931 | M36: -0.54097561
A37: 上市合计 | B37: 476071.7 | C37: 0.21353504 | D37: 131391.07 | E37: 0.21615627 | F37: -191.5954 | G37: 1187.8419 | H37: 2.7451529 | I37: 14887.254 | J37: 0.053143671 | K37: 0.55873665 | L37: -1.0527457 | M37: -0.065622755
A38: 注：市场份额根据工业和信息化部公布数据计算得出，为上月值
A39: ='分省业务-IDC'!A39+1 -> 42

Sheet 分省业务-新兴市场重点产品
A1: 新兴市场-重点产品情况表（27/36)
E2: ='分省业务-物联网'!A2 -> 45323 | K2: 单位：万户
A3: 单位 | B3: 咪咕视频会员到达数 | D3: 咪咕视频手机APP 月活用户数 | F3: 视频彩铃 会员用户数 | H3: 视频彩铃 行为月活用户数 | J3: 咪咕音乐全场景 月活用户数
B4: 本月 | C4: 环比变化± | D4: 本月 | E4: 环比变化 ± | F4: 本月 | G4: 环比变化 ± | H4: 本月 | I4: 环比变化 ± | J4: 本月 | K4: 环比变化 ±
A5: 广东 | B5: 1559.4592 | C5: 0.031923499 | D5: 978.6777 | E5: 0.23643916 | F5: 1178.6796 | G5: 0.035185408 | H5: 475.0427 | I5: 0.1754453 | J5: 1716.7182 | K5: -0.058150356
A6: 浙江 | B6: 2656.5375 | C6: 0.0014397307 | D6: 1456.5544 | E6: -0.022569185 | F6: 1834.8699 | G6: -0.014242281 | H6: 833.1021 | I6: -0.050258969 | J6: 989.9792 | K6: -0.0076537565
A7: 江苏 | B7: 2365.1829 | C7: -0.0069091524 | D7: 726.7007 | E7: -0.010763164 | F7: 1754.4969 | G7: 0.0021112056 | H7: 557.9645 | I7: 0.042885118 | J7: 1106.7198 | K7: -0.018878037
A8: 山东 | B8: 1420.4711 | C8: -0.0088354644 | D8: 427.4075 | E8: -0.023631183 | F8: 1117.2368 | G8: 0.0076595659 | H8: 679.9622 | I8: 0.36730484 | J8: 1145.3162 | K8: -0.025813162
A9: 北京 | B9: 199.6628 | C9: 0.022292379 | D9: 184.7536 | E9: -0.090933872 | F9: 113.701 | G9: 0.18586899 | H9: 177.7043 | I9: 0.15450728 | J9: 315.7178 | K9: 0.092205751
A10: 上海 | B10: 482.8694 | C10: -0.015403218 | D10: 407.8712 | E10: 0.032678911 | F10: 363.8284 | G10: 0.035432182 | H10: 120.9222 | I10: 0.25782172 | J10: 397.1974 | K10: -0.031689462
A11: 天津 | B11: 184.413 | C11: 0.01010859 | D11: 57.8777 | E11: -0.1580556 | F11: 183.7916 | G11: 0.0079018068 | H11: 77.0223 | I11: 0.14231835 | J11: 110.1708 | K11: -0.033501302
A12: 四川 | B12: 1089.8949 | C12: 0.0022113305 | D12: 346.9972 | E12: -0.068481148 | F12: 561.8007 | G12: -0.027204644 | H12: 321.6147 | I12: 0.55784922 | J12: 1318.0244 | K12: 0.011759374
A13: 辽宁 | B13: 597.8492 | C13: -0.011590128 | D13: 552.2743 | E13: 0.10654747 | F13: 375.257 | G13: -0.02523864 | H13: 204.254 | I13: 0.48783712 | J13: 550.6933 | K13: -0.027439022
A14: 河南 | B14: 2264.4687 | C14: -0.020139452 | D14: 361.1518 | E14: 0.12010686 | F14: 479.9865 | G14: -0.045993547 | H14: 403.531 | I14: 0.18293376 | J14: 1083.0217 | K14: -0.024699991
A15: 河北 | B15: 665.0772 | C15: -0.061667265 | D15: 333.9068 | E15: -0.077012212 | F15: 433.2758 | G15: -0.014801989 | H15: 291.2479 | I15: 0.3001378 | J15: 642.9649 | K15: -0.042799614
A16: 福建 | B16: 650.1914 | C16: -0.032022293 | D16: 322.2003 | E16: -0.027520363 | F16: 485.5376 | G16: -0.038152572 | H16: 320.9058 | I16: 0.11297478 | J16: 661.9435 | K16: -0.01738224
... A36: 上市合计 | B36: 24717.566 | C36: -0.011224986 | D36: 9332.8652 | E36: 0.024802118 | F36: 16378.542 | G36: -0.0026504336 | H36: 8421.0632 | I36: 0.20730455 | J36: 18517.158 | K36: -0.021068853
A37: ='分省业务-物联网'!A39+1 -> 43

Sheet 分省业务-新兴市场重点产品（续）
A1: 新兴市场-重点产品情况表（续）（28/36)
E2: ='分省业务-新兴市场重点产品'!E2 -> 45323 | K2: 单位：万户
A3: 单位 | B3: 云游戏核心用户 月活规模 | D3: 云游戏会员用户数 | F3: 和包客户端交易 月活用户数 | H3: 咪咕阅读全场景 月活用户数 | J3: 云VR全场景月活用户数
B4: 本月 | C4: 环比变化 ± | D4: 本月 | E4: 环比变化 ± | F4: 本月 | G4: 环比变化 ± | H4: 本月 | I4: 环比变化 ± | J4: 本月 | K4: 环比变化 ±
A5: 广东 | B5: 339.4904 | C5: 0.0053961239 | D5: 166.5613 | E5: 0.052071312 | F5: 1667.2487 | G5: -0.06219451 | H5: 779.5792 | I5: 0.005107542 | J5: 89.6478 | K5: -0.13127431
A6: 浙江 | B6: 277.5316 | C6: -0.059792426 | D6: 177.3856 | E6: -0.17038085 | F6: 659.859 | G6: 0.26832813 | H6: 1363.7471 | I6: -0.0099095649 | J6: 270.666 | K6: -0.18747028
A7: 江苏 | B7: 395.0205 | C7: -0.013494939 | D7: 1086.6551 | E7: -0.0099985441 | F7: 268.7914 | G7: -0.67139476 | H7: 652.6443 | I7: -0.11896452 | J7: 18.6175 | K7: -0.23577559
A8: 山东 | B8: 399.2132 | C8: 0.062825217 | D8: 627.638 | E8: -0.0057032362 | F8: 817.7447 | G8: 1.4487238 | H8: 570.6739 | I8: 0.010028 | J8: 4.6552 | K8: -0.17548707
A9: 北京 | B9: 63.2557 | C9: -0.22638043 | D9: 25.9794 | E9: 0.0051730075 | F9: 62.7331 | G9: -0.11887258 | H9: 335.9091 | I9: 0.018264916 | J9: 16.9768 | K9: -0.22969981
A10: 上海 | B10: 74.9051 | C10: -0.18494681 | D10: 0.9452 | E10: -0.11910531 | F10: 159.9133 | G10: -0.095057979 | H10: 214.3353 | I10: 0.034023067 | J10: 5.3122 | K10: -0.20316203
A11: 天津 | B11: 60.2172 | C11: -0.021768372 | D11: 136.5236 | E11: 0.021775396 | F11: 51.8654 | G11: -0.044357394 | H11: 111.2671 | I11: 0.014746909 | J11: 0.4629 | K11: -0.41419894
A12: 四川 | B12: 244.4076 | C12: -0.092550307 | D12: 98.2987 | E12: -0.01875471 | F12: 248.8734 | G12: -0.074838646 | H12: 427.4959 | I12: 0.0060135478 | J12: 100.5862 | K12: -0.31375188
A13: 辽宁 | B13: 118.9165 | C13: -0.10426586 | D13: 23.8278 | E13: -0.13106044 | F13: 134.3404 | G13: -0.081735169 | H13: 276.0644 | I13: 0.0024776483 | J13: 4.7477 | K13: -0.34401382
A14: 河南 | B14: 300.3646 | C14: -0.03041918 | D14: 128.6375 | E14: -0.079206 | F14: 357.3769 | G14: -0.39201287 | H14: 285.9444 | I14: 0.014769542 | J14: 4.3817 | K14: 0.051095066
A15: 河北 | B15: 243.0004 | C15: -0.085054063 | D15: 181.8529 | E15: -0.15956425 | F15: 237.3355 | G15: -0.08937871 | H15: 296.2567 | I15: 0.0064427868 | J15: 3.3141 | K15: -0.27791093
A16: 福建 | B16: 122.5668 | C16: -0.036210858 | D16: 24.7502 | E16: -0.00012523583 | F16: 168.1788 | G16: -0.022809979 | H16: 245.5352 | I16: 0.0091513411 | J16: 76.195 | K16: 0.24386597
... A36: 上市合计 | B36: 5218.8556 | C36: -0.033416686 | D36: 4768.371 | E36: -0.018574017 | F36: 8215.0394 | G36: -0.018532033 | H36: 10143.766 | I36: -0.0030033348 | J36: 758.3086 | K36: -0.16674631
A37: ='分省业务-新兴市场重点产品'!A37+1 -> 44

Sheet 分省业务-移动语音短彩信
A1: 移动语音和短彩信业务情况表（29/36)
A2: =主要经营情况表!$A$2 -> 45323
A3: 单位 | B3: 移动语音业务收入 （亿元） | D3: 移动电话计费时长 （亿分钟） | F3: 短彩信收入 （亿元） | H3: 短彩信计费量 （亿条）
B4: 本年累计 | C4: 比上年 同期± | D4: 本年累计 | E4: 比上年 同期± | F4: 本年累计 | G4: 比上年 同期± | H4: 本年累计 | I4: 比上年 同期±
A5: 广东 | B5: 15.07242 | C5: 0.16832774 | D5: 426.55296 | E5: -0.01995886 | F5: 9.6728453 | G5: 0.47574905 | H5: 201.64049 | I5: 0.477969
A6: 浙江 | B6: 10.075296 | C6: -0.081598353 | D6: 283.17907 | E6: -0.053922651 | F6: 2.367136 | G6: 0.19851905 | H6: 77.504529 | I6: -0.038584916
A7: 江苏 | B7: 9.3831083 | C7: -0.041971034 | D7: 254.15888 | E7: -0.070720741 | F7: 2.9058366 | G7: -0.11769739 | H7: 66.584136 | I7: -0.084101045
A8: 山东 | B8: 6.8893451 | C8: 0.075833269 | D8: 354.17912 | E8: -0.075441327 | F8: 2.2297231 | G8: -0.05232504 | H8: 71.33021 | I8: -0.21038473
A9: 北京 | B9: 3.0321236 | C9: -0.13934339 | D9: 63.420316 | E9: -0.10065846 | F9: 18.118561 | G9: -0.039949442 | H9: 386.06654 | I9: 0.17123798
A10: 上海 | B10: 1.568369 | C10: -0.1951391 | D10: 66.676409 | E10: -0.099492105 | F10: 4.7103264 | G10: -0.25307945 | H10: 76.664232 | I10: -0.28654738
A11: 天津 | B11: 1.37425 | C11: -0.024467407 | D11: 35.111929 | E11: -0.072673148 | F11: 0.099585724 | G11: 0.33857886 | H11: 2.6425288 | I11: -0.29589572
A12: 四川 | B12: 6.1514526 | C12: -0.029509306 | D12: 291.44349 | E12: -0.033607637 | F12: 0.95375317 | G12: -0.00087642064 | H12: 58.841549 | I12: -0.093991402
A13: 辽宁 | B13: 3.8069509 | C13: -0.1006517 | D13: 130.93776 | E13: -0.10112744 | F13: 0.22261194 | G13: -0.76993863 | H13: 6.2036369 | I13: -0.83836831
A14: 河南 | B14: 5.1152212 | C14: -0.23088266 | D14: 254.20968 | E14: -0.098683422 | F14: 1.6032746 | G14: 0.80607182 | H14: 82.833891 | I14: 0.94340759
A15: 河北 | B15: 3.9233731 | C15: -0.055690767 | D15: 142.45079 | E15: -0.24652046 | F15: 0.54306655 | G15: -0.034708545 | H15: 56.009835 | I15: 0.13525279
A16: 福建 | B16: 4.9400117 | C16: 0.14086307 | D16: 149.81671 | E16: -0.040061367 | F16: 2.9094852 | G16: -0.25485009 | H16: 125.83594 | I16: -0.21254082
... A37: 上市合计 | B37: 122.02748 | C37: -0.052535843 | D37: 4307.7519 | E37: -0.06763202 | F37: 56.162793 | G37: -0.0017397185 | H37: 1552.7433 | I37: 0.0039086597
A38: ='分省业务-新兴市场重点产品（续）'!A37+1 -> 45

Sheet 分省业务-资本开支和基站
A1: 资本开支和基站情况表（30/36)
A2: =主要经营情况表!A2 -> 45323
A3: 单位 | B3: 资本开支（亿元） | E3: 基站数（万个） | H3: 其中：5G基站数（万个） | K3: 其中：4G基站数（万个）
B4: 本年累计 | C4: 比上年 同期± | D4: 占通信服务收入比重 | E4: 到达数 | F4: 比上年同期± | G4: 本年累计 净增 | H4: 到达数 | I4: 比上年同期± | J4: 本年累计 净增 | K4: 到达数 | L4: 比上年同期± | M4: 本年累计 净增
A5: 广东 | B5: 13.241631 | C5: 1.7942062 | D5: 0.06201992 | E5: 65.0341 | F5: 0.082166593 | G5: 1.1419 | H5: 20.5371 | I5: 0.44237414 | J5: 1.1451 | K5: 33.1609 | L5: 0.015262198 | M5: 0.0252
A6: 浙江 | B6: 10.920891 | C6: 0.44834182 | D6: 0.079755639 | E6: 46.8464 | F6: 0.090932802 | G6: 0.0636 | H6: 14.7357 | I6: 0.3979679 | J6: 0.0015 | K6: 23.0265 | L6: 0.0079977937 | M6: 0.1123
A7: 江苏 | B7: 7.9990998 | C7: 0.16978727 | D7: 0.057218873 | E7: 47.2694 | F7: 0.093121135 | G7: 0.2631 | H7: 13.7331 | I7: 0.40135103 | J7: 0 | K7: 24.0963 | L7: 0.034255865 | M7: 0.446
A8: 山东 | B8: 7.626948 | C8: 2.5219938 | D8: 0.078033691 | E8: 36.7193 | F8: 0.088221086 | G8: -0.0401 | H8: 10.7877 | I8: 0.375 | J8: 0.002 | K8: 17.2428 | L8: 0.020652425 | M8: 0.0158
A9: 北京 | B9: 3.7947375 | C9: -0.32310906 | D9: 0.077692154 | E9: 17.3152 | F9: 0.14605686 | G9: 0.1816 | H9: 6.1533 | I9: 0.4635382 | J9: 0.2929 | K9: 7.7298 | L9: 0.032512289 | M9: -0.1084
A10: 上海 | B10: 3.2944482 | C10: 0.67359998 | D10: 0.079414605 | E10: 13.2761 | F10: 0.10294093 | G10: 0.0448 | H10: 5.0734 | I10: 0.39145937 | J10: 0.0709 | K10: 5.669 | L10: 0.011454468 | M10: -0.0003
A11: 天津 | B11: 1.8539891 | C11: 0.62884187 | D11: 0.18154604 | E11: 7.2767 | F11: 0.14655091 | G11: -0.1272 | H11: 2.6721 | I11: 0.58788923 | J11: 0 | K11: 3.1263 | L11: 0.080530882 | M11: 0.0177
A12: 四川 | B12: 9.2333627 | C12: 0.19981853 | D12: 0.1263269 | E12: 31.4929 | F12: 0.10317927 | G12: 0.5351 | H12: 10.1091 | I12: 0.55378798 | J12: 0.6809 | K12: 16.0253 | L12: -9.9832157e-05 | M12: 0.0012
A13: 辽宁 | B13: 3.6849574 | C13: -0.28290834 | D13: 0.10230193 | E13: 19.7281 | F13: 0.15247692 | G13: -0.1519 | H13: 6.7067 | I13: 0.84788119 | J13: 0 | K13: 9.7726 | L13: 0.019593523 | M13: -0.1241
A14: 河南 | B14: 6.4276072 | C14: -0.55835423 | D14: 0.073680917 | E14: 34.6408 | F14: 0.15495897 | G14: 0.9237 | H14: 11.5312 | I14: 0.75783167 | J14: 0.9671 | K14: 17.4113 | L14: 0 | M14: 0
A15: 河北 | B15: 4.4363544 | C15: -0.58176572 | D15: 0.098112143 | E15: 29.293 | F15: 0.15370831 | G15: 0.4775 | H15: 8.8425 | I15: 0.8984692 | J15: 0.5169 | K15: 15.1902 | L15: 0.0023226658 | M15: 0.0397
A16: 福建 | B16: 5.6804479 | C16: 0.4528163 | D16: 0.10851793 | E16: 26.1501 | F16: 0.079333829 | G16: 0.2368 | H16: 6.5402 | I16: 0.48786314 | J16: 0.2946 | K16: 13.43 | L16: 0.0027027431 | M16: -0.0434
... A37: 上市合计 | B37: 134.1946 | C37: -0.15211787 | D37: 0.084929147 | E37: 667.1712 | F37: 0.098158941 | G37: 5.5786 | H37: 200.5492 | I37: 0.51223897 | J37: 5.9867 | K37: 337.7592 | L37: 0.010211003 | M37: 0.7668
A38: 注：基站数=GSM基站+TD-LTE基站+LTE FDD基站+5G基站+NB-IoT基站
A39: ='分省业务-移动语音短彩信'!A38+1 -> 46

Sheet 分省业务-网络运行 
A1: 网络运行情况表（31/36)
A2: =主要经营情况表!A2 -> 45323
A3: 省份 | B3: 5G无线网络利用率 | C3: 700M网络利用率 | D3: 5G SA时长驻留比 | E3: 5G流量占比 | F3: 2C 5G SA网日均流量 （TB） | G3: 5G零低流量小区占比
A4: 广东 | B4: 0.162639 | C4: 0.201076 | D4: 0.92342857 | E4: 0.58080423 | F4: 25174.551 | G4: 0.0068
A5: 浙江 | B5: 0.128796 | C5: 0.180007 | D5: 0.95074286 | E5: 0.63290817 | F5: 15077.621 | G5: 0.0044
A6: 江苏 | B6: 0.165247 | C6: 0.199537 | D6: 0.96681429 | E6: 0.60708062 | F6: 15920.194 | G6: 0.0067
A7: 山东 | B7: 0.208155 | C7: 0.247864 | D7: 0.97378571 | E7: 0.59706966 | F7: 14794.513 | G7: 0.001
A8: 北京 | B8: 0.131157 | C8: 0.135407 | D8: 0.94985714 | E8: 0.60178533 | F8: 4243.9186 | G8: 0.0064
A9: 上海 | B9: 0.146187 | C9: 0.148899 | D9: 0.9753 | E9: 0.60037293 | F9: 3781.9569 | G9: 0.0088
A10: 天津 | B10: 0.141389 | C10: 0.16486 | D10: 0.96911429 | E10: 0.59000965 | F10: 1780.1084 | G10: 0.0078
A11: 四川 | B11: 0.1876 | C11: 0.278441 | D11: 0.93272857 | E11: 0.56031045 | F11: 14587.997 | G11: 0.0011
A12: 辽宁 | B12: 0.166511 | C12: 0.189698 | D12: 0.94008571 | E12: 0.56424152 | F12: 4911.3793 | G12: 0.0066
A13: 河南 | B13: 0.216642 | C13: 0.335397 | D13: 0.94741429 | E13: 0.59389351 | F13: 16141.431 | G13: 0.0053
A14: 河北 | B14: 0.178215 | C14: 0.231945 | D14: 0.95787143 | E14: 0.5311237 | F14: 6744.4499 | G14: 0.0067
A15: 福建 | B15: 0.18185 | C15: 0.197293 | D15: 0.94687143 | E15: 0.5469172 | F15: 6970.3962 | G15: 0.0008
... A35: 上市合计 | B35: 0.181471 | C35: 0.23447 | D35: 0.938 | E35: 0.57729294 | F35: 235746.49 | G35: 0.0051
A36: 注：1.5G流量占比=（5G NSA流量+5G SA流量）/（5G NSA流量+5G SA流量+4G流量）*100%
A37: 2.零低流量为流量<500MB的小区，取连续7天数据，如5个工作日中出现2天及以上日均流量为零低流量，且2个周末中
A38: 出现1天及以上日均零低流量，即算为5G零低流量小区。
A39: ='分省业务-资本开支和基站'!A39+1 -> 47

Sheet 分省业务-网络运行 (续)
A1: 网络运行情况表（续）（32/36)
A2: =主要经营情况表!A2 -> 45323
A3: 省份 | B3: 4G网忙时 无线利用率 | C3: “高4无5”站点比例 | D3: 家宽单用户中断时长（分钟） | E3: 家宽装机及时率 | F3: PON口利用率 | G3: 10GPON口利用率
A4: 广东 | B4: 0.2044 | C4: 0.024359605 | D4: 0.26458741 | E4: 0.9999 | F4: 0.69297321 | G4: 0.73463047
A5: 浙江 | B5: 0.1639 | C5: 0.011166116 | D5: 0.20289334 | E5: 0.9974 | F5: 0.75038251 | G5: 0.84452148
A6: 江苏 | B6: 0.176 | C6: 0.015862885 | D6: 0.30238797 | E6: 1 | F6: 0.73998365 | G6: 0.97184303
A7: 山东 | B7: 0.2047 | C7: 0.004289114 | D7: 0.12119253 | E7: 1 | F7: 0.81710417 | G7: 0.86958005
A8: 北京 | B8: 0.2031 | C8: 0.015113739 | D8: 0.11335608 | E8: 0.9999 | F8: 0.68671004 | G8: 0.84049676
A9: 上海 | B9: 0.1957 | C9: 0.023508275 | D9: 0.23761684 | E9: 0.9993 | F9: 0.81232529 | G9: 0.82547264
A10: 天津 | B10: 0.1736 | C10: 0.01275483 | D10: 0.19930827 | E10: 0.9963 | F10: 0.58143826 | G10: 0.70544066
A11: 四川 | B11: 0.262 | C11: 0.040764513 | D11: 0.32499214 | E11: 1 | F11: 0.78729588 | G11: 0.84412839
A12: 辽宁 | B12: 0.2316 | C12: 0.010873749 | D12: 0.13734541 | E12: 1 | F12: 0.62920875 | G12: 0.77868777
A13: 河南 | B13: 0.2551 | C13: 0.026271044 | D13: 0.27213565 | E13: 1 | F13: 0.86435887 | G13: 0.88606846
A14: 河北 | B14: 0.1975 | C14: 0.012016741 | D14: 0.20644667 | E14: 1 | F14: 0.6748474 | G14: 0.83232179
A15: 福建 | B15: 0.1927 | C15: 0.018578278 | D15: 0.24443721 | E15: 1 | F15: 0.7539094 | G15: 0.81521133
... A35: 上市合计 | B35: 0.208 | C35: 0.0262 | D35: 0.27412178 | E35: 0.9987 | F35: 0.70681221 | G35: 0.80563865
A36: 注：1.“高4无5”站点比例：尚未实现5G覆盖区域5G登网用户日均产生的4G流量超25GB的4G站点占全网4G站点比例
A37: 2.家宽单用户中断时长=中断总时长/活跃用户数
A38: 3.家宽装机及时率：统计周期内及时完成的装机工单量占统计周期内完成的装机工单总量的比例
A39: 4.PON口利用率=已占用PON口数量/PON口总量*100%
A40: 5.10GPON口利用率=已占用10GPON口数量/10GPON口总量*100%
A41: ='分省业务-网络运行 '!A39+1 -> 48

Sheet 重点地市财务数据
A1: 重点地市财务数据（33/36)
B2: =主要经营情况表!A2 -> 45323 | K2: 单位：万元
A3: 单位 | B3: 营运收入 | D3: 通信服务收入 | H3: 归属于母公司的所有者净利润 | J3: 净利润率
B4: 本年累计 | C4: 比上年 同期± | D4: 本年累计 | E4: 比上年 同期± | F4: 与本省平均 增幅差 | G4: 占本省 收入比 | H4: 本年累计 | I4: 比上年 同期± | J4: 本年累计 | K4: 比上年 同期±
A5: 广州* | B5: 408217.43 | C5: 0.042 | D5: 401402.18 | E5: 0.0337 | F5: 0.33652393 | G5: 0.18800503 | H5: 86626.992 | I5: -0.18380146 | J5: 0.2122 | K5: -5.8708
A6: 深圳* | B6: 382873.74 | C6: 0.0386 | D6: 378048.79 | E6: 0.0372 | F6: 0.68652393 | G6: 0.17706698 | H6: 74654.856 | I6: -0.29713053 | J6: 0.195 | K6: -9.3148
A7: 杭州* | B7: 280840.74 | C7: -0.0084 | D7: 272474.49 | E7: 0.0186 | F7: -1.7730815 | G7: 0.19898905 | H7: 69058.393 | I7: -0.12303138 | J7: 0.2459 | K7: -3.2139
A8: 苏州* | B8: 262206.26 | C8: 0.0156 | D8: 253476.96 | E8: 0.0524 | F8: 1.6926425 | G8: 0.18131622 | H8: 66822.213 | I8: -0.15855206 | J8: 0.2548 | K8: -5.2748
A9: 东莞* | B9: 245108.84 | C9: 0.0516 | D9: 242939.14 | E9: 0.0499 | F9: 1.9565239 | G9: 0.11378558 | H9: 65627.04 | I9: -0.024849581 | J9: 0.2677 | K9: -2.1004
A10: 成都* | B10: 214324.15 | C10: 0.0341 | D10: 211481.27 | E10: 0.0253 | F10: 0.36522046 | G10: 0.28933958 | H10: 77465.028 | I10: 0.12494103 | J10: 0.3614 | K10: 2.9195
A11: 宁波* | B11: 201857.23 | C11: -0.0519 | D11: 195592.88 | E11: -0.0467 | F11: -8.3030815 | G11: 0.14284215 | H11: 53029.084 | I11: -0.21205036 | J11: 0.2627 | K11: -5.34
A12: 金华* | B12: 189780.51 | C12: 0.1081 | D12: 183507.63 | E12: 0.103 | F12: 6.6669185 | G12: 0.13401625 | H12: 59761.374 | I12: 0.10352222 | J12: 0.3149 | K12: -0.1306
A13: 郑州* | B13: 179963.57 | C13: 0.0299 | D13: 177631.05 | E13: 0.0357 | F13: 3.0664942 | G13: 0.20362194 | H13: 42436.312 | I13: 0.028951406 | J13: 0.2358 | K13: -0.0221
A14: 温州* | B14: 190607.69 | C14: 0.0242 | D14: 176247.27 | E14: -0.0085 | F14: -4.4830815 | G14: 0.12871398 | H14: 37784.797 | I14: -0.25018593 | J14: 0.1982 | K14: -7.2544
A15: 南京* | B15: 184694.08 | C15: 0.0623 | D15: 175234.83 | E15: 0.0451 | F15: 0.96264255 | G15: 0.12534835 | H15: 39542.071 | I15: -0.021346762 | J15: 0.2141 | K15: -1.8309
A16: 无锡* | B16: 181819.13 | C16: 0.0534 | D16: 169363.37 | E16: 0.0404 | F16: 0.49264255 | G16: 0.1211484 | H16: 52211.222 | I16: -0.064006406 | J16: 0.2872 | K16: -3.6025
... A50: 拉萨 | B50: 20541.291 | C50: 0.0173 | D50: 20090.797 | E50: 0.0078 | F50: -4.0506332 | G50: 0.38400956 | H50: 4006.3461 | I50: -0.52119267 | J50: 0.195 | K50: -21.9346
A51: 注：1.重点地市是指各省省会、国家计划单列市及2023年累计通服收入在50亿以上的地市公司
A52: 2.地市顺序按照通信服务收入进行排序，标“*”为2023年印发的《规模较大地市分公司正职管理若干规定》中认定的大地市公司，每年将动态调整，下同
A53: ='分省业务-网络运行 (续)'!A41+1 -> 49

Sheet 重点地市四轮数据 
A1: 重点地市CHBN收入表（34/36)
B2: =主要经营情况表!A2 -> 45323 | L2: 单位：万元
A3: 单位 | B3: 个人市场收入(C) | E3: 家庭市场收入(H) | H3: 政企市场收入(B) | K3: 新兴市场收入(N)
B4: 本年累计 | C4: 比上年同期± | D4: 占通信服务收入比重 | E4: 本年累计 | F4: 比上年同期± | G4: 占通信服务收入比重 | H4: 本年累计 | I4: 比上年同期± | J4: 占通信服务收入比重 | K4: 本年累计 | L4: 比上年同期± | M4: 占通信服务收入比重
A5: 广州* | B5: 214740.64 | C5: -0.0107 | D5: 0.535 | E5: 31122.148 | F5: 0.0847 | G5: 0.0775 | H5: 147092.76 | I5: 0.0618 | J5: 0.3664 | K5: 8446.6366 | L5: 1.1016 | M5: 0.021
A6: 深圳* | B6: 206819.64 | C6: -0.0294 | D6: 0.5471 | E6: 26163.761 | F6: -0.0737 | G6: 0.0692 | H6: 136038.94 | I6: 0.1588 | J6: 0.3598 | K6: 9026.4588 | L6: 0.5691 | M6: 0.0239
A7: 杭州* | B7: 138355.83 | C7: -0.0799 | D7: 0.5078 | E7: 22743.083 | F7: 0.0008 | G7: 0.0835 | H7: 105080.22 | I7: 0.1815 | J7: 0.3857 | K7: 6295.3622 | L7: 0.1539 | M7: 0.0231
A8: 苏州* | B8: 139885.26 | C8: -0.0159 | D8: 0.5519 | E8: 26805.065 | F8: -0.0169 | G8: 0.1057 | H8: 82895.812 | I8: 0.2169 | J8: 0.327 | K8: 3890.8251 | L8: 0.1689 | M8: 0.0153
A9: 东莞* | B9: 134967.23 | C9: -0.0029 | D9: 0.5556 | E9: 23849.116 | F9: 0.0239 | G9: 0.0982 | H9: 79115.016 | I9: 0.1604 | J9: 0.3257 | K9: 5007.7731 | L9: 0.0979 | M9: 0.0206
A10: 成都* | B10: 114340.66 | C10: 0.011 | D10: 0.5407 | E10: 36220.732 | F10: 0.1499 | G10: 0.1713 | H10: 55744.084 | I10: -0.0357 | J10: 0.2636 | K10: 5175.7937 | L10: 0.3435 | M10: 0.0245
A11: 宁波* | B11: 115029.38 | C11: -0.1285 | D11: 0.5881 | E11: 22907.725 | F11: -0.0057 | G11: 0.1171 | H11: 51672.781 | I11: 0.1432 | J11: 0.2642 | K11: 5982.9945 | L11: 0.2099 | M11: 0.0306
A12: 金华* | B12: 122856.9 | C12: 0.1018 | D12: 0.6695 | E12: 19992.472 | F12: 0.0313 | G12: 0.1089 | H12: 34228.535 | I12: 0.0961 | J12: 0.1865 | K12: 6429.7235 | L12: 0.5079 | M12: 0.035
A13: 郑州* | B13: 85509.222 | C13: -0.1027 | D13: 0.4814 | E13: 16594.174 | F13: 0.1073 | G13: 0.0934 | H13: 69080.792 | I13: 0.2181 | J13: 0.3889 | K13: 6446.8611 | L13: 0.4283 | M13: 0.0363
A14: 温州* | B14: 107785.32 | C14: -0.0644 | D14: 0.6116 | E14: 24357.195 | F14: 0.0491 | G14: 0.1382 | H14: 38679.218 | I14: 0.0903 | J14: 0.2195 | K14: 5425.54 | L14: 0.405 | M14: 0.0308
A15: 南京* | B15: 88320.763 | C15: -0.0214 | D15: 0.504 | E15: 17827.655 | F15: 0.0092 | G15: 0.1017 | H15: 66866.959 | I15: 0.1618 | J15: 0.3816 | K15: 2219.4574 | L15: 0.0105 | M15: 0.0127
A16: 无锡* | B16: 88600.024 | C16: -0.0042 | D16: 0.5231 | E16: 18313.064 | F16: 0.0138 | G16: 0.1081 | H16: 59979.088 | I16: 0.1214 | J16: 0.3541 | K16: 2471.1943 | L16: 0.0925 | M16: 0.0146
... A50: 拉萨 | B50: 9635.1582 | C50: -0.0176 | D50: 0.4796 | E50: 1824.5852 | F50: 0.2207 | G50: 0.0908 | H50: 8218.2276 | I50: 0.0073 | J50: 0.4091 | K50: 412.8258 | L50: -0.1302 | M50: 0.0205
A52: =重点地市财务数据!A53+1 -> 50

Sheet 重点地市业务数据 
A1: 重点地市业务数据表（35/36)
A2: =重点地市财务数据!B2 -> 45323
A3: 单位 | B3: 移动电话客户数（万户） | E3: 5G套餐客户数（万户） | H3: 5G网络客户数（万户） | K3: 手机上网流量 （亿MB)
B4: 到达数 | C4: 比上年 同期± | D4: 本年累计净增 | E4: 到达数 | F4: 比上年 同期± | G4: 渗透率 | H4: 到达数 | I4: 比上年 同期± | J4: 渗透率 | K4: 本年累计 | L4: 比上年 同期±
A5: 广州* | B5: 1727.8093 | C5: 0.0242 | D5: 1.6853 | E5: 1557.6519 | F5: 0.2015 | G5: 0.9015 | H5: 928.9346 | I5: 0.2689 | J5: 0.5376 | K5: 5714.2581 | L5: 0.0906
A6: 深圳* | B6: 1679.6978 | C6: 0.0382 | D6: 4.7533 | E6: 1439.624 | F6: 0.107 | G6: 0.8571 | H6: 901.0688 | I6: 0.2825 | J6: 0.5364 | K6: 5392.0125 | L6: 0.0661
A7: 杭州* | B7: 1142.7408 | C7: 0.005 | D7: -4.6439 | E7: 991.5923 | F7: 0.0923 | G7: 0.8677 | H7: 590.437 | I7: 0.2454 | J7: 0.5167 | K7: 3290.0795 | L7: -0.094
A8: 苏州* | B8: 1034.4848 | C8: 0.0316 | D8: 6.801 | E8: 862.4229 | F8: 0.2271 | G8: 0.8337 | H8: 507.329 | I8: 0.3156 | J8: 0.4904 | K8: 3418.8877 | L8: 0.0188
A9: 东莞* | B9: 1087.776 | C9: 0.0164 | D9: -9.6522 | E9: 932.3544 | F9: 0.1097 | G9: 0.8571 | H9: 623.225 | I9: 0.2772 | J9: 0.5729 | K9: 4439.4944 | L9: 0.0721
A10: 成都* | B10: 1324.4953 | C10: 0.0042 | D10: -1.3791 | E10: 1025.7447 | F10: 0.2022 | G10: 0.7744 | H10: 661.7987 | I10: 0.3713 | J10: 0.4997 | K10: 3954.9328 | L10: 0.1625
A11: 宁波* | B11: 920.0814 | C11: 0.0031 | D11: -5.0929 | E11: 797.3693 | F11: 0.2449 | G11: 0.8666 | H11: 465.7238 | I11: 0.2581 | J11: 0.5062 | K11: 2734.4457 | L11: -0.1181
A12: 金华* | B12: 731.7095 | C12: 0.0144 | D12: -2.8569 | E12: 627.3829 | F12: 0.2712 | G12: 0.8574 | H12: 389.0455 | I12: 0.2546 | J12: 0.5317 | K12: 2367.657 | L12: -0.0739
A13: 郑州* | B13: 990.5234 | C13: 0.0154 | D13: -4.1829 | E13: 805.0948 | F13: 0.2255 | G13: 0.8128 | H13: 526.5222 | I13: 0.3559 | J13: 0.5316 | K13: 3373.6791 | L13: 0.2219
A14: 温州* | B14: 1002.1779 | C14: 0.0192 | D14: -2.272 | E14: 876.1066 | F14: 0.291 | G14: 0.8742 | H14: 506.8676 | I14: 0.2623 | J14: 0.5058 | K14: 2652.1927 | L14: -0.167
A15: 南京* | B15: 773.5364 | C15: 0.0146 | D15: -10.482 | E15: 637.1101 | F15: 0.2241 | G15: 0.8236 | H15: 374.3278 | I15: 0.319 | J15: 0.4839 | K15: 2065.1996 | L15: -0.0217
A16: 无锡* | B16: 627.5337 | C16: 0.0158 | D16: 0.9369 | E16: 521.2175 | F16: 0.2973 | G16: 0.8306 | H16: 310.958 | I16: 0.2781 | J16: 0.4955 | K16: 1787.5142 | L16: -0.087
... A50: 拉萨 | B50: 59.263 | C50: 0.0981 | D50: 1.0157 | E50: 47.6278 | F50: 0.2183 | G50: 0.8037 | H50: 34.0774 | I50: 0.6753 | J50: 0.575 | K50: 407.8235 | L50: 0.4687
A52: ='重点地市四轮数据 '!A52+1 -> 51

Sheet 重点地市业务数据  (续)
A1: 重点地市业务数据表（续）（36/36)
A2: =重点地市财务数据!B2 -> 45323
A3: 单位 | B3: 家庭宽带客户数（万户） | E3: 移动高清客户数（万户） | H3: 通信服务收入份额（%) | J3: 移动电话客户到达份额（%)
B4: 到达数 | C4: 比上年 同期± | D4: 本年累计净增 | E4: 到达数 | F4: 比上年 同期± | G4: 渗透率 | H4: 本年累计 | I4: 比上年 同期± | J4: 本年累计 | K4: 比上年 同期±
A5: 广州* | B5: 285.1162 | C5: 0.041 | D5: 3.0655 | E5: 197.8501 | F5: 0.0156 | G5: 0.6939 | H5: 0.5041 | I5: -0.03 | J5: 0.5199 | K5: -0.32
A6: 深圳* | B6: 233.0265 | C6: -0.031 | D6: -0.4971 | E6: 187.5633 | F6: -0.0963 | G6: 0.8049 | H6: 0.4944 | I6: 1.49 | J6: 0.5649 | K6: -0.84
A7: 杭州* | B7: 280.7423 | C7: 0.0614 | D7: 1.6701 | E7: 209.521 | F7: 0.1377 | G7: 0.7463 | H7: 0.539 | I7: -1.41 | J7: 0.6058 | K7: -0.69
A8: 苏州* | B8: 271.4202 | C8: -0.015 | D8: -1.0606 | E8: 193.585 | F8: -0.0003 | G8: 0.7132 | H8: 0.5103 | I8: 0.08 | J8: 0.5435 | K8: 0.42
A9: 东莞* | B9: 206.3944 | C9: 0.0092 | D9: -0.9562 | E9: 150.6951 | F9: -0.166 | G9: 0.7301 | H9: 0.6175 | I9: -0.78 | J9: 0.6517 | K9: -0.29
A10: 成都* | B10: 406.0988 | C10: 0.0254 | D10: 0.1956 | E10: 404.0883 | F10: 0.0481 | G10: 0.995 | H10: 0.532 | I10: 2.37 | J10: 0.5553 | K10: 0.4
A11: 宁波* | B11: 267.0411 | C11: 0.0557 | D11: 1.1246 | E11: 215.1404 | F11: 0.0691 | G11: 0.8056 | H11: 0.6325 | I11: -0.71 | J11: 0.6552 | K11: -0.75
A12: 金华* | B12: 198.4818 | C12: 0.0569 | D12: 1.1797 | E12: 160.5739 | F12: 0.1207 | G12: 0.809 | H12: 0.7335 | I12: 0.25 | J12: 0.732 | K12: -0.59
A13: 郑州* | B13: 292.7251 | C13: 0.0825 | D13: -0.5677 | E13: 155.7725 | F13: 0.024 | G13: 0.5321 | H13: 0.5058 | I13: -1.65 | J13: 0.5212 | K13: -6.98
A14: 温州* | B14: 277.8386 | C14: 0.0496 | D14: 0.7213 | E14: 211.4853 | F14: 0.1016 | G14: 0.7612 | H14: 0.6501 | I14: -3.16 | J14: 0.7201 | K14: -0.88
A15: 南京* | B15: 246.5583 | C15: 0.0556 | D15: -1.0341 | E15: 158.1739 | F15: 0.0944 | G15: 0.6415 | H15: 0.5032 | I15: 0.29 | J15: 0.549 | K15: -0.65
A16: 无锡* | B16: 185.6196 | C16: 0.0127 | D16: 0.6363 | E16: 135.2028 | F16: 0.0319 | G16: 0.7284 | H16: 0.5736 | I16: -0.89 | J16: 0.6026 | K16: -0.2
... A50: 拉萨 | B50: 17.0446 | C50: 0.0456 | D50: -0.6587 | E50: 10.5725 | F50: 0.1881 | G50: 0.6203 | H50: 0.4642 | I50: -4.74 | J50: 0.5443 | K50: 1.63
A51: 注：1.主营业务收入份额、移动电话客户到达份额为上月值，为各省公司上报数据
A53: ='重点地市业务数据 '!A52+1 -> 52

Sheet 香港公司主要情况表
A1: 香港公司主要情况表
A2: =主要经营情况表!A2 -> 45323
A3: 指标 | B3: 单位 | C3: 本月实际 | D3: 比上月± | E3: 比上年同期± | F3: 本年累计 | G3: 比上年同期±
A4: 一、财务情况
A5: 1.营运收入 | B5: 万元 | C5: 56588.852 | D5: -0.096430158 | E5: -0.00088728974 | F5: 119216.94 | G5: -0.02612853
A6: 其中：通信服务收入 | B6: 万元 | C6: 44950.396 | D6: -0.053489939 | E6: 0.063140228 | F6: 92441.065 | G6: -0.014451017
A7: 2.营运支出 | B7: 万元 | C7: 51521.655 | D7: -0.096464079 | E7: 0.034622355 | F7: 108543.91 | G7: -0.0054234706
A8: 其中：成本费用总额 | B8: 万元 | C8: 40982.553 | D8: -0.045592353 | E8: 0.13885502 | F8: 83922.856 | G8: 0.019709972
A9: 3.利润总额 | B9: 万元 | C9: 6993.8618 | D9: -0.098794004 | E9: -0.11606149 | F9: 14754.42 | G9: -0.040597254
A10: 4.净利润 | B10: 万元 | C10: 5853.5812 | D10: 0.0032793238 | E10: 0.024446286 | F10: 11688.029 | G10: 0.026849545
A11: 5.EBITDA | B11: 万元 | C11: 17807.818 | D11: -0.026032992 | E11: -0.013327602 | F11: 36091.618 | G11: 0.021105612
A12: EBITDA margin | B12: % | C12: 0.31468774 | D12: 2.2745252 | E12: -0.39676937 | F12: 0.302739 | G12: 1.4004053
A13: 6.资产总额 | B13: 万元 | C13: - | D13: - | E13: - | F13: 1550505.1 | G13: 0.10252759
A14: 7.负债总额 | B14: 万元 | C14: - | D14: - | E14: - | F14: 478627.93 | G14: 0.08686359
A15: 资产负债率 | B15: % | C15: - | D15: - | E15: - | F15: 0.30869161 | G15: -0.44488979
A16: 二、业务发展
A17: 1.移动电话客户数 | B17: 万户 | C17: - | D17: - | E17: - | F17: 542.9487 | G17: 0.030325359
A18: 其中：5G套餐客户数 | B18: 万户 | C18: - | D18: - | E18: - | F18: 286.6143 | G18: 0.28852537
A19: 5G网络客户数 | B19: 万户 | C19: - | D19: - | E19: - | F19: 234.2523 | G19: 0.36892463
A20: 4G网络客户数(剔除使用5G网络) | B20: 万户 | C20: - | D20: - | E20: - | F20: 187.1394 | G20: -0.14853076
A21: 净增移动电话客户数 | B21: 万户 | C21: -0.8597 | D21: - | E21: - | F21: -4.2393 | G21: -1.9544319
A22: 2.计费总时长 | B22: 亿分钟 | C22: 4.8841774 | D22: -0.14430567 | E22: -0.1194898 | F22: 10.59203 | G22: -0.083188953
A23: 3.移动数据流量 | B23: 亿MB | C23: 597.35685 | D23: -0.072511923 | E23: 0.34442847 | F23: 1241.4156 | G23: 0.37464451
A24: 4.移动数据流量客户DOU | B24: GB/户/月 | C24: 16.603882 | D24: 0.00022052133 | E24: 0.22207709 | F24: 16.604419 | G24: 0.23425048
A25: 5.移动业务ARPU | B25: 元/户/月 | C25: 81.155039 | D25: 0.031469534 | E25: -0.0077087973 | F25: 79.847754 | G25: 0.042068752
A26: 6.家庭宽带客户数 | B26: 万户 | C26: - | D26: - | E26: - | F26: 13.7081 | G26: 0.13972031
A27: 三、能力与投资
A28: 1.基站数 | B28: 个 | C28: 3 | D28: -0.84210526 | E28: -0.66666667 | F28: 8537 | G28: 0.00035153504
A29: 其中：5G基站数 | B29: 个 | C29: 2 | D29: -0.81818182 | E29: -0.66666667 | F29: 2894 | G29: 0.080657207
A30: 4G基站数 | B30: 个 | C30: 2 | D30: -0.75 | E30: -0.33333333 | F30: 3232 | G30: 0.032587859
A31: 2.资本开支 | B31: 万元 | C31: 2263.416 | D31: -0.10734502 | E31: -0.43212707 | F31: 4799.016 | G31: -0.28831231
A32: 注：1.按照香港公司本位币，本年累计营运收入为12.88亿港币，同比增幅为-7.58%；通信服务收入为9.98亿港币，
A33: 同比增幅为-6.5%；净利润为1.3亿港币，同比增幅为-2.6%。
A34: 2.移动业务ARPU=移动业务收入/移动电话客户数
A35: ='重点地市业务数据 (续)'!A53+1 -> 53

Sheet 辛姆巴科主要情况表
A1: 辛姆巴科公司主要情况表
A2: =主要经营情况表!A2 -> 45323
A3: 指标 | B3: 单位 | C3: 本月 | D3: 比上月± | E3: 比上年同期± | F3: 本年累计 | G3: 比上年同期±
A4: 一、财务情况
A5: 1.营运收入 | B5: 万元 | C5: 31905.616 | D5: -0.041496969 | E5: 0.0028660702 | F5: 65192.539 | G5: -0.0071763718
A6: 其中：通信服务收入 | B6: 万元 | C6: 31588.56 | D6: -0.041380539 | E6: 0.00083409178 | F6: 64540.697 | G6: -0.0081169262
A7: 2.营运支出 | B7: 万元 | C7: 27822.632 | D7: -0.034333962 | E7: -0.057867793 | F7: 56634.489 | G7: -0.024825258
A8: 其中：成本费用总额 | B8: 万元 | C8: 28818.62 | D8: -0.036898931 | E8: -0.07876502 | F8: 58741.356 | G8: -0.048655316
A9: 3.利润总额 | B9: 万元 | C9: 3174.7067 | D9: -0.11875378 | E9: -0.179465 | F9: 6777.2262 | G9: -
A10: 4.净利润 | B10: 万元 | C10: 1359.1089 | D10: -0.014262315 | E10: -0.47063515 | F10: 2737.8823 | G10: -
A11: 5.EBITDA | B11: 万元 | C11: 13307.326 | D11: -0.052866875 | E11: 0.047303914 | F11: 27357.438 | G11: -0.064957558
A12: EBITDA margin | B12: % | C12: 0.41708413 | D12: -0.50069068 | E12: 1.7697174 | F12: 0.41964063 | G12: -2.59318
A13: 6.资产总额 | B13: 万元 | C13: - | D13: - | E13: - | F13: 739288.35 | G13: -0.13917592
A14: 7.负债总额 | B14: 万元 | C14: - | D14: - | E14: - | F14: 295717.63 | G14: -0.12185137
A15: 资产负债率 | B15: % | C15: - | D15: - | E15: - | F15: 0.4000031 | G15: 0.78914567
A16: 8.自由现金流 | B16: 万元 | C16: 12403.302 | D16: -0.094123005 | E16: 0.089693323 | F16: 26095.341 | G16: 1.4517902
A17: 二、业务发展
A18: 1.移动电话客户数 | B18: 万户 | C18: - | D18: - | E18: - | F18: 4780.6622 | G18: 0.036998135
A19: 其中：4G客户数 | B19: 万户 | C19: - | D19: - | E19: - | F19: 3524.93 | G19: 0.098225391
A20: 净增移动电话客户数 | B20: 万户 | C20: 39.6583 | D20: 0.64098331 | E20: 0.08320496 | F20: 63.8257 | G20: -0.048931969
A21: 2.计费总时长 | B21: 亿分钟 | C21: 151.81411 | D21: -0.040234623 | E21: 0.09617038 | F21: 309.99247 | G21: 0.09864427
A22: 3.移动数据流量 | B22: 亿MB | C22: 3717.9131 | D22: -0.053892751 | E22: 0.21871108 | F22: 7647.6082 | G22: 0.19731151
A23: 4.移动数据流量客户DOU | B23: GB/户/月 | C23: 9.8261879 | D23: -0.0031846242 | E23: 0.11203755 | F23: 9.8399184 | G23: 0.11524335
A24: 5.移动业务ARPU | B24: 元/户/月 | C24: 6.9782852 | D24: 0.017862163 | E24: -0.065434975 | F24: 6.9125641 | G24: -0.05714008
A25: 三、能力与投资
A26: 1.基站数 | B26: 个 | C26: -135 | D26: -6.1923077 | E26: -3.0769231 | F26: 43672 | G26: 0.0063832239
A27: 其中：4G基站数 | B27: 个 | C27: -10 | D27: -1.9090909 | E27: -1.4761905 | F27: 14655 | G27: 0.0095756407
A28: 2.资本开支 | B28: 万元 | C28: 250.89884 | D28: -0.16350324 | E28: -0.89490446 | F28: 550.83884 | G28: -0.95299356
A29: 注：1.按照辛姆巴科公司本位币，本年累计营运收入为260.6亿卢比，同比增幅为21.4%；通信服务收入为258.0亿
A30: 卢比，同比增幅为21.2%；净利润为10.9亿卢比。
A31: 2.移动业务ARPU=通信服务收入/移动电话客户数
A32: =香港公司主要情况表!A35+1 -> 54

Sheet 国际公司
A1: 国际公司主要情况表
A2: =主要经营情况表!A2 -> 45323
A3: 指标 | B3: 单位 | C3: 合计 | E3: 其中：来自集团外部
C4: 本年累计/到达 | D4: 比上年同期± | E4: 本年累计/到达 | F4: 比上年同期±
A5: 一.财务情况
A6: 营运收入（人民币） | B6: 万人民币 | C6: 407541.33 | D6: 0.20604618 | E6: 270067.98 | F6: 0.21338872
A7: 营运收入（港币） | B7: 万港币 | C7: 443401.37 | D7: 0.1625805 | E7: 293831.58 | F7: 0.16965841
A8: 其中：话音业务收入 | B8: 万港币 | C8: 107310.69 | D8: 0.13281146 | E8: 103052.5 | F8: 0.15305556
A9: 移动业务收入 | B9: 万港币 | C9: 87094.668 | D9: -0.02764209 | E9: 42234.093 | F9: -0.22543903
A10: 数据业务收入 | B10: 万港币 | C10: 245697.78 | D10: 0.25773953 | E10: 145241.34 | F10: 0.37582964
A11: 二.业务发展
A12: （一）话音业务
A13: 国际语音（IDD）业务量 | B13: 万分钟 | C13: 71538.46 | D13: 0.14313715 | E13: 56155.419 | F13: -
A14: （二）移动业务
A15: A2P SMS信息量 | B15: 万条 | C15: 51566 | D15: - | E15: - | F15: -
A16: （三）数据业务
A17: 1.国际专线业务已售带宽 | B17: G | C17: 65230 | D17: - | E17: 61725 | F17: -
A18: 2.互联网转接业务已售带宽 | B18: G | C18: 9076 | D18: - | E18: 8132 | F18: -
A19: 3.国际IPVPN业务已售带宽 | B19: G | C19: 9016 | D19: - | E19: 4019 | F19: -
A20: 4.IDC已售机架数 | B20: 个 | C20: 13708 | D20: - | E20: 13458 | F20: -
A21: 其中：自有 | B21: 个 | C21: 4374 | D21: - | E21: 4273 | F21: -
A22: 5.ICT集成项目签约合同数 | B22: 个 | C22: 320 | D22: - | E22: 315 | F22: -
A23: ICT集成项目签约合同额 | B23: 万元 | C23: 15863 | D23: - | E23: 15643 | F23: -
A24: 三.能力与投资
A25: 1.海外POP点 | B25: 个 | C25: 235 | D25: 0.02173913 | E25: - | F25: -
A26: 其中：自建 | B26: 个 | C26: 136 | D26: 0.022556391 | E26: - | F26: -
A27: 租用 | B27: 个 | C27: 99 | D27: 0.020618557 | E27: - | F27: -
A28: 2.国际带宽 | B28: G | C28: 146776.85 | D28: 0.19709256 | E28: - | F28: -
A29: 3.正式商用5G的国家或地区 | B29: 个 | C29: 85 | D29: 0.26865672 | E29: - | F29: -
A30: 5G漫游出访开通率 | B30: % | C30: 0.89411765 | D30: -0.1404741 | E30: - | F30: -
A31: 4.正式商用VoLTE的国家或地区 | B31: 个 | C31: 81 | D31: - | E31: - | F31: -
A32: VoLTE国漫开通率 | B32: % | C32: 0.80246914 | D32: - | E32: - | F32: -
A33: 5.跨境专线业务开通及时率 | B33: % | C33: 0.66666667 | D33: - | E33: - | F33: -
A34: 注：1.本表财务情况和业务发展中的“合计”指国际公司从通过省公司签约的客户及自己直接签约的客户获取的全部收入与业务量。
A35: 本表财务情况和业务发展中的“其中：来自集团外部”指国际公司从自己直接签约的客户获取的收入与业务量。
A36: 2.话音业务收入指国际语音（IDD）业务和国际400业务的批发端收入
A37: 3.移动业务收入指国际漫游、WiFi漫游、国际短彩信、A2P SMS、国际一卡多号等业务收入
A38: 4.数据业务收入指互联网转接、国际专线、IPVPN、ICT、IDC、CMNET、SDWAN等业务收入
A39: 5.自建海外POP点包含场地及设备全部为自建的POP点以及场地为租用但设备为自建的POP点，包含VPOP。
A40: 租用POP点指场地和设备均为租用的POP点
A41: 6.5G漫游出访开通率=开通5G漫游的国家或地区/正式商用5G的国家或地区
A42: 7.VoLTE国漫开通率=开通VoLTE漫游的国家或地区/正式商用VoLTE的国家或地区
A43: 8.跨境专线业务开通及时率=本年按时开通的跨境专线（境外段）/本年客户要求开通的跨境专线（境外段）
A44: =辛姆巴科主要情况表!A32+1 -> 55

Sheet 财务公司、终端公司
A1: 财务公司主要情况表
A2: =主要经营情况表!A2 -> 45323
A3: 指标 | B3: 单位 | C3: 本年累计/到达 | D3: 比上年同期±
A4: 一、资金运作
A5: 全集团资金规模 | B5: 亿元 | C5: 8060.2536 | D5: 0.037588844
A6: 其中：集中运作资金规模 | B6: 亿元 | C6: 6833.818 | D6: -0.026517839
A7: 其中：金融投资规模 | B7: 亿元 | C7: 4672.2507 | D7: 0.11147941
A8: 全集团资金收益 | B8: 亿元 | C8: 16.996121 | D8: -0.23296572
A9: 其中：集中运作资金收益 | B9: 亿元 | C9: 16.735545 | D9: -0.27575954
A10: 其中：金融投资收益 | B10: 亿元 | C10: 11.943117 | D10: -0.13201995
A11: 全集团资金收益率 | B11: % | C11: 0.0267 | D11: -0.73
A12: 其中：集中运作资金收益率 | B12: % | C12: 0.0313 | D12: -0.77
A13: 其中：金融投资收益率 | B13: % | C13: 0.0346 | D13: -0.79
A14: 二、重点工作履行
A15: 资金集中度 | B15: % | C15: 0.8112 | D15: -6.14 | E15: T-2
A16: 集中备付率 | B16: % | C16: 0.1398 | D16: -8.6408847
A17: 产业链金融规模 | B17: 亿元 | C17: 86.721156 | D17: 1.6362888
A18: 贷款余额 | B18: 亿元 | C18: 327.33875 | D18: -0.196
A19: 结算规模 | B19: 亿元 | C19: 25643.495 | D19: 1.1658271
A20: 注：1.“资金运作”指标均为上月数
A21: 2.全集团资金规模指全集团用于金融增值运作和日常运营开支的资金资产期末本金金额
A22: 3.集中运作资金规模指财务公司实际管理资金的期末本金金额
A23: 4.金融投资规模指财务公司集中运作的理财、基金、债券、优先股、资产支持证券、投资专户期末本金金额
A24: 5.资金集中度指集中资金规模占全集团资金规模的比例，
A25: 剔除未到期定期存款、专户资金等无法集中资金因素，为上月数
A26: 6.集中备付率指集中运作资金中的活期存款占集中资金规模的比例，为上月数
A28: 终端公司主要情况表
A29: =主要经营情况表!A2 -> 45323
A30: 指标 | B30: 单位 | C30: 本年累计/到达 | D30: 比上年同期±
A31: 一、财务情况
A32: 1.营运收入 | B32: 万元 | C32: 2640152.9 | D32: 0.086970911
A33: 其中：终端销售收入 | B33: 万元 | C33: 2626988 | D33: 0.087321173
A34: 2.毛利 | B34: 万元 | C34: 82424.202 | D34: -0.040288357
A35: 3.存货周转率 | B35: 次 | C35: 22.4173 | D35: 0.042388762
A36: 二、业务发展
A37: 1.终端公司终端销量 | B37: 万台 | C37: 3995.6533 | D37: 0.30859125
A38: （1）手机销量 | B38: 万台 | C38: 1267.1787 | D38: 0.088715292
A39: 其中：零售销量 | B39: 万台 | C39: 160.3069 | D39: 0.67599489
A40: 分销销量 | B40: 万台 | C40: 1106.8718 | D40: 0.036132641
A41: （2）智能硬件销量 | B41: 万台 | C41: 2728.4746 | D41: 0.44403504
A42: 2.泛全联盟泛终端销量 | B42: 万台 | C42: 826.4 | D42: 0.029781931
A43: 其中：5G手机销量 | B43: 万台 | C43: 352.4 | D43: 0.15314136
A44: 注：1.存货周转率=累计终端销售成本/平均存货
A45: 2.泛全联盟泛终端销量指终端公司通过泛全联盟销售的泛终端销量，泛终端包括 5G 手机和泛智能终端，为上月数
A46: 3.泛全联盟5G手机销量指由终端公司供货并且通过合约或者线上裸机形式销售的 5G 手机规模,其中终端合约包括
A47: 顺差让利、信用购直销(含 5G 金币、免息分期等)模式，为上月数
A48: =国际公司!A44+1 -> 56

Sheet 中移铁通
A1: 铁通公司主要情况表
A2: =主要经营情况表!A2 -> 45323
A3: 指标 | B3: 单位 | C3: 本年累计 | D3: 比上年同期±
A4: 一.财务情况
A5: 铁通拓展业务收入 | B5: 万元 | C5: 1269935.8 | D5: 0.039402584
A6: 其中：网络管理技术服务收入 | B6: 万元 | C6: 415251.38 | D6: -
A7: 工程建设与服务收入 | B7: 万元 | C7: 326368.7 | D7: -
A8: 销售服务收入 | B8: 万元 | C8: 256802.7 | D8: -
A9: 信息服务收入 | B9: 万元 | C9: 261721.01 | D9: -
A10: 其中：ICT业务收入 | B10: 万元 | C10: 246595.18 | D10: -
A11: 二.业务发展
A12: （一）装维业务
A13: 1.家庭宽带装机数 | B13: 万户 | C13: 869.0594 | D13: -0.048298663
A14: （二）工程建设业务
A15: 1.工程建设合同个数 | B15: 个 | C15: 4270 | D15: -
A16: 2.工程建设合同金额 | B16: 万元 | C16: 251106 | D16: 0.9398169
A17: （三）销售业务
A18: 1.重点家庭业务拓展
A19: (1)家庭宽带业务铁通营销占比 | B19: % | C19: 0.44427089 | D19: 8.393023
A20: (2)移动高清业务铁通营销占比 | B20: % | C20: 0.43156012 | D20: 7.0494659
A21: (3)智能组网业务铁通营销占比 | B21: % | C21: 0.47260896 | D21: 0
A22: (4)家庭安防业务铁通营销占比 | B22: % | C22: 0.32925037 | D22: 0
A23: (5)健康养老业务铁通营销占比 | B23: % | C23: 0.27381943 | D23: 0
A24: 2.铁通泛终端直销量 | B24: 万台 | C24: 300.4301 | D24: 0.1838994
A25: （四）信息服务
A26: 1.信息服务合同个数 | B26: 个 | C26: 1551 | D26: -
A27: 其中：ICT合同个数 | B27: 个 | C27: 1511 | D27: -
A28: 2.信息服务合同金额 | B28: 万元 | C28: 227368.98 | D28: -
A29: 其中：ICT合同金额 | B29: 万元 | C29: 222746.17 | D29: -
A30: 注：1.铁通拓展业务收入=香港口径报表通服收入-政策性收入(城域网、转网补偿)，
A31: 主要包括维护业务、工程业务、销售产品、ICT信息服务业务等收入。
A32: 2.铁通维护家庭宽带占比=铁通公司维护的家庭宽带客户数/中国移动30省（除西藏）家庭宽带客户数*100%
A33: 3.重点家庭业务拓展中铁通营销占比：指铁通公司新发展的客户数/中国移动30省（除西藏）新增的客户数，
A34: 数据为上月值
A35: =财务公司、终端公司!A48+1 -> 57

Sheet 集成、在线营销服务中心、物联网公司
A1: 集成公司主要情况表
A2: =主要经营情况表!A2 -> 45323
A3: 指标 | B3: 单位 | C3: 本年累计/到达 | D3: 比上年同期±
A4: 一、财务状况
A5: 集成项目收入 | B5: 万元 | C5: 84523 | D5: 0.0080710301
A6: 二、业务发展
A7: 1.集成项目签约数量 | B7: 个 | C7: 488 | D7: 0.040511727
A8: 集成项目签约金额 | B8: 万元 | C8: 290219 | D8: -
A9: 2.智慧党建订购集团客户数 | B9: 家 | C9: 28254 | D9: 0.61886209
A10: 注：1.集成项目签约数量、 集成项目签约金额为本年累计数。
A12: 在线营销服务中心主要情况表
A13: =主要经营情况表!A2 -> 45323
A14: 指标 | B14: 单位 | C14: 本年累计/到达 | D14: 比上年同期±
A15: 一、线上销售
A16: 1.号卡全网线上销量占比 | B16: % | C16: 0.340443 | D16: 5.8560874
A17: 2.5G套包全网线上办理占比 | B17: % | C17: 0.71918753 | D17: 6.1561886
A18: 3.权益包全网线上办理占比 | B18: % | C18: 0.75258939 | D18: 4.7842352
A19: 4.5G手机全网线上销量 | B19: 万台 | C19: 112.41 | D19: 0.86109272
A20: 二、权益运营
A21: 1.权益融合客户数 | B21: 万户 | C21: 31666.01 | D21: 0.066896829
A22: 2.权益融合活跃客户数 | B22: 万户 | C22: 6353.07 | D22: 0.3640896
A23: 3.权益融合客户活跃度 | B23: % | C23: 0.20062742 | D23: 4.3710487
A24: 注：1.全网线上销售(办理）占比=全网线上销售（办理）量/全网销售（办理）量
A25: 2.全网线上渠道5G手机销量：指终端公司统一供货，由全网线上渠道销售的5G手机的数量，
A26: 包括合约销售和裸机直销等
A27: 3.权益融合活跃客户数为当月活跃客户数，
A28: 权益融合客户活跃度=权益融合活跃客户/权益融合客户数，为当月活跃度
A30: 物联网公司主要情况表
A31: =主要经营情况表!A2 -> 45323
A32: 指标 | B32: 单位 | C32: 本年累计 | D32: 比上年同期±
A33: 自主品牌智能硬件全网总销量 | B33: 万个 | C33: 2902.9955 | D33: -0.25608876
A34: 其中：芯片 | B34: 万个 | C34: 2543.0587 | D34: -0.28866836
A35: 模组 | B35: 万个 | C35: 301.0301 | D35: 0.59573224
A36: 终端 | B36: 万个 | C36: 58.9067 | D36: -0.57506929
A37: =中移铁通!A35+1 -> 58

Sheet 金科、信息技术中心
A1: 金科公司主要情况表
A2: =主要经营情况表!A2 -> 45323
A3: 指标 | B3: 单位 | C3: 本年累计/到达 | D3: 比上年同期±
A4: 一.财务情况
A5: 互联网金融收入 | B5: 万元 | C5: 6817.0794 | D5: -0.28205529
A6: 二.业务情况
A7: （一）和包
A8: 1.和包交易额 | B8: 万元 | C8: 16063833 | D8: 0.13383807
A9: （二）信用购
A10: 1.信用购终端销量 | B10: 万台 | C10: 329.0521 | D10: -0.18095797
A11: 2.信用购贷款额 | B11: 万元 | C11: 41766.773 | D11: -0.713936
A12: （三）和聚宝
A13: 和聚宝日均余额 | B13: 万元 | C13: 96321.133 | D13: -0.11038396
A14: （四）保险
A15: 1.本年新增保险客户数 | B15: 万户 | C15: 342.6404 | D15: -
A16: 其中：守机宝客户数 | B16: 万户 | C16: 116.4374 | D16: -
A17: 2.保险保费规模 | B17: 万元 | C17: 2879.82 | D17: -
A18: （五）积分商城
A19: 1.积分商城交易活跃客户数 | B19: 万户 | C19: 5743.2587 | D19: - | F19: 当月
A20: 2.积分商城交易额 | B20: 万元 | C20: 919425.85 | D20: 0.39251683
A21: 注：1.互联网金融收入取自管理会计报表，指境内和包支付等互联网金融产品带来的收入
A22: 2.信用购终端销量指金科公司统一平台发展的信用购（含5G金币、分期免息等）终端业务量
A23: 3.积分商城交易活跃客户数为当月活跃客户数
A25: 信息技术中心主要情况表
A26: =主要经营情况表!A2 -> 45323
A27: 指标 | B27: 单位 | C27: 本年累计/到达 | D27: 比上年同期±
A28: 一.财务情况
A29: 智慧中台对外收入 | B29: 万元 | C29: 107232.8 | D29: -
A30: 二、能力沉淀
A31: 1.智慧中台能力沉淀数量 | B31: 项 | C31: 1036 | D31: 0.16143498
A32: 其中：业务能力数量 | B32: 项 | C32: 518 | D32: -
A33: 数据能力数量 | B33: 项 | C33: 273 | D33: -
A34: 技术能力数量 | B34: 项 | C34: 245 | D34: -
A35: 2.智慧中台能力提供方数量 | B35: 家 | C35: 56 | D35: 0
A36: 其中：集团总部部门 | B36: 家 | C36: 6 | D36: 0.2
A37: 省公司 | B37: 家 | C37: 31 | D37: 0
A38: 专业公司及直属单位 | B38: 家 | C38: 19 | D38: -0.05
A39: 三、能力使用
A40: 1.智慧中台能力调用量 | B40: 亿次 | C40: 524.82 | D40: 0.79948568
A41: 2.智慧中台能力使用方数量 | B41: 家 | C41: 8802 | D41: 6.4846939
A42: 其中：内部使用方数量 | B42: 家 | C42: 66 | D42: 0
A43: 外部使用方数量 | B43: 家 | C43: 8736 | D43: 6.8702703
A44: 四、梧桐大数据平台能力
A45: 1.日均实时采集数据量 | B45: PB | C45: 5.3 | D45: -
A46: 2.日均调度任务数 | B46: 万个 | C46: 137.37 | D46: -
A47: 注：1.智慧中台能力沉淀数量指截止到统计期末，业务能力、数据能力和技术能力台上累计数量之和。为上月值
A48: 2.智慧中台能力提供方数量指截止到统计期末，提供智慧中台能力的单位数量。为上月值
A49: 3.智慧中台能力调用量指统计周期内，所有使用中台能力产生的有效调用次数之和。为年初至上月累计值
A50: 4.智慧中台能力使用方数量：指截止到统计周期末使用智慧中台能力的内外部单位数量之和。为上月值
A51: =集成、在线营销服务中心、物联网公司!A37+1 -> 59

Sheet 其他单位主要财务指标情况表
A1: 专业公司、事业部及直属单位主要财务指标表
B2: =主要经营情况表!A2 -> 45323 | G2: 单位：亿元
A3: 单位 | B3: 营运收入 | D3: 营运支出 | F3: 净利润
B4: 本年累计 | C4: 同比增幅 | D4: 本年累计 | E4: 同比增幅 | F4: 本年累计 | G4: 同比增幅
A5: 一、市场拓展
A6: 香港公司 | B6: 11.921694 | C6: -0.0261 | D6: 10.854391 | E6: -0.0054 | F6: 1.1688029 | G6: 0.0268
A7: 辛姆巴科 | B7: 6.5192539 | C7: -0.0072 | D7: 5.6634489 | E7: -0.0248 | F7: 0.27378823 | G7: 0
A8: 国际公司 | B8: 40.754133 | C8: 0.206 | D8: 38.386748 | E8: 0.2067 | F8: 1.9565939 | G8: -0.1148
A9: 咪咕公司 | B9: 16.676208 | C9: 0.2308 | D9: 19.271634 | E9: -0.1563 | F9: -3.2178571 | G9: -
A10: 互联网公司 | B10: 5.0870555 | C10: 0.12120952 | D10: 5.3342111 | E10: 0.42483991 | F10: -0.26329345 | G10: -1.3447274
A11: 金科公司 | B11: 5.9091675 | C11: 0.071699435 | D11: 6.1258144 | E11: 0.055663168 | F11: 0.0015188406 | G11: -1.0261424
A12: 终端公司 | B12: 264.01529 | C12: 0.087 | D12: 261.81568 | E12: 0.0925 | F12: 1.7065656 | G12: -0.3094
A13: 投资公司 | B13: 0.43468258 | C13: - | D13: 4.0800631 | E13: 28.469619 | F13: -3.9512909 | G13: -13.817819
A14: 财务公司 | B14: 2.3443723 | C14: 0.5953 | D14: 0.056117427 | E14: -0.855 | F14: 2.1963187 | G14: 0.3715
A15: 智慧家庭运营中心 | B15: 4.8537088 | C15: -0.3278 | D15: 5.4858758 | E15: -0.1875 | F15: -0.55933775 | G15: -2.1785
A16: 物联网公司 | B16: 4.7551362 | C16: 0.1238 | D16: 5.5126853 | E16: 0.0293 | F16: -0.68280893 | G16: 0
A17: 云能力中心 | B17: 15.602857 | C17: 0.1613 | D17: 18.005924 | E17: 0.2321 | F17: -2.4915163 | G17: 0
A18: 上海产业研究院 | B18: 0.32894734 | C18: 0.062932266 | D18: 1.2878001 | E18: 0.057025353 | F18: -0.94723787 | G18: -
A19: 成都产业研究院 | B19: 0.15211772 | C19: -0.48978367 | D19: 1.1053316 | E19: -0.10465023 | F19: -0.93519466 | G19: -
A20: 雄安产业研究院 （集成公司） | B20: 8.4522514 | C20: 0.0080652311 | D20: 9.1175972 | E20: -0.088855975 | F20: -0.63656128 | G20: -
A21: 信息技术中心（公司） | B21: 20.713058 | C21: 0.03359422 | D21: 9.4723881 | E21: -0.085300984 | F21: 9.3335165 | G21: 0.17993554
A22: 设计院 | B22: 5.0827682 | C22: 0.0323 | D22: 4.6169183 | E22: 0.0407 | F22: 0.58484618 | G22: 0.0312
A23: 铁通公司 | B23: 131.13078 | C23: 0.0274 | D23: 131.36257 | E23: 0.006 | F23: 0.64833377 | G23: -0.5531
A24: 在线营销服务中心 | B24: 31.423366 | C24: 0.10971827 | D24: 31.610534 | E24: 0.095934804 | F24: -0.15206614 | G24: -0.56711298
A25: 二、基础支撑
A26: 研究院 | B26: - | C26: - | D26: 2.4282656 | E26: 0.1868046 | F26: - | G26: -
A27: 移动党校 | B27: - | C27: - | D27: 0.28013301 | E27: 0.69997292 | F27: - | G27: -
A28: 信息港中心 | B28: - | C28: - | D28: 0.48153592 | E28: 0.0025819891 | F28: - | G28: -
A29: 香港机构 | B29: - | C29: - | D29: 0.086230119 | E29: -0.21296731 | F29: - | G29: -
A30: 信息安全中心 | B30: - | C30: - | D30: 0.38340518 | E30: 0.74159107 | F30: - | G30: -
A31: 供应链管理中心 | B31: - | C31: - | D31: 0.17625742 | E31: 0.00027391596 | F31: - | G31: -
A32: 三、经营事业部
A33: 政企事业部 | B33: 2.4581529 | C33: -0.17646276 | D33: 1.8673475 | E33: -0.31725269 | F33: 0.62244415 | G33: -
A34: 网络事业部 | B34: - | C34: - | D34: 0.81943 | E34: 1.3 | F34: - | G34: -
A35: 注：本表为各单位自身报表数据，含有多账套的为合并拼销后的数据
A36: =金科、信息技术中心!A51+1 -> 60

Sheet 集团公司人员和薪酬情况表
C1: 集团公司人员和薪酬情况表
C2: =主要经营情况表!A2 -> 45323
C3: 指标名称 | D3: 单位 | E3: 本年累计 | F3: 上年同期 | G3: 同比增幅
A4: NG1100 | C4: 一、人员情况
A5: NM1105 | C5: 1. 全部从业人员 | D5: 人 | E5: 478629 | F5: 478817 | G5: -0.00039263435
A6: NM1106 | C6: 其中：在岗职工 | D6: 人 | E6: 451366 | F6: 450244 | G6: 0.0024919821
A7: NM1107 | C7: 其他从业人员 | D7: 人 | E7: 27263 | F7: 28573 | G7: -0.045847478
C8: 其中：数智化新型人才 | D8: 人 | E8: 180332 | F8: 166703 | G8: 0.081756177
C9: 其中：研发人员 | D9: 人 | E9: 48175 | F9: - | G9: -
A10: NM1205 | C10: 2. 内退职工 | D10: 人 | E10: 965 | F10: 1215 | G10: -0.20576132
A11: NM1206 | C11: 3. 离退休人员 | D11: 人 | E11: 78769 | F11: 73874 | G11: 0.066261472
C12: 4.数字员工 | D12: 人 | E12: 30090 | F12: - | G12: -
A13: NM1207 | C13: 二、薪酬情况
A14: NM1210 | C14: 雇员薪酬及相关成本 | D14: 亿元 | E14: 235.96013 | F14: 211.88213 | G14: 0.11363864
A15: NM4210 | C15: —工资总额 | D15: 亿元 | E15: 162.63851 | F15: 145.9166 | G15: 0.11459913
A16: NG1510 | C16: —劳务费 | D16: 亿元 | E16: 5.7146366 | F16: 5.829327 | G16: -0.019674725
C17: 注：1.集团公司人员和薪酬为全集团口径，包括境内、境外机构，不含福建诺基亚
C18: 公司707人(全部为在岗职工)
C19: 2.数智化新型人才是指适应公司数智化转型发展需要，从事数智化产品和服务的
C20: 规划、研发、运维、产品、内容等方面工作，并具备相关知识能力素质的专业人才,
C21: 当前公司的数字化新型人才重点集中在连接、算力、能力、网络信息安全领域
C22: 3.数字员工是融合RPA、大模型等数字化技术的软件机器人，具备智能识别、分析、
C23: 决策、生成和自动执行等能力，能够代替人类员工跨系统、跨应用自动一体完成某项
C24: 任务和工作
C25: =其他单位主要财务指标情况表!A36+1 -> 61

Sheet KPI指标表（国内口径）
A1: 集团公司主要情况表
A2: =主要经营情况表!A2 -> 45323
A3: 指标 | B3: 单位 | C3: 本月 | D3: 本年累计/ （或本年到达） | E3: 上年同期/ （或上年到达） | F3: 比上年同期±
A4: 移动电话客户数 | B4: 万户 | C4: - | D4: 103887.2 | E4: 102474.9 | F4: 0.013781911
A5: 其中：净增客户数 | B5: 万户 | C5: -11.4 | D5: 70.4 | E5: 431.3 | F5: -0.83677255
A6: 其中：5G客户数 | B6: 万户 | C6: - | D6: 47238.967 | E6: 34306.683 | F6: 0.37696107
A7: 净增5G客户数 | B7: 万户 | C7: 827.4312 | D7: 987.0335 | E7: 1741.9198 | F7: -0.43336456
A8: 固定电话客户数 | B8: 万户 | C8: - | D8: 2204.1 | E8: 2189.7 | F8: 0.0065762433
A9: 其中：净增客户数 | B9: 万户 | C9: -11.3 | D9: -10 | E9: -5.5 | F9: -
A10: 固定互联网宽带客户数 | B10: 万户 | C10: - | D10: 30237.3 | E10: 27764.1 | F10: 0.089079063
A11: 个人上网客户数 | B11: 万户 | C11: - | D11: 91253.6 | E11: 89843.5 | F11: 0.01569507
A12: 移动电话计费时长 | B12: 亿分钟 | C12: 2140.9 | D12: 4617.7 | E12: 4902.4 | F12: -0.058073597
A13: 短彩信业务计费量 | B13: 亿条 | C13: 741 | D13: 1581.5 | E13: 1580.2 | F13: 0.00082268067
A14: 固定电话计费时长 | B14: 亿分钟 | C14: 12.3 | D14: 31.1 | E14: 27.5 | F14: 0.13090909
A15: 5G基站数 | B15: 万个 | C15: 1.5103 | D15: 200.2598 | E15: 132.3496 | F15: 0.51311224
A16: 固定资产投资完成额 | B16: 亿元 | C16: 41.2329 | D16: 171.6796 | E16: 172.4451 | F16: -0.0044390939
A17: 其中：5G投资额 | B17: 亿元 | C17: 20.5 | D17: 85.8 | E17: 93.8 | F17: -0.085287846
A18: ARPU值 | B18: 元/户/月 | C18: 59 | D18: 55.8 | E18: 56 | F18: -0.0035714286
A19: 移动电话ARPU | B19: 元/户/月 | C19: 50.893914 | D19: 47.272807 | E19: 48.091173 | F19: -0.017016972
A20: 营业收入 | B20: 亿元 | C20: 888.2355 | D20: 1789.4059 | E20: 1706.0074 | F20: 0.048885192
A21: 其中：主营业务收入 | B21: 亿元 | C21: 765.45457 | D21: 1493.6342 | E21: 1431.6477 | F21: 0.043297314
A22: 成本费用 | B22: 亿元 | C22: 767.5117 | D22: 1560.0241 | E22: 1493.7109 | F22: 0.044394936
A23: 其中：营业成本 | B23: 亿元 | C23: 736.1415 | D23: 1366.5431 | E23: 1322.4103 | F23: 0.033373001
... A26: 管理费用 | B26: 亿元 | C26: 43.1752 | D26: 82.734 | E26: 80.7665 | F26: 0.024360347
A27: 财务费用 | B27: 亿元 | C27: -2.0775 | D27: -3.926 | E27: -6.8571 | F27: -
A28: 利润总额 | B28: 亿元 | C28: 131.0813 | D28: 224.3543 | E28: 222.1506 | F28: 0.0099198472
A29: 净利润 | B29: 亿元 | C29: 101.0457 | D29: 173.6376 | E29: 170.4389 | F29: 0.018767429
A30: 资产总额 | B30: 亿元 | C30: - | D30: 24133.791 | E30: 23127.917 | F30: 0.04349179
A31: 负债总额 | B31: 亿元 | C31: - | D31: 6757.2739 | E31: 6827.4268 | F31: -0.01027516
A32: 所有者权益 | B32: 亿元 | C32: - | D32: 17376.517 | E32: 16300.49 | F32: 0.066011967
A33: 资产负债率 | B33: % | C33: - | D33: 0.27999222 | E33: 0.29520284 | F33: -1.5210619
A34: 净资产收益率 | B34: % | C34: - | D34: 0.061614731 | E34: 0.065257926 | F34: -0.36431951
A35: 研发经费投入强度 | B35: % | C35: - | D35: 0.013317381 | E35: 0.030099987 | F35: -1.6782606
A36: 全员劳动生产率 | B36: 万元/人/年 | C36: - | D36: 104.07224 | E36: 100.86455 | F36: 0.031801999
A37: 营业现金比率 | B37: % | C37: - | D37: 0.14223933 | E37: 0.28144169 | F37: -13.920235
A38: 产业数字化收入占比 | B38: % | C38: - | D38: 0.12746718 | E38: 0.12161653 | F38: 0.58506571
A39: 注：1.5G客户数、5G基站数为内地31省数据，其余指标为集团公司数据
A40: 2.ARPU值=主营业务收入/(固定电话客户数+移动电话客户数)
A41: =集团公司人员和薪酬情况表!C25+1 -> 62
